Workbook

Sheet DET_ASIG
A1: ID_ASIG_CAM_DET | B1: ID_CARRERA | C1: NOMBRE_CARRERA | D1: NIVEL | E1: ASIGNATURA | F1: ID_ASIG | G1: DETALLADO | H1: ID_DETALLADO
A2: 1 | B2: FCACC-CO-AD | C2: =_xlfn.XLOOKUP(TAB_H_ASIG_CON_DET[[#This Row],[ID_CARRERA]],MAE_CARRERA[ID_CARRERA],MAE_CARRERA[NOMBRE_CARRERA],"Seleccione ID Carrera") -> CONTABILIDAD Y AUDITORÍA 2024 NS | D2: 1 | E2: MATEMÁTICA | F2: =_xlfn.XLOOKUP(TAB_H_ASIG_CON_DET[[#This Row],[ASIGNATURA]],MAE_ASIGNATURA[NOM_ASIG],MAE_ASIGNATURA[ID_ASIG],"Seleccione Asignatura") -> FCACC-CO-EX-NI-1-MATEM | G2: UNIDAD BASICA | H2: =_xlfn.XLOOKUP(TAB_H_ASIG_CON_DET[[#This Row],[DETALLADO]],MAE_CONOCIMIENTO[CAMPO_DETALLADO],MAE_CONOCIMIENTO[ID_DDETALLADO],"Seleccione Campo Detallado") -> F-C-D-UNI-BAS
A3: 2 | B3: FCACC-CO-AD | C3: =_xlfn.XLOOKUP(TAB_H_ASIG_CON_DET[[#This Row],[ID_CARRERA]],MAE_CARRERA[ID_CARRERA],MAE_CARRERA[NOMBRE_CARRERA],"Seleccione ID Carrera") -> CONTABILIDAD Y AUDITORÍA 2024 NS | D3: 1 | E3: CONTABILIDAD BÁSICA | F3: =_xlfn.XLOOKUP(TAB_H_ASIG_CON_DET[[#This Row],[ASIGNATURA]],MAE_ASIGNATURA[NOM_ASIG],MAE_ASIGNATURA[ID_ASIG],"Seleccione Asignatura") -> FCACC-CO-AD-NI-1-CONTA-BÁS | G3: UNIDAD BASICA | H3: =_xlfn.XLOOKUP(TAB_H_ASIG_CON_DET[[#This Row],[DETALLADO]],MAE_CONOCIMIENTO[CAMPO_DETALLADO],MAE_CONOCIMIENTO[ID_DDETALLADO],"Seleccione Campo Detallado") -> F-C-D-UNI-BAS
A4: 3 | B4: FCACC-CO-AD | C4: =_xlfn.XLOOKUP(TAB_H_ASIG_CON_DET[[#This Row],[ID_CARRERA]],MAE_CARRERA[ID_CARRERA],MAE_CARRERA[NOMBRE_CARRERA],"Seleccione ID Carrera") -> CONTABILIDAD Y AUDITORÍA 2024 NS | D4: 1 | E4: METODOLOGÍA DE LA INVESTIGACIÓN | F4: =_xlfn.XLOOKUP(TAB_H_ASIG_CON_DET[[#This Row],[ASIGNATURA]],MAE_ASIGNATURA[NOM_ASIG],MAE_ASIGNATURA[ID_ASIG],"Seleccione Asignatura") -> FCACC-AD-EM-NI-1-METOD-DE -LA | G4: UNIDAD BASICA | H4: =_xlfn.XLOOKUP(TAB_H_ASIG_CON_DET[[#This Row],[DETALLADO]],MAE_CONOCIMIENTO[CAMPO_DETALLADO],MAE_CONOCIMIENTO[ID_DDETALLADO],"Seleccione Campo Detallado") -> F-C-D-UNI-BAS
A5: 4 | B5: FCACC-CO-AD | C5: =_xlfn.XLOOKUP(TAB_H_ASIG_CON_DET[[#This Row],[ID_CARRERA]],MAE_CARRERA[ID_CARRERA],MAE_CARRERA[NOMBRE_CARRERA],"Seleccione ID Carrera") -> CONTABILIDAD Y AUDITORÍA 2024 NS | D5: 1 | E5: ADMINISTRACIÓN | F5: =_xlfn.XLOOKUP(TAB_H_ASIG_CON_DET[[#This Row],[ASIGNATURA]],MAE_ASIGNATURA[NOM_ASIG],MAE_ASIGNATURA[ID_ASIG],"Seleccione Asignatura") -> FCACC-CO-AD-NI-1-ADMIN | G5: UNIDAD BASICA | H5: =_xlfn.XLOOKUP(TAB_H_ASIG_CON_DET[[#This Row],[DETALLADO]],MAE_CONOCIMIENTO[CAMPO_DETALLADO],MAE_CONOCIMIENTO[ID_DDETALLADO],"Seleccione Campo Detallado") -> F-C-D-UNI-BAS
A6: 5 | B6: FCACC-CO-AD | C6: =_xlfn.XLOOKUP(TAB_H_ASIG_CON_DET[[#This Row],[ID_CARRERA]],MAE_CARRERA[ID_CARRERA],MAE_CARRERA[NOMBRE_CARRERA],"Seleccione ID Carrera") -> CONTABILIDAD Y AUDITORÍA 2024 NS | D6: 1 | E6: MACROECONOMÍA | F6: =_xlfn.XLOOKUP(TAB_H_ASIG_CON_DET[[#This Row],[ASIGNATURA]],MAE_ASIGNATURA[NOM_ASIG],MAE_ASIGNATURA[ID_ASIG],"Seleccione Asignatura") -> FCACC-AD-EM-NI-2-MACRO | G6: UNIDAD BASICA | H6: =_xlfn.XLOOKUP(TAB_H_ASIG_CON_DET[[#This Row],[DETALLADO]],MAE_CONOCIMIENTO[CAMPO_DETALLADO],MAE_CONOCIMIENTO[ID_DDETALLADO],"Seleccione Campo Detallado") -> F-C-D-UNI-BAS
A7: 6 | B7: FCACC-CO-AD | C7: =_xlfn.XLOOKUP(TAB_H_ASIG_CON_DET[[#This Row],[ID_CARRERA]],MAE_CARRERA[ID_CARRERA],MAE_CARRERA[NOMBRE_CARRERA],"Seleccione ID Carrera") -> CONTABILIDAD Y AUDITORÍA 2024 NS | D7: 2 | E7: LEGISLACIÓN LABORAL | F7: =_xlfn.XLOOKUP(TAB_H_ASIG_CON_DET[[#This Row],[ASIGNATURA]],MAE_ASIGNATURA[NOM_ASIG],MAE_ASIGNATURA[ID_ASIG],"Seleccione Asignatura") -> FCACC-AU-CO-GE-NI-2-LEGIS-LAB | G7: UNIDAD BASICA | H7: =_xlfn.XLOOKUP(TAB_H_ASIG_CON_DET[[#This Row],[DETALLADO]],MAE_CONOCIMIENTO[CAMPO_DETALLADO],MAE_CONOCIMIENTO[ID_DDETALLADO],"Seleccione Campo Detallado") -> F-C-D-UNI-BAS
A8: 7 | B8: FCACC-CO-AD | C8: =_xlfn.XLOOKUP(TAB_H_ASIG_CON_DET[[#This Row],[ID_CARRERA]],MAE_CARRERA[ID_CARRERA],MAE_CARRERA[NOMBRE_CARRERA],"Seleccione ID Carrera") -> CONTABILIDAD Y AUDITORÍA 2024 NS | D8: 2 | E8: LEGISLACIÓN MERCANTIL Y SOCIETARIA | F8: =_xlfn.XLOOKUP(TAB_H_ASIG_CON_DET[[#This Row],[ASIGNATURA]],MAE_ASIGNATURA[NOM_ASIG],MAE_ASIGNATURA[ID_ASIG],"Seleccione Asignatura") -> FCACC-CO-AD-NI-2-LEGIS-MER-Y | G8: UNIDAD BASICA | H8: =_xlfn.XLOOKUP(TAB_H_ASIG_CON_DET[[#This Row],[DETALLADO]],MAE_CONOCIMIENTO[CAMPO_DETALLADO],MAE_CONOCIMIENTO[ID_DDETALLADO],"Seleccione Campo Detallado") -> F-C-D-UNI-BAS
A9: 8 | B9: FCACC-CO-AD | C9: =_xlfn.XLOOKUP(TAB_H_ASIG_CON_DET[[#This Row],[ID_CARRERA]],MAE_CARRERA[ID_CARRERA],MAE_CARRERA[NOMBRE_CARRERA],"Seleccione ID Carrera") -> CONTABILIDAD Y AUDITORÍA 2024 NS | D9: 2 | E9: CONTABILIDAD INTERMEDIA | F9: =_xlfn.XLOOKUP(TAB_H_ASIG_CON_DET[[#This Row],[ASIGNATURA]],MAE_ASIGNATURA[NOM_ASIG],MAE_ASIGNATURA[ID_ASIG],"Seleccione Asignatura") -> FCACC-CO-AD-NI-2-CONTA-INT | G9: UNIDAD BASICA | H9: =_xlfn.XLOOKUP(TAB_H_ASIG_CON_DET[[#This Row],[DETALLADO]],MAE_CONOCIMIENTO[CAMPO_DETALLADO],MAE_CONOCIMIENTO[ID_DDETALLADO],"Seleccione Campo Detallado") -> F-C-D-UNI-BAS
A10: 9 | B10: FCACC-CO-AD | C10: =_xlfn.XLOOKUP(TAB_H_ASIG_CON_DET[[#This Row],[ID_CARRERA]],MAE_CARRERA[ID_CARRERA],MAE_CARRERA[NOMBRE_CARRERA],"Seleccione ID Carrera") -> CONTABILIDAD Y AUDITORÍA 2024 NS | D10: 2 | E10: MATEMÁTICA FINANCIERA | F10: =_xlfn.XLOOKUP(TAB_H_ASIG_CON_DET[[#This Row],[ASIGNATURA]],MAE_ASIGNATURA[NOM_ASIG],MAE_ASIGNATURA[ID_ASIG],"Seleccione Asignatura") -> FCACC-AD-EM-NI-2-MATEM-FIN | G10: UNIDAD BASICA | H10: =_xlfn.XLOOKUP(TAB_H_ASIG_CON_DET[[#This Row],[DETALLADO]],MAE_CONOCIMIENTO[CAMPO_DETALLADO],MAE_CONOCIMIENTO[ID_DDETALLADO],"Seleccione Campo Detallado") -> F-C-D-UNI-BAS
A11: 10 | B11: FCACC-CO-AD | C11: =_xlfn.XLOOKUP(TAB_H_ASIG_CON_DET[[#This Row],[ID_CARRERA]],MAE_CARRERA[ID_CARRERA],MAE_CARRERA[NOMBRE_CARRERA],"Seleccione ID Carrera") -> CONTABILIDAD Y AUDITORÍA 2024 NS | D11: 2 | E11: ESTADÍSTICA DESCRIPTIVA | F11: =_xlfn.XLOOKUP(TAB_H_ASIG_CON_DET[[#This Row],[ASIGNATURA]],MAE_ASIGNATURA[NOM_ASIG],MAE_ASIGNATURA[ID_ASIG],"Seleccione Asignatura") -> FCACC-AU-CO-GE-NI-1-ESTAD-DES | G11: UNIDAD BASICA | H11: =_xlfn.XLOOKUP(TAB_H_ASIG_CON_DET[[#This Row],[DETALLADO]],MAE_CONOCIMIENTO[CAMPO_DETALLADO],MAE_CONOCIMIENTO[ID_DDETALLADO],"Seleccione Campo Detallado") -> F-C-D-UNI-BAS
A12: 11 | B12: FCACC-CO-AD | C12: =_xlfn.XLOOKUP(TAB_H_ASIG_CON_DET[[#This Row],[ID_CARRERA]],MAE_CARRERA[ID_CARRERA],MAE_CARRERA[NOMBRE_CARRERA],"Seleccione ID Carrera") -> CONTABILIDAD Y AUDITORÍA 2024 NS | D12: 3 | E12: ESTADÍSTICA APLICADA | F12: =_xlfn.XLOOKUP(TAB_H_ASIG_CON_DET[[#This Row],[ASIGNATURA]],MAE_ASIGNATURA[NOM_ASIG],MAE_ASIGNATURA[ID_ASIG],"Seleccione Asignatura") -> FCACC-CO-AD-NI-3-ESTAD-APL | G12: UNIDAD BASICA | H12: =_xlfn.XLOOKUP(TAB_H_ASIG_CON_DET[[#This Row],[DETALLADO]],MAE_CONOCIMIENTO[CAMPO_DETALLADO],MAE_CONOCIMIENTO[ID_DDETALLADO],"Seleccione Campo Detallado") -> F-C-D-UNI-BAS
A13: 12 | B13: FCACC-CO-AD | C13: =_xlfn.XLOOKUP(TAB_H_ASIG_CON_DET[[#This Row],[ID_CARRERA]],MAE_CARRERA[ID_CARRERA],MAE_CARRERA[NOMBRE_CARRERA],"Seleccione ID Carrera") -> CONTABILIDAD Y AUDITORÍA 2024 NS | D13: 3 | E13: CONTABILIDAD AVANZADA | F13: =_xlfn.XLOOKUP(TAB_H_ASIG_CON_DET[[#This Row],[ASIGNATURA]],MAE_ASIGNATURA[NOM_ASIG],MAE_ASIGNATURA[ID_ASIG],"Seleccione Asignatura") -> FCACC-CO-AD-NI-3-CONTA-AVA | G13: UNIDAD BASICA | H13: =_xlfn.XLOOKUP(TAB_H_ASIG_CON_DET[[#This Row],[DETALLADO]],MAE_CONOCIMIENTO[CAMPO_DETALLADO],MAE_CONOCIMIENTO[ID_DDETALLADO],"Seleccione Campo Detallado") -> F-C-D-UNI-BAS
... A45: 59 | B45: FCACC-CO-AD | C45: =_xlfn.XLOOKUP(TAB_H_ASIG_CON_DET[[#This Row],[ID_CARRERA]],MAE_CARRERA[ID_CARRERA],MAE_CARRERA[NOMBRE_CARRERA],"Seleccione ID Carrera") -> CONTABILIDAD Y AUDITORÍA 2024 NS | D45: 6 | E45: INVESTIGACIÓN OPERATIVA | F45: =_xlfn.XLOOKUP(TAB_H_ASIG_CON_DET[[#This Row],[ASIGNATURA]],MAE_ASIGNATURA[NOM_ASIG],MAE_ASIGNATURA[ID_ASIG],"Seleccione Asignatura") -> FCACC-CO-EX-NI-4-INVES-OPE | G45: NEGOCIOS INTERNACIONALES | H45: =_xlfn.XLOOKUP(TAB_H_ASIG_CON_DET[[#This Row],[DETALLADO]],MAE_CONOCIMIENTO[CAMPO_DETALLADO],MAE_CONOCIMIENTO[ID_DDETALLADO],"Seleccione Campo Detallado") -> F-C-D-NEG-INT
A46: 60 | B46: FCACC-CO-AD | C46: =_xlfn.XLOOKUP(TAB_H_ASIG_CON_DET[[#This Row],[ID_CARRERA]],MAE_CARRERA[ID_CARRERA],MAE_CARRERA[NOMBRE_CARRERA],"Seleccione ID Carrera") -> CONTABILIDAD Y AUDITORÍA 2024 NS | D46: 7 | E46: AUDITORÍA TRIBUTARIA | F46: =_xlfn.XLOOKUP(TAB_H_ASIG_CON_DET[[#This Row],[ASIGNATURA]],MAE_ASIGNATURA[NOM_ASIG],MAE_ASIGNATURA[ID_ASIG],"Seleccione Asignatura") -> FCACC-AU-CO-GE-NI-6-AUDIT-TRI | H46: =_xlfn.XLOOKUP(TAB_H_ASIG_CON_DET[[#This Row],[DETALLADO]],MAE_CONOCIMIENTO[CAMPO_DETALLADO],MAE_CONOCIMIENTO[ID_DDETALLADO],"Seleccione Campo Detallado") -> F-C-D-
A47: 61 | B47: FCACC-CO-AD | C47: =_xlfn.XLOOKUP(TAB_H_ASIG_CON_DET[[#This Row],[ID_CARRERA]],MAE_CARRERA[ID_CARRERA],MAE_CARRERA[NOMBRE_CARRERA],"Seleccione ID Carrera") -> CONTABILIDAD Y AUDITORÍA 2024 NS | D47: 7 | E47: AUDITORÍA DE CALIDAD | F47: =_xlfn.XLOOKUP(TAB_H_ASIG_CON_DET[[#This Row],[ASIGNATURA]],MAE_ASIGNATURA[NOM_ASIG],MAE_ASIGNATURA[ID_ASIG],"Seleccione Asignatura") -> FCACC-CO-AD-NI-7-AUDIT-DE -CAL | H47: =_xlfn.XLOOKUP(TAB_H_ASIG_CON_DET[[#This Row],[DETALLADO]],MAE_CONOCIMIENTO[CAMPO_DETALLADO],MAE_CONOCIMIENTO[ID_DDETALLADO],"Seleccione Campo Detallado") -> F-C-D-
A48: 62 | B48: FCACC-CO-AD | C48: =_xlfn.XLOOKUP(TAB_H_ASIG_CON_DET[[#This Row],[ID_CARRERA]],MAE_CARRERA[ID_CARRERA],MAE_CARRERA[NOMBRE_CARRERA],"Seleccione ID Carrera") -> CONTABILIDAD Y AUDITORÍA 2024 NS | D48: 7 | E48: AUDITORÍA GUBERNAMENTAL | F48: =_xlfn.XLOOKUP(TAB_H_ASIG_CON_DET[[#This Row],[ASIGNATURA]],MAE_ASIGNATURA[NOM_ASIG],MAE_ASIGNATURA[ID_ASIG],"Seleccione Asignatura") -> FCACC-CO-AD-NI-7-AUDIT-GUB | H48: =_xlfn.XLOOKUP(TAB_H_ASIG_CON_DET[[#This Row],[DETALLADO]],MAE_CONOCIMIENTO[CAMPO_DETALLADO],MAE_CONOCIMIENTO[ID_DDETALLADO],"Seleccione Campo Detallado") -> F-C-D-
A49: 63 | B49: FCACC-CO-AD | C49: =_xlfn.XLOOKUP(TAB_H_ASIG_CON_DET[[#This Row],[ID_CARRERA]],MAE_CARRERA[ID_CARRERA],MAE_CARRERA[NOMBRE_CARRERA],"Seleccione ID Carrera") -> CONTABILIDAD Y AUDITORÍA 2024 NS | D49: 8 | E49: EVALUACIÓN DE PROYECTOS SOCIALES Y PRODUACTIVOS | F49: =_xlfn.XLOOKUP(TAB_H_ASIG_CON_DET[[#This Row],[ASIGNATURA]],MAE_ASIGNATURA[NOM_ASIG],MAE_ASIGNATURA[ID_ASIG],"Seleccione Asignatura") -> FCACC-CO-AD-NI-7-EVALU-DE -PRO | H49: =_xlfn.XLOOKUP(TAB_H_ASIG_CON_DET[[#This Row],[DETALLADO]],MAE_CONOCIMIENTO[CAMPO_DETALLADO],MAE_CONOCIMIENTO[ID_DDETALLADO],"Seleccione Campo Detallado") -> F-C-D-
A50: 64 | B50: FCACC-CO-AD | C50: =_xlfn.XLOOKUP(TAB_H_ASIG_CON_DET[[#This Row],[ID_CARRERA]],MAE_CARRERA[ID_CARRERA],MAE_CARRERA[NOMBRE_CARRERA],"Seleccione ID Carrera") -> CONTABILIDAD Y AUDITORÍA 2024 NS | D50: 7 | E50: EVALUACIÓN DE PROYECTOS SOCIALES Y PRODUACTIVOS | F50: =_xlfn.XLOOKUP(TAB_H_ASIG_CON_DET[[#This Row],[ASIGNATURA]],MAE_ASIGNATURA[NOM_ASIG],MAE_ASIGNATURA[ID_ASIG],"Seleccione Asignatura") -> FCACC-CO-AD-NI-7-EVALU-DE -PRO | H50: =_xlfn.XLOOKUP(TAB_H_ASIG_CON_DET[[#This Row],[DETALLADO]],MAE_CONOCIMIENTO[CAMPO_DETALLADO],MAE_CONOCIMIENTO[ID_DDETALLADO],"Seleccione Campo Detallado") -> F-C-D-
A51: 65 | B51: FCACC-8-TITU | C51: =_xlfn.XLOOKUP(TAB_H_ASIG_CON_DET[[#This Row],[ID_CARRERA]],MAE_CARRERA[ID_CARRERA],MAE_CARRERA[NOMBRE_CARRERA],"Seleccione ID Carrera") -> Titulación | D51: 7 | E51: Trabajo de integración curricular: Fase de diseño CA-24 | F51: =_xlfn.XLOOKUP(TAB_H_ASIG_CON_DET[[#This Row],[ASIGNATURA]],MAE_ASIGNATURA[NOM_ASIG],MAE_ASIGNATURA[ID_ASIG],"Seleccione Asignatura") -> FCACC-8-TITU-NI-7-Traba-de -int | G51: CONTABILIDAD Y AUDITORÍA | H51: =_xlfn.XLOOKUP(TAB_H_ASIG_CON_DET[[#This Row],[DETALLADO]],MAE_CONOCIMIENTO[CAMPO_DETALLADO],MAE_CONOCIMIENTO[ID_DDETALLADO],"Seleccione Campo Detallado") -> F-C-D-CON-Y A-AUD
A52: 66 | B52: FCACC-8-TITU | C52: =_xlfn.XLOOKUP(TAB_H_ASIG_CON_DET[[#This Row],[ID_CARRERA]],MAE_CARRERA[ID_CARRERA],MAE_CARRERA[NOMBRE_CARRERA],"Seleccione ID Carrera") -> Titulación | D52: 7 | E52: Trabajo de integración curricular: Fase de diseño CA-24 | F52: =_xlfn.XLOOKUP(TAB_H_ASIG_CON_DET[[#This Row],[ASIGNATURA]],MAE_ASIGNATURA[NOM_ASIG],MAE_ASIGNATURA[ID_ASIG],"Seleccione Asignatura") -> FCACC-8-TITU-NI-7-Traba-de -int | G52: GESTIÓN FINANCIERA | H52: =_xlfn.XLOOKUP(TAB_H_ASIG_CON_DET[[#This Row],[DETALLADO]],MAE_CONOCIMIENTO[CAMPO_DETALLADO],MAE_CONOCIMIENTO[ID_DDETALLADO],"Seleccione Campo Detallado") -> F-C-D-GES-FIN
A53: 67 | B53: FCACC-8-TITU | C53: =_xlfn.XLOOKUP(TAB_H_ASIG_CON_DET[[#This Row],[ID_CARRERA]],MAE_CARRERA[ID_CARRERA],MAE_CARRERA[NOMBRE_CARRERA],"Seleccione ID Carrera") -> Titulación | D53: 7 | E53: Trabajo de integración curricular: Fase de diseño CA-24 | F53: =_xlfn.XLOOKUP(TAB_H_ASIG_CON_DET[[#This Row],[ASIGNATURA]],MAE_ASIGNATURA[NOM_ASIG],MAE_ASIGNATURA[ID_ASIG],"Seleccione Asignatura") -> FCACC-8-TITU-NI-7-Traba-de -int | G53: ADMINISTRACIÓN | H53: =_xlfn.XLOOKUP(TAB_H_ASIG_CON_DET[[#This Row],[DETALLADO]],MAE_CONOCIMIENTO[CAMPO_DETALLADO],MAE_CONOCIMIENTO[ID_DDETALLADO],"Seleccione Campo Detallado") -> F-C-D-ADM
A54: 68 | B54: FCACC-8-TITU | C54: =_xlfn.XLOOKUP(TAB_H_ASIG_CON_DET[[#This Row],[ID_CARRERA]],MAE_CARRERA[ID_CARRERA],MAE_CARRERA[NOMBRE_CARRERA],"Seleccione ID Carrera") -> Titulación | D54: 7 | E54: Trabajo de integración curricular: Fase de diseño CA-22 | F54: =_xlfn.XLOOKUP(TAB_H_ASIG_CON_DET[[#This Row],[ASIGNATURA]],MAE_ASIGNATURA[NOM_ASIG],MAE_ASIGNATURA[ID_ASIG],"Seleccione Asignatura") -> FCACC-8-TITU-NI-7-Traba-de -int | G54: CONTABILIDAD Y AUDITORÍA | H54: =_xlfn.XLOOKUP(TAB_H_ASIG_CON_DET[[#This Row],[DETALLADO]],MAE_CONOCIMIENTO[CAMPO_DETALLADO],MAE_CONOCIMIENTO[ID_DDETALLADO],"Seleccione Campo Detallado") -> F-C-D-CON-Y A-AUD
A55: 69 | B55: FCACC-8-TITU | C55: =_xlfn.XLOOKUP(TAB_H_ASIG_CON_DET[[#This Row],[ID_CARRERA]],MAE_CARRERA[ID_CARRERA],MAE_CARRERA[NOMBRE_CARRERA],"Seleccione ID Carrera") -> Titulación | D55: 7 | E55: Trabajo de integración curricular: Fase de diseño CA-22 | F55: =_xlfn.XLOOKUP(TAB_H_ASIG_CON_DET[[#This Row],[ASIGNATURA]],MAE_ASIGNATURA[NOM_ASIG],MAE_ASIGNATURA[ID_ASIG],"Seleccione Asignatura") -> FCACC-8-TITU-NI-7-Traba-de -int | G55: GESTIÓN FINANCIERA | H55: =_xlfn.XLOOKUP(TAB_H_ASIG_CON_DET[[#This Row],[DETALLADO]],MAE_CONOCIMIENTO[CAMPO_DETALLADO],MAE_CONOCIMIENTO[ID_DDETALLADO],"Seleccione Campo Detallado") -> F-C-D-GES-FIN
A56: 70 | B56: FCACC-8-TITU | C56: =_xlfn.XLOOKUP(TAB_H_ASIG_CON_DET[[#This Row],[ID_CARRERA]],MAE_CARRERA[ID_CARRERA],MAE_CARRERA[NOMBRE_CARRERA],"Seleccione ID Carrera") -> Titulación | D56: 7 | E56: Trabajo de integración curricular: Fase de diseño CA-22 | F56: =_xlfn.XLOOKUP(TAB_H_ASIG_CON_DET[[#This Row],[ASIGNATURA]],MAE_ASIGNATURA[NOM_ASIG],MAE_ASIGNATURA[ID_ASIG],"Seleccione Asignatura") -> FCACC-8-TITU-NI-7-Traba-de -int | G56: ADMINISTRACIÓN | H56: =_xlfn.XLOOKUP(TAB_H_ASIG_CON_DET[[#This Row],[DETALLADO]],MAE_CONOCIMIENTO[CAMPO_DETALLADO],MAE_CONOCIMIENTO[ID_DDETALLADO],"Seleccione Campo Detallado") -> F-C-D-ADM
A57: 71 | B57: FCACC-CO-AD | C57: =_xlfn.XLOOKUP(TAB_H_ASIG_CON_DET[[#This Row],[ID_CARRERA]],MAE_CARRERA[ID_CARRERA],MAE_CARRERA[NOMBRE_CARRERA],"Seleccione ID Carrera") -> CONTABILIDAD Y AUDITORÍA 2024 NS | D57: 8 | E57: AUDITORÍA FORENSE | F57: =_xlfn.XLOOKUP(TAB_H_ASIG_CON_DET[[#This Row],[ASIGNATURA]],MAE_ASIGNATURA[NOM_ASIG],MAE_ASIGNATURA[ID_ASIG],"Seleccione Asignatura") -> FCACC-AU-CO-GE-NI-8-AUDIT-FOR | G57: CONTABILIDAD Y AUDITORÍA | H57: =_xlfn.XLOOKUP(TAB_H_ASIG_CON_DET[[#This Row],[DETALLADO]],MAE_CONOCIMIENTO[CAMPO_DETALLADO],MAE_CONOCIMIENTO[ID_DDETALLADO],"Seleccione Campo Detallado") -> F-C-D-CON-Y A-AUD
A58: 72 | B58: FCACC-CO-AD | C58: =_xlfn.XLOOKUP(TAB_H_ASIG_CON_DET[[#This Row],[ID_CARRERA]],MAE_CARRERA[ID_CARRERA],MAE_CARRERA[NOMBRE_CARRERA],"Seleccione ID Carrera") -> CONTABILIDAD Y AUDITORÍA 2024 NS | D58: 8 | E58: AUDITORÍA DE GESTIÓN | F58: =_xlfn.XLOOKUP(TAB_H_ASIG_CON_DET[[#This Row],[ASIGNATURA]],MAE_ASIGNATURA[NOM_ASIG],MAE_ASIGNATURA[ID_ASIG],"Seleccione Asignatura") -> FCACC-AU-CO-GE-NI-6-AUDIT-DE -GES | G58: CONTABILIDAD Y AUDITORÍA | H58: =_xlfn.XLOOKUP(TAB_H_ASIG_CON_DET[[#This Row],[DETALLADO]],MAE_CONOCIMIENTO[CAMPO_DETALLADO],MAE_CONOCIMIENTO[ID_DDETALLADO],"Seleccione Campo Detallado") -> F-C-D-CON-Y A-AUD
A59: 73 | B59: FCACC-CO-AD | C59: =_xlfn.XLOOKUP(TAB_H_ASIG_CON_DET[[#This Row],[ID_CARRERA]],MAE_CARRERA[ID_CARRERA],MAE_CARRERA[NOMBRE_CARRERA],"Seleccione ID Carrera") -> CONTABILIDAD Y AUDITORÍA 2024 NS | D59: 8 | E59: PROCESO DE CONTRATACIÓN PÚBLICA | F59: =_xlfn.XLOOKUP(TAB_H_ASIG_CON_DET[[#This Row],[ASIGNATURA]],MAE_ASIGNATURA[NOM_ASIG],MAE_ASIGNATURA[ID_ASIG],"Seleccione Asignatura") -> FCACC-AU-CO-GE-NI-6-PROCE-DE -CON | G59: CONTABILIDAD Y AUDITORÍA | H59: =_xlfn.XLOOKUP(TAB_H_ASIG_CON_DET[[#This Row],[DETALLADO]],MAE_CONOCIMIENTO[CAMPO_DETALLADO],MAE_CONOCIMIENTO[ID_DDETALLADO],"Seleccione Campo Detallado") -> F-C-D-CON-Y A-AUD
A60: 74 | B60: FCACC-CO-AD | C60: =_xlfn.XLOOKUP(TAB_H_ASIG_CON_DET[[#This Row],[ID_CARRERA]],MAE_CARRERA[ID_CARRERA],MAE_CARRERA[NOMBRE_CARRERA],"Seleccione ID Carrera") -> CONTABILIDAD Y AUDITORÍA 2024 NS | D60: 8 | E60: PROCESO DE CONTRATACIÓN PÚBLICA | F60: =_xlfn.XLOOKUP(TAB_H_ASIG_CON_DET[[#This Row],[ASIGNATURA]],MAE_ASIGNATURA[NOM_ASIG],MAE_ASIGNATURA[ID_ASIG],"Seleccione Asignatura") -> FCACC-AU-CO-GE-NI-6-PROCE-DE -CON | G60: ADMINISTRACIÓN | H60: =_xlfn.XLOOKUP(TAB_H_ASIG_CON_DET[[#This Row],[DETALLADO]],MAE_CONOCIMIENTO[CAMPO_DETALLADO],MAE_CONOCIMIENTO[ID_DDETALLADO],"Seleccione Campo Detallado") -> F-C-D-ADM
A61: 75 | B61: FCACC-CO-AD | C61: =_xlfn.XLOOKUP(TAB_H_ASIG_CON_DET[[#This Row],[ID_CARRERA]],MAE_CARRERA[ID_CARRERA],MAE_CARRERA[NOMBRE_CARRERA],"Seleccione ID Carrera") -> CONTABILIDAD Y AUDITORÍA 2024 NS | D61: 8 | E61: AUDITORÍA INFORMÁTICA | F61: =_xlfn.XLOOKUP(TAB_H_ASIG_CON_DET[[#This Row],[ASIGNATURA]],MAE_ASIGNATURA[NOM_ASIG],MAE_ASIGNATURA[ID_ASIG],"Seleccione Asignatura") -> FCACC-CO-AD-NI-8-AUDIT-INF | G61: CONTABILIDAD Y AUDITORÍA | H61: =_xlfn.XLOOKUP(TAB_H_ASIG_CON_DET[[#This Row],[DETALLADO]],MAE_CONOCIMIENTO[CAMPO_DETALLADO],MAE_CONOCIMIENTO[ID_DDETALLADO],"Seleccione Campo Detallado") -> F-C-D-CON-Y A-AUD
A62: 76 | B62: FCACC-CO-AD | C62: =_xlfn.XLOOKUP(TAB_H_ASIG_CON_DET[[#This Row],[ID_CARRERA]],MAE_CARRERA[ID_CARRERA],MAE_CARRERA[NOMBRE_CARRERA],"Seleccione ID Carrera") -> CONTABILIDAD Y AUDITORÍA 2024 NS | D62: 8 | E62: AUDITORÍA AMBIENTAL | F62: =_xlfn.XLOOKUP(TAB_H_ASIG_CON_DET[[#This Row],[ASIGNATURA]],MAE_ASIGNATURA[NOM_ASIG],MAE_ASIGNATURA[ID_ASIG],"Seleccione Asignatura") -> FCACC-CO-AD-NI-8-AUDIT-AMB | G62: CONTABILIDAD Y AUDITORÍA | H62: =_xlfn.XLOOKUP(TAB_H_ASIG_CON_DET[[#This Row],[DETALLADO]],MAE_CONOCIMIENTO[CAMPO_DETALLADO],MAE_CONOCIMIENTO[ID_DDETALLADO],"Seleccione Campo Detallado") -> F-C-D-CON-Y A-AUD
... A250: 265 | B250: FCACC-8-TITU | C250: =_xlfn.XLOOKUP(TAB_H_ASIG_CON_DET[[#This Row],[ID_CARRERA]],MAE_CARRERA[ID_CARRERA],MAE_CARRERA[NOMBRE_CARRERA],"Seleccione ID Carrera") -> Titulación | D250: 8 | E250: Trabajo de integración curricular: Fase de resultados e informe F-24 | F250: =_xlfn.XLOOKUP(TAB_H_ASIG_CON_DET[[#This Row],[ASIGNATURA]],MAE_ASIGNATURA[NOM_ASIG],MAE_ASIGNATURA[ID_ASIG],"Seleccione Asignatura") -> FCACC-8-TITU-NI-8-Traba-de -int | G250: ADMINISTRACIÓN | H250: =_xlfn.XLOOKUP(TAB_H_ASIG_CON_DET[[#This Row],[DETALLADO]],MAE_CONOCIMIENTO[CAMPO_DETALLADO],MAE_CONOCIMIENTO[ID_DDETALLADO],"Seleccione Campo Detallado") -> F-C-D-ADM
A251: 266 | C251: ADMINISTRACIÓN DE EMPRESAS 2024 NS | F251: =_xlfn.XLOOKUP(TAB_H_ASIG_CON_DET[[#This Row],[ASIGNATURA]],MAE_ASIGNATURA[NOM_ASIG],MAE_ASIGNATURA[ID_ASIG],"Seleccione Asignatura") -> Seleccione Asignatura | H251: =_xlfn.XLOOKUP(TAB_H_ASIG_CON_DET[[#This Row],[DETALLADO]],MAE_CONOCIMIENTO[CAMPO_DETALLADO],MAE_CONOCIMIENTO[ID_DDETALLADO],"Seleccione Campo Detallado") -> F-C-D-
A252: 267 | C252: =_xlfn.XLOOKUP(TAB_H_ASIG_CON_DET[[#This Row],[ID_CARRERA]],MAE_CARRERA[ID_CARRERA],MAE_CARRERA[NOMBRE_CARRERA],"Seleccione ID Carrera") -> Seleccione ID Carrera | F252: =_xlfn.XLOOKUP(TAB_H_ASIG_CON_DET[[#This Row],[ASIGNATURA]],MAE_ASIGNATURA[NOM_ASIG],MAE_ASIGNATURA[ID_ASIG],"Seleccione Asignatura") -> Seleccione Asignatura | H252: =_xlfn.XLOOKUP(TAB_H_ASIG_CON_DET[[#This Row],[DETALLADO]],MAE_CONOCIMIENTO[CAMPO_DETALLADO],MAE_CONOCIMIENTO[ID_DDETALLADO],"Seleccione Campo Detallado") -> F-C-D-
A253: 268 | C253: =_xlfn.XLOOKUP(TAB_H_ASIG_CON_DET[[#This Row],[ID_CARRERA]],MAE_CARRERA[ID_CARRERA],MAE_CARRERA[NOMBRE_CARRERA],"Seleccione ID Carrera") -> Seleccione ID Carrera | F253: =_xlfn.XLOOKUP(TAB_H_ASIG_CON_DET[[#This Row],[ASIGNATURA]],MAE_ASIGNATURA[NOM_ASIG],MAE_ASIGNATURA[ID_ASIG],"Seleccione Asignatura") -> Seleccione Asignatura | H253: =_xlfn.XLOOKUP(TAB_H_ASIG_CON_DET[[#This Row],[DETALLADO]],MAE_CONOCIMIENTO[CAMPO_DETALLADO],MAE_CONOCIMIENTO[ID_DDETALLADO],"Seleccione Campo Detallado") -> F-C-D-
A254: 269 | C254: =_xlfn.XLOOKUP(TAB_H_ASIG_CON_DET[[#This Row],[ID_CARRERA]],MAE_CARRERA[ID_CARRERA],MAE_CARRERA[NOMBRE_CARRERA],"Seleccione ID Carrera") -> Seleccione ID Carrera | F254: =_xlfn.XLOOKUP(TAB_H_ASIG_CON_DET[[#This Row],[ASIGNATURA]],MAE_ASIGNATURA[NOM_ASIG],MAE_ASIGNATURA[ID_ASIG],"Seleccione Asignatura") -> Seleccione Asignatura | H254: =_xlfn.XLOOKUP(TAB_H_ASIG_CON_DET[[#This Row],[DETALLADO]],MAE_CONOCIMIENTO[CAMPO_DETALLADO],MAE_CONOCIMIENTO[ID_DDETALLADO],"Seleccione Campo Detallado") -> F-C-D-
A255: 270 | C255: =_xlfn.XLOOKUP(TAB_H_ASIG_CON_DET[[#This Row],[ID_CARRERA]],MAE_CARRERA[ID_CARRERA],MAE_CARRERA[NOMBRE_CARRERA],"Seleccione ID Carrera") -> Seleccione ID Carrera | F255: =_xlfn.XLOOKUP(TAB_H_ASIG_CON_DET[[#This Row],[ASIGNATURA]],MAE_ASIGNATURA[NOM_ASIG],MAE_ASIGNATURA[ID_ASIG],"Seleccione Asignatura") -> Seleccione Asignatura | H255: =_xlfn.XLOOKUP(TAB_H_ASIG_CON_DET[[#This Row],[DETALLADO]],MAE_CONOCIMIENTO[CAMPO_DETALLADO],MAE_CONOCIMIENTO[ID_DDETALLADO],"Seleccione Campo Detallado") -> F-C-D-
A256: 271 | C256: =_xlfn.XLOOKUP(TAB_H_ASIG_CON_DET[[#This Row],[ID_CARRERA]],MAE_CARRERA[ID_CARRERA],MAE_CARRERA[NOMBRE_CARRERA],"Seleccione ID Carrera") -> Seleccione ID Carrera | F256: =_xlfn.XLOOKUP(TAB_H_ASIG_CON_DET[[#This Row],[ASIGNATURA]],MAE_ASIGNATURA[NOM_ASIG],MAE_ASIGNATURA[ID_ASIG],"Seleccione Asignatura") -> Seleccione Asignatura | H256: =_xlfn.XLOOKUP(TAB_H_ASIG_CON_DET[[#This Row],[DETALLADO]],MAE_CONOCIMIENTO[CAMPO_DETALLADO],MAE_CONOCIMIENTO[ID_DDETALLADO],"Seleccione Campo Detallado") -> F-C-D-
A257: 272 | C257: =_xlfn.XLOOKUP(TAB_H_ASIG_CON_DET[[#This Row],[ID_CARRERA]],MAE_CARRERA[ID_CARRERA],MAE_CARRERA[NOMBRE_CARRERA],"Seleccione ID Carrera") -> Seleccione ID Carrera | F257: =_xlfn.XLOOKUP(TAB_H_ASIG_CON_DET[[#This Row],[ASIGNATURA]],MAE_ASIGNATURA[NOM_ASIG],MAE_ASIGNATURA[ID_ASIG],"Seleccione Asignatura") -> Seleccione Asignatura | H257: =_xlfn.XLOOKUP(TAB_H_ASIG_CON_DET[[#This Row],[DETALLADO]],MAE_CONOCIMIENTO[CAMPO_DETALLADO],MAE_CONOCIMIENTO[ID_DDETALLADO],"Seleccione Campo Detallado") -> F-C-D-
A258: 273 | C258: =_xlfn.XLOOKUP(TAB_H_ASIG_CON_DET[[#This Row],[ID_CARRERA]],MAE_CARRERA[ID_CARRERA],MAE_CARRERA[NOMBRE_CARRERA],"Seleccione ID Carrera") -> Seleccione ID Carrera | F258: =_xlfn.XLOOKUP(TAB_H_ASIG_CON_DET[[#This Row],[ASIGNATURA]],MAE_ASIGNATURA[NOM_ASIG],MAE_ASIGNATURA[ID_ASIG],"Seleccione Asignatura") -> Seleccione Asignatura | H258: =_xlfn.XLOOKUP(TAB_H_ASIG_CON_DET[[#This Row],[DETALLADO]],MAE_CONOCIMIENTO[CAMPO_DETALLADO],MAE_CONOCIMIENTO[ID_DDETALLADO],"Seleccione Campo Detallado") -> F-C-D-
A259: 274 | C259: =_xlfn.XLOOKUP(TAB_H_ASIG_CON_DET[[#This Row],[ID_CARRERA]],MAE_CARRERA[ID_CARRERA],MAE_CARRERA[NOMBRE_CARRERA],"Seleccione ID Carrera") -> Seleccione ID Carrera | F259: =_xlfn.XLOOKUP(TAB_H_ASIG_CON_DET[[#This Row],[ASIGNATURA]],MAE_ASIGNATURA[NOM_ASIG],MAE_ASIGNATURA[ID_ASIG],"Seleccione Asignatura") -> Seleccione Asignatura | H259: =_xlfn.XLOOKUP(TAB_H_ASIG_CON_DET[[#This Row],[DETALLADO]],MAE_CONOCIMIENTO[CAMPO_DETALLADO],MAE_CONOCIMIENTO[ID_DDETALLADO],"Seleccione Campo Detallado") -> F-C-D-
A260: 275 | C260: =_xlfn.XLOOKUP(TAB_H_ASIG_CON_DET[[#This Row],[ID_CARRERA]],MAE_CARRERA[ID_CARRERA],MAE_CARRERA[NOMBRE_CARRERA],"Seleccione ID Carrera") -> Seleccione ID Carrera | F260: =_xlfn.XLOOKUP(TAB_H_ASIG_CON_DET[[#This Row],[ASIGNATURA]],MAE_ASIGNATURA[NOM_ASIG],MAE_ASIGNATURA[ID_ASIG],"Seleccione Asignatura") -> Seleccione Asignatura | H260: =_xlfn.XLOOKUP(TAB_H_ASIG_CON_DET[[#This Row],[DETALLADO]],MAE_CONOCIMIENTO[CAMPO_DETALLADO],MAE_CONOCIMIENTO[ID_DDETALLADO],"Seleccione Campo Detallado") -> F-C-D-
A261: 276 | C261: =_xlfn.XLOOKUP(TAB_H_ASIG_CON_DET[[#This Row],[ID_CARRERA]],MAE_CARRERA[ID_CARRERA],MAE_CARRERA[NOMBRE_CARRERA],"Seleccione ID Carrera") -> Seleccione ID Carrera | F261: =_xlfn.XLOOKUP(TAB_H_ASIG_CON_DET[[#This Row],[ASIGNATURA]],MAE_ASIGNATURA[NOM_ASIG],MAE_ASIGNATURA[ID_ASIG],"Seleccione Asignatura") -> Seleccione Asignatura | H261: =_xlfn.XLOOKUP(TAB_H_ASIG_CON_DET[[#This Row],[DETALLADO]],MAE_CONOCIMIENTO[CAMPO_DETALLADO],MAE_CONOCIMIENTO[ID_DDETALLADO],"Seleccione Campo Detallado") -> F-C-D-
A262: 277 | C262: =_xlfn.XLOOKUP(TAB_H_ASIG_CON_DET[[#This Row],[ID_CARRERA]],MAE_CARRERA[ID_CARRERA],MAE_CARRERA[NOMBRE_CARRERA],"Seleccione ID Carrera") -> Seleccione ID Carrera | F262: =_xlfn.XLOOKUP(TAB_H_ASIG_CON_DET[[#This Row],[ASIGNATURA]],MAE_ASIGNATURA[NOM_ASIG],MAE_ASIGNATURA[ID_ASIG],"Seleccione Asignatura") -> Seleccione Asignatura | H262: =_xlfn.XLOOKUP(TAB_H_ASIG_CON_DET[[#This Row],[DETALLADO]],MAE_CONOCIMIENTO[CAMPO_DETALLADO],MAE_CONOCIMIENTO[ID_DDETALLADO],"Seleccione Campo Detallado") -> F-C-D-
A263: 278 | C263: =_xlfn.XLOOKUP(TAB_H_ASIG_CON_DET[[#This Row],[ID_CARRERA]],MAE_CARRERA[ID_CARRERA],MAE_CARRERA[NOMBRE_CARRERA],"Seleccione ID Carrera") -> Seleccione ID Carrera | F263: =_xlfn.XLOOKUP(TAB_H_ASIG_CON_DET[[#This Row],[ASIGNATURA]],MAE_ASIGNATURA[NOM_ASIG],MAE_ASIGNATURA[ID_ASIG],"Seleccione Asignatura") -> Seleccione Asignatura | H263: =_xlfn.XLOOKUP(TAB_H_ASIG_CON_DET[[#This Row],[DETALLADO]],MAE_CONOCIMIENTO[CAMPO_DETALLADO],MAE_CONOCIMIENTO[ID_DDETALLADO],"Seleccione Campo Detallado") -> F-C-D-
... A583: 598 | C583: =_xlfn.XLOOKUP(TAB_H_ASIG_CON_DET[[#This Row],[ID_CARRERA]],MAE_CARRERA[ID_CARRERA],MAE_CARRERA[NOMBRE_CARRERA],"Seleccione ID Carrera") -> Seleccione ID Carrera | F583: =_xlfn.XLOOKUP(TAB_H_ASIG_CON_DET[[#This Row],[ASIGNATURA]],MAE_ASIGNATURA[NOM_ASIG],MAE_ASIGNATURA[ID_ASIG],"Seleccione Asignatura") -> Seleccione Asignatura | H583: =_xlfn.XLOOKUP(TAB_H_ASIG_CON_DET[[#This Row],[DETALLADO]],MAE_CONOCIMIENTO[CAMPO_DETALLADO],MAE_CONOCIMIENTO[ID_DDETALLADO],"Seleccione Campo Detallado") -> F-C-D-
A584: 599 | C584: =_xlfn.XLOOKUP(TAB_H_ASIG_CON_DET[[#This Row],[ID_CARRERA]],MAE_CARRERA[ID_CARRERA],MAE_CARRERA[NOMBRE_CARRERA],"Seleccione ID Carrera") -> Seleccione ID Carrera | E584: No existe información | F584: =_xlfn.XLOOKUP(TAB_H_ASIG_CON_DET[[#This Row],[ASIGNATURA]],MAE_ASIGNATURA[NOM_ASIG],MAE_ASIGNATURA[ID_ASIG],"Seleccione Asignatura") -> Seleccione Asignatura | H584: =_xlfn.XLOOKUP(TAB_H_ASIG_CON_DET[[#This Row],[DETALLADO]],MAE_CONOCIMIENTO[CAMPO_DETALLADO],MAE_CONOCIMIENTO[ID_DDETALLADO],"Seleccione Campo Detallado") -> F-C-D-

Sheet Hoja1
A1: NIVEL | O1: ASIGNATURA
A2: {=TRANSPOSE(_xlfn.UNIQUE(_xlfn._xlws.FILTER(MAE_ASIGNATURA[ID_NIVEL],MAE_ASIGNATURA[ID_CARRERA]=DET_ASIG!$B2,"No existe información")))} -> 1 | B2: 2 | C2: 3 | D2: 4 | E2: 5 | F2: 6 | G2: 7 | H2: 8 | O2: {=TRANSPOSE(_xlfn.UNIQUE(_xlfn._xlws.FILTER(MAE_ASIGNATURA[NOM_ASIG],(MAE_ASIGNATURA[ID_NIVEL]=DET_ASIG!$D2)*(MAE_ASIGNATURA[ID_CARRERA]=DET_ASIG!$B2),"No existe información")))} -> CONTABILIDAD BÁSICA | P2: MATEMÁTICA | Q2: METODOLOGÍA DE LA INVESTIGACIÓN | R2: ADMINISTRACIÓN | S2: MACROECONOMÍA
A3: {=TRANSPOSE(_xlfn.UNIQUE(_xlfn._xlws.FILTER(MAE_ASIGNATURA[ID_NIVEL],MAE_ASIGNATURA[ID_CARRERA]=DET_ASIG!$B3,"No existe información")))} -> 1 | B3: 2 | C3: 3 | D3: 4 | E3: 5 | F3: 6 | G3: 7 | H3: 8 | O3: {=TRANSPOSE(_xlfn.UNIQUE(_xlfn._xlws.FILTER(MAE_ASIGNATURA[NOM_ASIG],(MAE_ASIGNATURA[ID_NIVEL]=DET_ASIG!$D3)*(MAE_ASIGNATURA[ID_CARRERA]=DET_ASIG!$B3),"No existe información")))} -> CONTABILIDAD BÁSICA | P3: MATEMÁTICA | Q3: METODOLOGÍA DE LA INVESTIGACIÓN | R3: ADMINISTRACIÓN | S3: MACROECONOMÍA
A4: {=TRANSPOSE(_xlfn.UNIQUE(_xlfn._xlws.FILTER(MAE_ASIGNATURA[ID_NIVEL],MAE_ASIGNATURA[ID_CARRERA]=DET_ASIG!$B4,"No existe información")))} -> 1 | B4: 2 | C4: 3 | D4: 4 | E4: 5 | F4: 6 | G4: 7 | H4: 8 | O4: {=TRANSPOSE(_xlfn.UNIQUE(_xlfn._xlws.FILTER(MAE_ASIGNATURA[NOM_ASIG],(MAE_ASIGNATURA[ID_NIVEL]=DET_ASIG!$D4)*(MAE_ASIGNATURA[ID_CARRERA]=DET_ASIG!$B4),"No existe información")))} -> CONTABILIDAD BÁSICA | P4: MATEMÁTICA | Q4: METODOLOGÍA DE LA INVESTIGACIÓN | R4: ADMINISTRACIÓN | S4: MACROECONOMÍA
A5: {=TRANSPOSE(_xlfn.UNIQUE(_xlfn._xlws.FILTER(MAE_ASIGNATURA[ID_NIVEL],MAE_ASIGNATURA[ID_CARRERA]=DET_ASIG!$B5,"No existe información")))} -> 1 | B5: 2 | C5: 3 | D5: 4 | E5: 5 | F5: 6 | G5: 7 | H5: 8 | O5: {=TRANSPOSE(_xlfn.UNIQUE(_xlfn._xlws.FILTER(MAE_ASIGNATURA[NOM_ASIG],(MAE_ASIGNATURA[ID_NIVEL]=DET_ASIG!$D5)*(MAE_ASIGNATURA[ID_CARRERA]=DET_ASIG!$B5),"No existe información")))} -> CONTABILIDAD BÁSICA | P5: MATEMÁTICA | Q5: METODOLOGÍA DE LA INVESTIGACIÓN | R5: ADMINISTRACIÓN | S5: MACROECONOMÍA
A6: {=TRANSPOSE(_xlfn.UNIQUE(_xlfn._xlws.FILTER(MAE_ASIGNATURA[ID_NIVEL],MAE_ASIGNATURA[ID_CARRERA]=DET_ASIG!$B6,"No existe información")))} -> 1 | B6: 2 | C6: 3 | D6: 4 | E6: 5 | F6: 6 | G6: 7 | H6: 8 | O6: {=TRANSPOSE(_xlfn.UNIQUE(_xlfn._xlws.FILTER(MAE_ASIGNATURA[NOM_ASIG],(MAE_ASIGNATURA[ID_NIVEL]=DET_ASIG!$D6)*(MAE_ASIGNATURA[ID_CARRERA]=DET_ASIG!$B6),"No existe información")))} -> CONTABILIDAD BÁSICA | P6: MATEMÁTICA | Q6: METODOLOGÍA DE LA INVESTIGACIÓN | R6: ADMINISTRACIÓN | S6: MACROECONOMÍA
A7: {=TRANSPOSE(_xlfn.UNIQUE(_xlfn._xlws.FILTER(MAE_ASIGNATURA[ID_NIVEL],MAE_ASIGNATURA[ID_CARRERA]=DET_ASIG!$B7,"No existe información")))} -> 1 | B7: 2 | C7: 3 | D7: 4 | E7: 5 | F7: 6 | G7: 7 | H7: 8 | O7: {=TRANSPOSE(_xlfn.UNIQUE(_xlfn._xlws.FILTER(MAE_ASIGNATURA[NOM_ASIG],(MAE_ASIGNATURA[ID_NIVEL]=DET_ASIG!$D7)*(MAE_ASIGNATURA[ID_CARRERA]=DET_ASIG!$B7),"No existe información")))} -> LEGISLACIÓN LABORAL | P7: CONTABILIDAD INTERMEDIA | Q7: ESTADÍSTICA DESCRIPTIVA | R7: LEGISLACIÓN MERCANTIL Y SOCIETARIA | S7: MATEMÁTICA FINANCIERA
A8: {=TRANSPOSE(_xlfn.UNIQUE(_xlfn._xlws.FILTER(MAE_ASIGNATURA[ID_NIVEL],MAE_ASIGNATURA[ID_CARRERA]=DET_ASIG!$B8,"No existe información")))} -> 1 | B8: 2 | C8: 3 | D8: 4 | E8: 5 | F8: 6 | G8: 7 | H8: 8 | O8: {=TRANSPOSE(_xlfn.UNIQUE(_xlfn._xlws.FILTER(MAE_ASIGNATURA[NOM_ASIG],(MAE_ASIGNATURA[ID_NIVEL]=DET_ASIG!$D8)*(MAE_ASIGNATURA[ID_CARRERA]=DET_ASIG!$B8),"No existe información")))} -> LEGISLACIÓN LABORAL | P8: CONTABILIDAD INTERMEDIA | Q8: ESTADÍSTICA DESCRIPTIVA | R8: LEGISLACIÓN MERCANTIL Y SOCIETARIA | S8: MATEMÁTICA FINANCIERA
A9: {=TRANSPOSE(_xlfn.UNIQUE(_xlfn._xlws.FILTER(MAE_ASIGNATURA[ID_NIVEL],MAE_ASIGNATURA[ID_CARRERA]=DET_ASIG!$B9,"No existe información")))} -> 1 | B9: 2 | C9: 3 | D9: 4 | E9: 5 | F9: 6 | G9: 7 | H9: 8 | O9: {=TRANSPOSE(_xlfn.UNIQUE(_xlfn._xlws.FILTER(MAE_ASIGNATURA[NOM_ASIG],(MAE_ASIGNATURA[ID_NIVEL]=DET_ASIG!$D9)*(MAE_ASIGNATURA[ID_CARRERA]=DET_ASIG!$B9),"No existe información")))} -> LEGISLACIÓN LABORAL | P9: CONTABILIDAD INTERMEDIA | Q9: ESTADÍSTICA DESCRIPTIVA | R9: LEGISLACIÓN MERCANTIL Y SOCIETARIA | S9: MATEMÁTICA FINANCIERA
A10: {=TRANSPOSE(_xlfn.UNIQUE(_xlfn._xlws.FILTER(MAE_ASIGNATURA[ID_NIVEL],MAE_ASIGNATURA[ID_CARRERA]=DET_ASIG!$B10,"No existe información")))} -> 1 | B10: 2 | C10: 3 | D10: 4 | E10: 5 | F10: 6 | G10: 7 | H10: 8 | O10: {=TRANSPOSE(_xlfn.UNIQUE(_xlfn._xlws.FILTER(MAE_ASIGNATURA[NOM_ASIG],(MAE_ASIGNATURA[ID_NIVEL]=DET_ASIG!$D10)*(MAE_ASIGNATURA[ID_CARRERA]=DET_ASIG!$B10),"No existe información")))} -> LEGISLACIÓN LABORAL | P10: CONTABILIDAD INTERMEDIA | Q10: ESTADÍSTICA DESCRIPTIVA | R10: LEGISLACIÓN MERCANTIL Y SOCIETARIA | S10: MATEMÁTICA FINANCIERA
A11: {=TRANSPOSE(_xlfn.UNIQUE(_xlfn._xlws.FILTER(MAE_ASIGNATURA[ID_NIVEL],MAE_ASIGNATURA[ID_CARRERA]=DET_ASIG!$B11,"No existe información")))} -> 1 | B11: 2 | C11: 3 | D11: 4 | E11: 5 | F11: 6 | G11: 7 | H11: 8 | O11: {=TRANSPOSE(_xlfn.UNIQUE(_xlfn._xlws.FILTER(MAE_ASIGNATURA[NOM_ASIG],(MAE_ASIGNATURA[ID_NIVEL]=DET_ASIG!$D11)*(MAE_ASIGNATURA[ID_CARRERA]=DET_ASIG!$B11),"No existe información")))} -> LEGISLACIÓN LABORAL | P11: CONTABILIDAD INTERMEDIA | Q11: ESTADÍSTICA DESCRIPTIVA | R11: LEGISLACIÓN MERCANTIL Y SOCIETARIA | S11: MATEMÁTICA FINANCIERA
A12: {=TRANSPOSE(_xlfn.UNIQUE(_xlfn._xlws.FILTER(MAE_ASIGNATURA[ID_NIVEL],MAE_ASIGNATURA[ID_CARRERA]=DET_ASIG!$B12,"No existe información")))} -> 1 | B12: 2 | C12: 3 | D12: 4 | E12: 5 | F12: 6 | G12: 7 | H12: 8 | O12: {=TRANSPOSE(_xlfn.UNIQUE(_xlfn._xlws.FILTER(MAE_ASIGNATURA[NOM_ASIG],(MAE_ASIGNATURA[ID_NIVEL]=DET_ASIG!$D12)*(MAE_ASIGNATURA[ID_CARRERA]=DET_ASIG!$B12),"No existe información")))} -> CONTABILIDAD AVANZADA | P12: FUNDAMENTOS DE AUDITORÍA | Q12: ESTADÍSTICA APLICADA | R12: LEGISLACIÓN TRIBUTARIA | S12: SISTEMATIZACIÓN CONTABLE Y FINANCIERA | T12: PROCESO Y CONTROL DEL TALENTO HUMANO
A13: {=TRANSPOSE(_xlfn.UNIQUE(_xlfn._xlws.FILTER(MAE_ASIGNATURA[ID_NIVEL],MAE_ASIGNATURA[ID_CARRERA]=DET_ASIG!$B13,"No existe información")))} -> 1 | B13: 2 | C13: 3 | D13: 4 | E13: 5 | F13: 6 | G13: 7 | H13: 8 | O13: {=TRANSPOSE(_xlfn.UNIQUE(_xlfn._xlws.FILTER(MAE_ASIGNATURA[NOM_ASIG],(MAE_ASIGNATURA[ID_NIVEL]=DET_ASIG!$D13)*(MAE_ASIGNATURA[ID_CARRERA]=DET_ASIG!$B13),"No existe información")))} -> CONTABILIDAD AVANZADA | P13: FUNDAMENTOS DE AUDITORÍA | Q13: ESTADÍSTICA APLICADA | R13: LEGISLACIÓN TRIBUTARIA | S13: SISTEMATIZACIÓN CONTABLE Y FINANCIERA | T13: PROCESO Y CONTROL DEL TALENTO HUMANO
A14: {=TRANSPOSE(_xlfn.UNIQUE(_xlfn._xlws.FILTER(MAE_ASIGNATURA[ID_NIVEL],MAE_ASIGNATURA[ID_CARRERA]=DET_ASIG!$B14,"No existe información")))} -> 1 | B14: 2 | C14: 3 | D14: 4 | E14: 5 | F14: 6 | G14: 7 | H14: 8 | O14: {=TRANSPOSE(_xlfn.UNIQUE(_xlfn._xlws.FILTER(MAE_ASIGNATURA[NOM_ASIG],(MAE_ASIGNATURA[ID_NIVEL]=DET_ASIG!$D14)*(MAE_ASIGNATURA[ID_CARRERA]=DET_ASIG!$B14),"No existe información")))} -> CONTABILIDAD AVANZADA | P14: FUNDAMENTOS DE AUDITORÍA | Q14: ESTADÍSTICA APLICADA | R14: LEGISLACIÓN TRIBUTARIA | S14: SISTEMATIZACIÓN CONTABLE Y FINANCIERA | T14: PROCESO Y CONTROL DEL TALENTO HUMANO
A15: {=TRANSPOSE(_xlfn.UNIQUE(_xlfn._xlws.FILTER(MAE_ASIGNATURA[ID_NIVEL],MAE_ASIGNATURA[ID_CARRERA]=DET_ASIG!$B15,"No existe información")))} -> 1 | B15: 2 | C15: 3 | D15: 4 | E15: 5 | F15: 6 | G15: 7 | H15: 8 | O15: {=TRANSPOSE(_xlfn.UNIQUE(_xlfn._xlws.FILTER(MAE_ASIGNATURA[NOM_ASIG],(MAE_ASIGNATURA[ID_NIVEL]=DET_ASIG!$D15)*(MAE_ASIGNATURA[ID_CARRERA]=DET_ASIG!$B15),"No existe información")))} -> CONTABILIDAD AVANZADA | P15: FUNDAMENTOS DE AUDITORÍA | Q15: ESTADÍSTICA APLICADA | R15: LEGISLACIÓN TRIBUTARIA | S15: SISTEMATIZACIÓN CONTABLE Y FINANCIERA | T15: PROCESO Y CONTROL DEL TALENTO HUMANO
A16: {=TRANSPOSE(_xlfn.UNIQUE(_xlfn._xlws.FILTER(MAE_ASIGNATURA[ID_NIVEL],MAE_ASIGNATURA[ID_CARRERA]=DET_ASIG!$B16,"No existe información")))} -> 1 | B16: 2 | C16: 3 | D16: 4 | E16: 5 | F16: 6 | G16: 7 | H16: 8 | O16: {=TRANSPOSE(_xlfn.UNIQUE(_xlfn._xlws.FILTER(MAE_ASIGNATURA[NOM_ASIG],(MAE_ASIGNATURA[ID_NIVEL]=DET_ASIG!$D16)*(MAE_ASIGNATURA[ID_CARRERA]=DET_ASIG!$B16),"No existe información")))} -> CONTABILIDAD AVANZADA | P16: FUNDAMENTOS DE AUDITORÍA | Q16: ESTADÍSTICA APLICADA | R16: LEGISLACIÓN TRIBUTARIA | S16: SISTEMATIZACIÓN CONTABLE Y FINANCIERA | T16: PROCESO Y CONTROL DEL TALENTO HUMANO
A17: {=TRANSPOSE(_xlfn.UNIQUE(_xlfn._xlws.FILTER(MAE_ASIGNATURA[ID_NIVEL],MAE_ASIGNATURA[ID_CARRERA]=DET_ASIG!#REF!,"No existe información")))} -> #REF! | O17: {=TRANSPOSE(_xlfn.UNIQUE(_xlfn._xlws.FILTER(MAE_ASIGNATURA[NOM_ASIG],(MAE_ASIGNATURA[ID_NIVEL]=DET_ASIG!#REF!)*(MAE_ASIGNATURA[ID_CARRERA]=DET_ASIG!#REF!),"No existe información")))} -> #REF!
A18: {=TRANSPOSE(_xlfn.UNIQUE(_xlfn._xlws.FILTER(MAE_ASIGNATURA[ID_NIVEL],MAE_ASIGNATURA[ID_CARRERA]=DET_ASIG!#REF!,"No existe información")))} -> #REF! | O18: {=TRANSPOSE(_xlfn.UNIQUE(_xlfn._xlws.FILTER(MAE_ASIGNATURA[NOM_ASIG],(MAE_ASIGNATURA[ID_NIVEL]=DET_ASIG!#REF!)*(MAE_ASIGNATURA[ID_CARRERA]=DET_ASIG!#REF!),"No existe información")))} -> #REF!
A19: {=TRANSPOSE(_xlfn.UNIQUE(_xlfn._xlws.FILTER(MAE_ASIGNATURA[ID_NIVEL],MAE_ASIGNATURA[ID_CARRERA]=DET_ASIG!#REF!,"No existe información")))} -> #REF! | O19: {=TRANSPOSE(_xlfn.UNIQUE(_xlfn._xlws.FILTER(MAE_ASIGNATURA[NOM_ASIG],(MAE_ASIGNATURA[ID_NIVEL]=DET_ASIG!#REF!)*(MAE_ASIGNATURA[ID_CARRERA]=DET_ASIG!#REF!),"No existe información")))} -> #REF!
A20: {=TRANSPOSE(_xlfn.UNIQUE(_xlfn._xlws.FILTER(MAE_ASIGNATURA[ID_NIVEL],MAE_ASIGNATURA[ID_CARRERA]=DET_ASIG!#REF!,"No existe información")))} -> #REF! | O20: {=TRANSPOSE(_xlfn.UNIQUE(_xlfn._xlws.FILTER(MAE_ASIGNATURA[NOM_ASIG],(MAE_ASIGNATURA[ID_NIVEL]=DET_ASIG!#REF!)*(MAE_ASIGNATURA[ID_CARRERA]=DET_ASIG!#REF!),"No existe información")))} -> #REF!
A21: {=TRANSPOSE(_xlfn.UNIQUE(_xlfn._xlws.FILTER(MAE_ASIGNATURA[ID_NIVEL],MAE_ASIGNATURA[ID_CARRERA]=DET_ASIG!#REF!,"No existe información")))} -> #REF! | O21: {=TRANSPOSE(_xlfn.UNIQUE(_xlfn._xlws.FILTER(MAE_ASIGNATURA[NOM_ASIG],(MAE_ASIGNATURA[ID_NIVEL]=DET_ASIG!#REF!)*(MAE_ASIGNATURA[ID_CARRERA]=DET_ASIG!#REF!),"No existe información")))} -> #REF!
A22: {=TRANSPOSE(_xlfn.UNIQUE(_xlfn._xlws.FILTER(MAE_ASIGNATURA[ID_NIVEL],MAE_ASIGNATURA[ID_CARRERA]=DET_ASIG!#REF!,"No existe información")))} -> #REF! | O22: {=TRANSPOSE(_xlfn.UNIQUE(_xlfn._xlws.FILTER(MAE_ASIGNATURA[NOM_ASIG],(MAE_ASIGNATURA[ID_NIVEL]=DET_ASIG!#REF!)*(MAE_ASIGNATURA[ID_CARRERA]=DET_ASIG!#REF!),"No existe información")))} -> #REF!
A23: {=TRANSPOSE(_xlfn.UNIQUE(_xlfn._xlws.FILTER(MAE_ASIGNATURA[ID_NIVEL],MAE_ASIGNATURA[ID_CARRERA]=DET_ASIG!#REF!,"No existe información")))} -> #REF! | O23: {=TRANSPOSE(_xlfn.UNIQUE(_xlfn._xlws.FILTER(MAE_ASIGNATURA[NOM_ASIG],(MAE_ASIGNATURA[ID_NIVEL]=DET_ASIG!#REF!)*(MAE_ASIGNATURA[ID_CARRERA]=DET_ASIG!#REF!),"No existe información")))} -> #REF!
A24: {=TRANSPOSE(_xlfn.UNIQUE(_xlfn._xlws.FILTER(MAE_ASIGNATURA[ID_NIVEL],MAE_ASIGNATURA[ID_CARRERA]=DET_ASIG!#REF!,"No existe información")))} -> #REF! | O24: {=TRANSPOSE(_xlfn.UNIQUE(_xlfn._xlws.FILTER(MAE_ASIGNATURA[NOM_ASIG],(MAE_ASIGNATURA[ID_NIVEL]=DET_ASIG!#REF!)*(MAE_ASIGNATURA[ID_CARRERA]=DET_ASIG!#REF!),"No existe información")))} -> #REF!
A25: {=TRANSPOSE(_xlfn.UNIQUE(_xlfn._xlws.FILTER(MAE_ASIGNATURA[ID_NIVEL],MAE_ASIGNATURA[ID_CARRERA]=DET_ASIG!#REF!,"No existe información")))} -> #REF! | O25: {=TRANSPOSE(_xlfn.UNIQUE(_xlfn._xlws.FILTER(MAE_ASIGNATURA[NOM_ASIG],(MAE_ASIGNATURA[ID_NIVEL]=DET_ASIG!#REF!)*(MAE_ASIGNATURA[ID_CARRERA]=DET_ASIG!#REF!),"No existe información")))} -> #REF!
A26: {=TRANSPOSE(_xlfn.UNIQUE(_xlfn._xlws.FILTER(MAE_ASIGNATURA[ID_NIVEL],MAE_ASIGNATURA[ID_CARRERA]=DET_ASIG!#REF!,"No existe información")))} -> #REF! | O26: {=TRANSPOSE(_xlfn.UNIQUE(_xlfn._xlws.FILTER(MAE_ASIGNATURA[NOM_ASIG],(MAE_ASIGNATURA[ID_NIVEL]=DET_ASIG!#REF!)*(MAE_ASIGNATURA[ID_CARRERA]=DET_ASIG!#REF!),"No existe información")))} -> #REF!
A27: {=TRANSPOSE(_xlfn.UNIQUE(_xlfn._xlws.FILTER(MAE_ASIGNATURA[ID_NIVEL],MAE_ASIGNATURA[ID_CARRERA]=DET_ASIG!#REF!,"No existe información")))} -> #REF! | O27: {=TRANSPOSE(_xlfn.UNIQUE(_xlfn._xlws.FILTER(MAE_ASIGNATURA[NOM_ASIG],(MAE_ASIGNATURA[ID_NIVEL]=DET_ASIG!#REF!)*(MAE_ASIGNATURA[ID_CARRERA]=DET_ASIG!#REF!),"No existe información")))} -> #REF!
A28: {=TRANSPOSE(_xlfn.UNIQUE(_xlfn._xlws.FILTER(MAE_ASIGNATURA[ID_NIVEL],MAE_ASIGNATURA[ID_CARRERA]=DET_ASIG!#REF!,"No existe información")))} -> #REF! | O28: {=TRANSPOSE(_xlfn.UNIQUE(_xlfn._xlws.FILTER(MAE_ASIGNATURA[NOM_ASIG],(MAE_ASIGNATURA[ID_NIVEL]=DET_ASIG!#REF!)*(MAE_ASIGNATURA[ID_CARRERA]=DET_ASIG!#REF!),"No existe información")))} -> #REF!
... A31: {=TRANSPOSE(_xlfn.UNIQUE(_xlfn._xlws.FILTER(MAE_ASIGNATURA[ID_NIVEL],MAE_ASIGNATURA[ID_CARRERA]=DET_ASIG!#REF!,"No existe información")))} -> #REF! | O31: {=TRANSPOSE(_xlfn.UNIQUE(_xlfn._xlws.FILTER(MAE_ASIGNATURA[NOM_ASIG],(MAE_ASIGNATURA[ID_NIVEL]=DET_ASIG!#REF!)*(MAE_ASIGNATURA[ID_CARRERA]=DET_ASIG!#REF!),"No existe información")))} -> #REF!
A32: {=TRANSPOSE(_xlfn.UNIQUE(_xlfn._xlws.FILTER(MAE_ASIGNATURA[ID_NIVEL],MAE_ASIGNATURA[ID_CARRERA]=DET_ASIG!$B17,"No existe información")))} -> 1 | B32: 2 | C32: 3 | D32: 4 | E32: 5 | F32: 6 | G32: 7 | H32: 8 | O32: {=TRANSPOSE(_xlfn.UNIQUE(_xlfn._xlws.FILTER(MAE_ASIGNATURA[NOM_ASIG],(MAE_ASIGNATURA[ID_NIVEL]=DET_ASIG!$D17)*(MAE_ASIGNATURA[ID_CARRERA]=DET_ASIG!$B17),"No existe información")))} -> CONTABILIDAD AVANZADA | P32: FUNDAMENTOS DE AUDITORÍA | Q32: ESTADÍSTICA APLICADA | R32: LEGISLACIÓN TRIBUTARIA | S32: SISTEMATIZACIÓN CONTABLE Y FINANCIERA | T32: PROCESO Y CONTROL DEL TALENTO HUMANO
A33: {=TRANSPOSE(_xlfn.UNIQUE(_xlfn._xlws.FILTER(MAE_ASIGNATURA[ID_NIVEL],MAE_ASIGNATURA[ID_CARRERA]=DET_ASIG!$B18,"No existe información")))} -> 1 | B33: 2 | C33: 3 | D33: 4 | E33: 5 | F33: 6 | G33: 7 | H33: 8 | O33: {=TRANSPOSE(_xlfn.UNIQUE(_xlfn._xlws.FILTER(MAE_ASIGNATURA[NOM_ASIG],(MAE_ASIGNATURA[ID_NIVEL]=DET_ASIG!$D18)*(MAE_ASIGNATURA[ID_CARRERA]=DET_ASIG!$B18),"No existe información")))} -> ADMINISTRACIÓN FINANCIERA | P33: CONTABILIDAD SUPERIOR | Q33: PLANIFICACIÓN Y DIRECCIÓN ESTRATÉGICA | R33: PLANIFICACIÓN DE AUDITORÍA | S33: TRIBUTACIÓN APLICADA
A34: {=TRANSPOSE(_xlfn.UNIQUE(_xlfn._xlws.FILTER(MAE_ASIGNATURA[ID_NIVEL],MAE_ASIGNATURA[ID_CARRERA]=DET_ASIG!$B19,"No existe información")))} -> 1 | B34: 2 | C34: 3 | D34: 4 | E34: 5 | F34: 6 | G34: 7 | H34: 8 | O34: {=TRANSPOSE(_xlfn.UNIQUE(_xlfn._xlws.FILTER(MAE_ASIGNATURA[NOM_ASIG],(MAE_ASIGNATURA[ID_NIVEL]=DET_ASIG!$D19)*(MAE_ASIGNATURA[ID_CARRERA]=DET_ASIG!$B19),"No existe información")))} -> ADMINISTRACIÓN FINANCIERA | P34: CONTABILIDAD SUPERIOR | Q34: PLANIFICACIÓN Y DIRECCIÓN ESTRATÉGICA | R34: PLANIFICACIÓN DE AUDITORÍA | S34: TRIBUTACIÓN APLICADA
A35: {=TRANSPOSE(_xlfn.UNIQUE(_xlfn._xlws.FILTER(MAE_ASIGNATURA[ID_NIVEL],MAE_ASIGNATURA[ID_CARRERA]=DET_ASIG!$B20,"No existe información")))} -> 1 | B35: 2 | C35: 3 | D35: 4 | E35: 5 | F35: 6 | G35: 7 | H35: 8 | O35: {=TRANSPOSE(_xlfn.UNIQUE(_xlfn._xlws.FILTER(MAE_ASIGNATURA[NOM_ASIG],(MAE_ASIGNATURA[ID_NIVEL]=DET_ASIG!$D20)*(MAE_ASIGNATURA[ID_CARRERA]=DET_ASIG!$B20),"No existe información")))} -> ADMINISTRACIÓN FINANCIERA | P35: CONTABILIDAD SUPERIOR | Q35: PLANIFICACIÓN Y DIRECCIÓN ESTRATÉGICA | R35: PLANIFICACIÓN DE AUDITORÍA | S35: TRIBUTACIÓN APLICADA
A36: {=TRANSPOSE(_xlfn.UNIQUE(_xlfn._xlws.FILTER(MAE_ASIGNATURA[ID_NIVEL],MAE_ASIGNATURA[ID_CARRERA]=DET_ASIG!$B21,"No existe información")))} -> 1 | B36: 2 | C36: 3 | D36: 4 | E36: 5 | F36: 6 | G36: 7 | H36: 8 | O36: {=TRANSPOSE(_xlfn.UNIQUE(_xlfn._xlws.FILTER(MAE_ASIGNATURA[NOM_ASIG],(MAE_ASIGNATURA[ID_NIVEL]=DET_ASIG!$D21)*(MAE_ASIGNATURA[ID_CARRERA]=DET_ASIG!$B21),"No existe información")))} -> ADMINISTRACIÓN FINANCIERA | P36: CONTABILIDAD SUPERIOR | Q36: PLANIFICACIÓN Y DIRECCIÓN ESTRATÉGICA | R36: PLANIFICACIÓN DE AUDITORÍA | S36: TRIBUTACIÓN APLICADA
A37: {=TRANSPOSE(_xlfn.UNIQUE(_xlfn._xlws.FILTER(MAE_ASIGNATURA[ID_NIVEL],MAE_ASIGNATURA[ID_CARRERA]=DET_ASIG!$B22,"No existe información")))} -> 1 | B37: 2 | C37: 3 | D37: 4 | E37: 5 | F37: 6 | G37: 7 | H37: 8 | O37: {=TRANSPOSE(_xlfn.UNIQUE(_xlfn._xlws.FILTER(MAE_ASIGNATURA[NOM_ASIG],(MAE_ASIGNATURA[ID_NIVEL]=DET_ASIG!$D22)*(MAE_ASIGNATURA[ID_CARRERA]=DET_ASIG!$B22),"No existe información")))} -> ADMINISTRACIÓN FINANCIERA | P37: CONTABILIDAD SUPERIOR | Q37: PLANIFICACIÓN Y DIRECCIÓN ESTRATÉGICA | R37: PLANIFICACIÓN DE AUDITORÍA | S37: TRIBUTACIÓN APLICADA
A38: {=TRANSPOSE(_xlfn.UNIQUE(_xlfn._xlws.FILTER(MAE_ASIGNATURA[ID_NIVEL],MAE_ASIGNATURA[ID_CARRERA]=DET_ASIG!$B23,"No existe información")))} -> 1 | B38: 2 | C38: 3 | D38: 4 | E38: 5 | F38: 6 | G38: 7 | H38: 8 | O38: {=TRANSPOSE(_xlfn.UNIQUE(_xlfn._xlws.FILTER(MAE_ASIGNATURA[NOM_ASIG],(MAE_ASIGNATURA[ID_NIVEL]=DET_ASIG!$D23)*(MAE_ASIGNATURA[ID_CARRERA]=DET_ASIG!$B23),"No existe información")))} -> ADMINISTRACIÓN FINANCIERA | P38: CONTABILIDAD SUPERIOR | Q38: PLANIFICACIÓN Y DIRECCIÓN ESTRATÉGICA | R38: PLANIFICACIÓN DE AUDITORÍA | S38: TRIBUTACIÓN APLICADA
A39: {=TRANSPOSE(_xlfn.UNIQUE(_xlfn._xlws.FILTER(MAE_ASIGNATURA[ID_NIVEL],MAE_ASIGNATURA[ID_CARRERA]=DET_ASIG!$B24,"No existe información")))} -> 1 | B39: 2 | C39: 3 | D39: 4 | E39: 5 | F39: 6 | G39: 7 | H39: 8 | O39: {=TRANSPOSE(_xlfn.UNIQUE(_xlfn._xlws.FILTER(MAE_ASIGNATURA[NOM_ASIG],(MAE_ASIGNATURA[ID_NIVEL]=DET_ASIG!$D24)*(MAE_ASIGNATURA[ID_CARRERA]=DET_ASIG!$B24),"No existe información")))} -> ADMINISTRACIÓN FINANCIERA | P39: CONTABILIDAD SUPERIOR | Q39: PLANIFICACIÓN Y DIRECCIÓN ESTRATÉGICA | R39: PLANIFICACIÓN DE AUDITORÍA | S39: TRIBUTACIÓN APLICADA
A40: {=TRANSPOSE(_xlfn.UNIQUE(_xlfn._xlws.FILTER(MAE_ASIGNATURA[ID_NIVEL],MAE_ASIGNATURA[ID_CARRERA]=DET_ASIG!$B25,"No existe información")))} -> 1 | B40: 2 | C40: 3 | D40: 4 | E40: 5 | F40: 6 | G40: 7 | H40: 8 | O40: {=TRANSPOSE(_xlfn.UNIQUE(_xlfn._xlws.FILTER(MAE_ASIGNATURA[NOM_ASIG],(MAE_ASIGNATURA[ID_NIVEL]=DET_ASIG!$D25)*(MAE_ASIGNATURA[ID_CARRERA]=DET_ASIG!$B25),"No existe información")))} -> CONTABILIDAD DE COSTOS | P40: CONTABILIDAD ESPECIALIZADA | Q40: AUDITORÍA FINANCIERA | R40: ORGANIZACIÓN Y MÉTODOS | S40: PRESUPUESTO
A41: {=TRANSPOSE(_xlfn.UNIQUE(_xlfn._xlws.FILTER(MAE_ASIGNATURA[ID_NIVEL],MAE_ASIGNATURA[ID_CARRERA]=DET_ASIG!$B26,"No existe información")))} -> 1 | B41: 2 | C41: 3 | D41: 4 | E41: 5 | F41: 6 | G41: 7 | H41: 8 | O41: {=TRANSPOSE(_xlfn.UNIQUE(_xlfn._xlws.FILTER(MAE_ASIGNATURA[NOM_ASIG],(MAE_ASIGNATURA[ID_NIVEL]=DET_ASIG!$D26)*(MAE_ASIGNATURA[ID_CARRERA]=DET_ASIG!$B26),"No existe información")))} -> CONTABILIDAD DE COSTOS | P41: CONTABILIDAD ESPECIALIZADA | Q41: AUDITORÍA FINANCIERA | R41: ORGANIZACIÓN Y MÉTODOS | S41: PRESUPUESTO
A42: {=TRANSPOSE(_xlfn.UNIQUE(_xlfn._xlws.FILTER(MAE_ASIGNATURA[ID_NIVEL],MAE_ASIGNATURA[ID_CARRERA]=DET_ASIG!$B27,"No existe información")))} -> 1 | B42: 2 | C42: 3 | D42: 4 | E42: 5 | F42: 6 | G42: 7 | H42: 8 | O42: {=TRANSPOSE(_xlfn.UNIQUE(_xlfn._xlws.FILTER(MAE_ASIGNATURA[NOM_ASIG],(MAE_ASIGNATURA[ID_NIVEL]=DET_ASIG!$D27)*(MAE_ASIGNATURA[ID_CARRERA]=DET_ASIG!$B27),"No existe información")))} -> CONTABILIDAD DE COSTOS | P42: CONTABILIDAD ESPECIALIZADA | Q42: AUDITORÍA FINANCIERA | R42: ORGANIZACIÓN Y MÉTODOS | S42: PRESUPUESTO
A43: {=TRANSPOSE(_xlfn.UNIQUE(_xlfn._xlws.FILTER(MAE_ASIGNATURA[ID_NIVEL],MAE_ASIGNATURA[ID_CARRERA]=DET_ASIG!$B28,"No existe información")))} -> 1 | B43: 2 | C43: 3 | D43: 4 | E43: 5 | F43: 6 | G43: 7 | H43: 8 | O43: {=TRANSPOSE(_xlfn.UNIQUE(_xlfn._xlws.FILTER(MAE_ASIGNATURA[NOM_ASIG],(MAE_ASIGNATURA[ID_NIVEL]=DET_ASIG!$D28)*(MAE_ASIGNATURA[ID_CARRERA]=DET_ASIG!$B28),"No existe información")))} -> CONTABILIDAD DE COSTOS | P43: CONTABILIDAD ESPECIALIZADA | Q43: AUDITORÍA FINANCIERA | R43: ORGANIZACIÓN Y MÉTODOS | S43: PRESUPUESTO
A44: {=TRANSPOSE(_xlfn.UNIQUE(_xlfn._xlws.FILTER(MAE_ASIGNATURA[ID_NIVEL],MAE_ASIGNATURA[ID_CARRERA]=DET_ASIG!$B29,"No existe información")))} -> 1 | B44: 2 | C44: 3 | D44: 4 | E44: 5 | F44: 6 | G44: 7 | H44: 8 | O44: {=TRANSPOSE(_xlfn.UNIQUE(_xlfn._xlws.FILTER(MAE_ASIGNATURA[NOM_ASIG],(MAE_ASIGNATURA[ID_NIVEL]=DET_ASIG!$D29)*(MAE_ASIGNATURA[ID_CARRERA]=DET_ASIG!$B29),"No existe información")))} -> CONTABILIDAD DE COSTOS | P44: CONTABILIDAD ESPECIALIZADA | Q44: AUDITORÍA FINANCIERA | R44: ORGANIZACIÓN Y MÉTODOS | S44: PRESUPUESTO
... A47: {=TRANSPOSE(_xlfn.UNIQUE(_xlfn._xlws.FILTER(MAE_ASIGNATURA[ID_NIVEL],MAE_ASIGNATURA[ID_CARRERA]=DET_ASIG!$B32,"No existe información")))} -> 1 | B47: 2 | C47: 3 | D47: 4 | E47: 5 | F47: 6 | G47: 7 | H47: 8 | O47: {=TRANSPOSE(_xlfn.UNIQUE(_xlfn._xlws.FILTER(MAE_ASIGNATURA[NOM_ASIG],(MAE_ASIGNATURA[ID_NIVEL]=DET_ASIG!$D32)*(MAE_ASIGNATURA[ID_CARRERA]=DET_ASIG!$B32),"No existe información")))} -> CONTABILIDAD DE COSTOS | P47: CONTABILIDAD ESPECIALIZADA | Q47: AUDITORÍA FINANCIERA | R47: ORGANIZACIÓN Y MÉTODOS | S47: PRESUPUESTO
A48: {=TRANSPOSE(_xlfn.UNIQUE(_xlfn._xlws.FILTER(MAE_ASIGNATURA[ID_NIVEL],MAE_ASIGNATURA[ID_CARRERA]=DET_ASIG!$B33,"No existe información")))} -> 1 | B48: 2 | C48: 3 | D48: 4 | E48: 5 | F48: 6 | G48: 7 | H48: 8 | O48: {=TRANSPOSE(_xlfn.UNIQUE(_xlfn._xlws.FILTER(MAE_ASIGNATURA[NOM_ASIG],(MAE_ASIGNATURA[ID_NIVEL]=DET_ASIG!$D33)*(MAE_ASIGNATURA[ID_CARRERA]=DET_ASIG!$B33),"No existe información")))} -> MARCO INTEGRADO E INDICADORES DE GESTIÓN | P48: CONTABILIDAD DE COSTOS AVANZADA | Q48: CONTABILIDAD GUBERNAMENTAL | R48: FORMULACIÓN DE PROYECTOS SOCIALES Y PRODUCTIVOS | S48: GESTIÓN DE LA CALIDAD Y ESTANDARIZACIÓN | T48: INVESTIGACIÓN OPERATIVA
A49: {=TRANSPOSE(_xlfn.UNIQUE(_xlfn._xlws.FILTER(MAE_ASIGNATURA[ID_NIVEL],MAE_ASIGNATURA[ID_CARRERA]=DET_ASIG!$B34,"No existe información")))} -> 1 | B49: 2 | C49: 3 | D49: 4 | E49: 5 | F49: 6 | G49: 7 | H49: 8 | O49: {=TRANSPOSE(_xlfn.UNIQUE(_xlfn._xlws.FILTER(MAE_ASIGNATURA[NOM_ASIG],(MAE_ASIGNATURA[ID_NIVEL]=DET_ASIG!$D34)*(MAE_ASIGNATURA[ID_CARRERA]=DET_ASIG!$B34),"No existe información")))} -> MARCO INTEGRADO E INDICADORES DE GESTIÓN | P49: CONTABILIDAD DE COSTOS AVANZADA | Q49: CONTABILIDAD GUBERNAMENTAL | R49: FORMULACIÓN DE PROYECTOS SOCIALES Y PRODUCTIVOS | S49: GESTIÓN DE LA CALIDAD Y ESTANDARIZACIÓN | T49: INVESTIGACIÓN OPERATIVA
A50: {=TRANSPOSE(_xlfn.UNIQUE(_xlfn._xlws.FILTER(MAE_ASIGNATURA[ID_NIVEL],MAE_ASIGNATURA[ID_CARRERA]=DET_ASIG!$B35,"No existe información")))} -> 1 | B50: 2 | C50: 3 | D50: 4 | E50: 5 | F50: 6 | G50: 7 | H50: 8 | O50: {=TRANSPOSE(_xlfn.UNIQUE(_xlfn._xlws.FILTER(MAE_ASIGNATURA[NOM_ASIG],(MAE_ASIGNATURA[ID_NIVEL]=DET_ASIG!$D35)*(MAE_ASIGNATURA[ID_CARRERA]=DET_ASIG!$B35),"No existe información")))} -> MARCO INTEGRADO E INDICADORES DE GESTIÓN | P50: CONTABILIDAD DE COSTOS AVANZADA | Q50: CONTABILIDAD GUBERNAMENTAL | R50: FORMULACIÓN DE PROYECTOS SOCIALES Y PRODUCTIVOS | S50: GESTIÓN DE LA CALIDAD Y ESTANDARIZACIÓN | T50: INVESTIGACIÓN OPERATIVA
A51: {=TRANSPOSE(_xlfn.UNIQUE(_xlfn._xlws.FILTER(MAE_ASIGNATURA[ID_NIVEL],MAE_ASIGNATURA[ID_CARRERA]=DET_ASIG!$B36,"No existe información")))} -> 1 | B51: 2 | C51: 3 | D51: 4 | E51: 5 | F51: 6 | G51: 7 | H51: 8 | O51: {=TRANSPOSE(_xlfn.UNIQUE(_xlfn._xlws.FILTER(MAE_ASIGNATURA[NOM_ASIG],(MAE_ASIGNATURA[ID_NIVEL]=DET_ASIG!$D36)*(MAE_ASIGNATURA[ID_CARRERA]=DET_ASIG!$B36),"No existe información")))} -> MARCO INTEGRADO E INDICADORES DE GESTIÓN | P51: CONTABILIDAD DE COSTOS AVANZADA | Q51: CONTABILIDAD GUBERNAMENTAL | R51: FORMULACIÓN DE PROYECTOS SOCIALES Y PRODUCTIVOS | S51: GESTIÓN DE LA CALIDAD Y ESTANDARIZACIÓN | T51: INVESTIGACIÓN OPERATIVA
A52: {=TRANSPOSE(_xlfn.UNIQUE(_xlfn._xlws.FILTER(MAE_ASIGNATURA[ID_NIVEL],MAE_ASIGNATURA[ID_CARRERA]=DET_ASIG!$B37,"No existe información")))} -> 1 | B52: 2 | C52: 3 | D52: 4 | E52: 5 | F52: 6 | G52: 7 | H52: 8 | O52: {=TRANSPOSE(_xlfn.UNIQUE(_xlfn._xlws.FILTER(MAE_ASIGNATURA[NOM_ASIG],(MAE_ASIGNATURA[ID_NIVEL]=DET_ASIG!$D37)*(MAE_ASIGNATURA[ID_CARRERA]=DET_ASIG!$B37),"No existe información")))} -> MARCO INTEGRADO E INDICADORES DE GESTIÓN | P52: CONTABILIDAD DE COSTOS AVANZADA | Q52: CONTABILIDAD GUBERNAMENTAL | R52: FORMULACIÓN DE PROYECTOS SOCIALES Y PRODUCTIVOS | S52: GESTIÓN DE LA CALIDAD Y ESTANDARIZACIÓN | T52: INVESTIGACIÓN OPERATIVA
A53: {=TRANSPOSE(_xlfn.UNIQUE(_xlfn._xlws.FILTER(MAE_ASIGNATURA[ID_NIVEL],MAE_ASIGNATURA[ID_CARRERA]=DET_ASIG!$B38,"No existe información")))} -> 1 | B53: 2 | C53: 3 | D53: 4 | E53: 5 | F53: 6 | G53: 7 | H53: 8 | O53: {=TRANSPOSE(_xlfn.UNIQUE(_xlfn._xlws.FILTER(MAE_ASIGNATURA[NOM_ASIG],(MAE_ASIGNATURA[ID_NIVEL]=DET_ASIG!$D38)*(MAE_ASIGNATURA[ID_CARRERA]=DET_ASIG!$B38),"No existe información")))} -> MARCO INTEGRADO E INDICADORES DE GESTIÓN | P53: CONTABILIDAD DE COSTOS AVANZADA | Q53: CONTABILIDAD GUBERNAMENTAL | R53: FORMULACIÓN DE PROYECTOS SOCIALES Y PRODUCTIVOS | S53: GESTIÓN DE LA CALIDAD Y ESTANDARIZACIÓN | T53: INVESTIGACIÓN OPERATIVA
A54: {=TRANSPOSE(_xlfn.UNIQUE(_xlfn._xlws.FILTER(MAE_ASIGNATURA[ID_NIVEL],MAE_ASIGNATURA[ID_CARRERA]=DET_ASIG!$B39,"No existe información")))} -> 1 | B54: 2 | C54: 3 | D54: 4 | E54: 5 | F54: 6 | G54: 7 | H54: 8 | O54: {=TRANSPOSE(_xlfn.UNIQUE(_xlfn._xlws.FILTER(MAE_ASIGNATURA[NOM_ASIG],(MAE_ASIGNATURA[ID_NIVEL]=DET_ASIG!$D39)*(MAE_ASIGNATURA[ID_CARRERA]=DET_ASIG!$B39),"No existe información")))} -> MARCO INTEGRADO E INDICADORES DE GESTIÓN | P54: CONTABILIDAD DE COSTOS AVANZADA | Q54: CONTABILIDAD GUBERNAMENTAL | R54: FORMULACIÓN DE PROYECTOS SOCIALES Y PRODUCTIVOS | S54: GESTIÓN DE LA CALIDAD Y ESTANDARIZACIÓN | T54: INVESTIGACIÓN OPERATIVA
A55: {=TRANSPOSE(_xlfn.UNIQUE(_xlfn._xlws.FILTER(MAE_ASIGNATURA[ID_NIVEL],MAE_ASIGNATURA[ID_CARRERA]=DET_ASIG!$B40,"No existe información")))} -> 1 | B55: 2 | C55: 3 | D55: 4 | E55: 5 | F55: 6 | G55: 7 | H55: 8 | O55: {=TRANSPOSE(_xlfn.UNIQUE(_xlfn._xlws.FILTER(MAE_ASIGNATURA[NOM_ASIG],(MAE_ASIGNATURA[ID_NIVEL]=DET_ASIG!$D40)*(MAE_ASIGNATURA[ID_CARRERA]=DET_ASIG!$B40),"No existe información")))} -> MARCO INTEGRADO E INDICADORES DE GESTIÓN | P55: CONTABILIDAD DE COSTOS AVANZADA | Q55: CONTABILIDAD GUBERNAMENTAL | R55: FORMULACIÓN DE PROYECTOS SOCIALES Y PRODUCTIVOS | S55: GESTIÓN DE LA CALIDAD Y ESTANDARIZACIÓN | T55: INVESTIGACIÓN OPERATIVA
A56: {=TRANSPOSE(_xlfn.UNIQUE(_xlfn._xlws.FILTER(MAE_ASIGNATURA[ID_NIVEL],MAE_ASIGNATURA[ID_CARRERA]=DET_ASIG!$B41,"No existe información")))} -> 1 | B56: 2 | C56: 3 | D56: 4 | E56: 5 | F56: 6 | G56: 7 | H56: 8 | O56: {=TRANSPOSE(_xlfn.UNIQUE(_xlfn._xlws.FILTER(MAE_ASIGNATURA[NOM_ASIG],(MAE_ASIGNATURA[ID_NIVEL]=DET_ASIG!$D41)*(MAE_ASIGNATURA[ID_CARRERA]=DET_ASIG!$B41),"No existe información")))} -> MARCO INTEGRADO E INDICADORES DE GESTIÓN | P56: CONTABILIDAD DE COSTOS AVANZADA | Q56: CONTABILIDAD GUBERNAMENTAL | R56: FORMULACIÓN DE PROYECTOS SOCIALES Y PRODUCTIVOS | S56: GESTIÓN DE LA CALIDAD Y ESTANDARIZACIÓN | T56: INVESTIGACIÓN OPERATIVA
A57: {=TRANSPOSE(_xlfn.UNIQUE(_xlfn._xlws.FILTER(MAE_ASIGNATURA[ID_NIVEL],MAE_ASIGNATURA[ID_CARRERA]=DET_ASIG!$B42,"No existe información")))} -> 1 | B57: 2 | C57: 3 | D57: 4 | E57: 5 | F57: 6 | G57: 7 | H57: 8 | O57: {=TRANSPOSE(_xlfn.UNIQUE(_xlfn._xlws.FILTER(MAE_ASIGNATURA[NOM_ASIG],(MAE_ASIGNATURA[ID_NIVEL]=DET_ASIG!$D42)*(MAE_ASIGNATURA[ID_CARRERA]=DET_ASIG!$B42),"No existe información")))} -> MARCO INTEGRADO E INDICADORES DE GESTIÓN | P57: CONTABILIDAD DE COSTOS AVANZADA | Q57: CONTABILIDAD GUBERNAMENTAL | R57: FORMULACIÓN DE PROYECTOS SOCIALES Y PRODUCTIVOS | S57: GESTIÓN DE LA CALIDAD Y ESTANDARIZACIÓN | T57: INVESTIGACIÓN OPERATIVA
A58: {=TRANSPOSE(_xlfn.UNIQUE(_xlfn._xlws.FILTER(MAE_ASIGNATURA[ID_NIVEL],MAE_ASIGNATURA[ID_CARRERA]=DET_ASIG!$B43,"No existe información")))} -> 1 | B58: 2 | C58: 3 | D58: 4 | E58: 5 | F58: 6 | G58: 7 | H58: 8 | O58: {=TRANSPOSE(_xlfn.UNIQUE(_xlfn._xlws.FILTER(MAE_ASIGNATURA[NOM_ASIG],(MAE_ASIGNATURA[ID_NIVEL]=DET_ASIG!$D43)*(MAE_ASIGNATURA[ID_CARRERA]=DET_ASIG!$B43),"No existe información")))} -> MARCO INTEGRADO E INDICADORES DE GESTIÓN | P58: CONTABILIDAD DE COSTOS AVANZADA | Q58: CONTABILIDAD GUBERNAMENTAL | R58: FORMULACIÓN DE PROYECTOS SOCIALES Y PRODUCTIVOS | S58: GESTIÓN DE LA CALIDAD Y ESTANDARIZACIÓN | T58: INVESTIGACIÓN OPERATIVA
A59: {=TRANSPOSE(_xlfn.UNIQUE(_xlfn._xlws.FILTER(MAE_ASIGNATURA[ID_NIVEL],MAE_ASIGNATURA[ID_CARRERA]=DET_ASIG!$B44,"No existe información")))} -> 1 | B59: 2 | C59: 3 | D59: 4 | E59: 5 | F59: 6 | G59: 7 | H59: 8 | O59: {=TRANSPOSE(_xlfn.UNIQUE(_xlfn._xlws.FILTER(MAE_ASIGNATURA[NOM_ASIG],(MAE_ASIGNATURA[ID_NIVEL]=DET_ASIG!$D44)*(MAE_ASIGNATURA[ID_CARRERA]=DET_ASIG!$B44),"No existe información")))} -> MARCO INTEGRADO E INDICADORES DE GESTIÓN | P59: CONTABILIDAD DE COSTOS AVANZADA | Q59: CONTABILIDAD GUBERNAMENTAL | R59: FORMULACIÓN DE PROYECTOS SOCIALES Y PRODUCTIVOS | S59: GESTIÓN DE LA CALIDAD Y ESTANDARIZACIÓN | T59: INVESTIGACIÓN OPERATIVA
A60: {=TRANSPOSE(_xlfn.UNIQUE(_xlfn._xlws.FILTER(MAE_ASIGNATURA[ID_NIVEL],MAE_ASIGNATURA[ID_CARRERA]=DET_ASIG!$B45,"No existe información")))} -> 1 | B60: 2 | C60: 3 | D60: 4 | E60: 5 | F60: 6 | G60: 7 | H60: 8 | O60: {=TRANSPOSE(_xlfn.UNIQUE(_xlfn._xlws.FILTER(MAE_ASIGNATURA[NOM_ASIG],(MAE_ASIGNATURA[ID_NIVEL]=DET_ASIG!$D45)*(MAE_ASIGNATURA[ID_CARRERA]=DET_ASIG!$B45),"No existe información")))} -> MARCO INTEGRADO E INDICADORES DE GESTIÓN | P60: CONTABILIDAD DE COSTOS AVANZADA | Q60: CONTABILIDAD GUBERNAMENTAL | R60: FORMULACIÓN DE PROYECTOS SOCIALES Y PRODUCTIVOS | S60: GESTIÓN DE LA CALIDAD Y ESTANDARIZACIÓN | T60: INVESTIGACIÓN OPERATIVA
A61: {=TRANSPOSE(_xlfn.UNIQUE(_xlfn._xlws.FILTER(MAE_ASIGNATURA[ID_NIVEL],MAE_ASIGNATURA[ID_CARRERA]=DET_ASIG!$B46,"No existe información")))} -> 1 | B61: 2 | C61: 3 | D61: 4 | E61: 5 | F61: 6 | G61: 7 | H61: 8 | O61: {=TRANSPOSE(_xlfn.UNIQUE(_xlfn._xlws.FILTER(MAE_ASIGNATURA[NOM_ASIG],(MAE_ASIGNATURA[ID_NIVEL]=DET_ASIG!$D46)*(MAE_ASIGNATURA[ID_CARRERA]=DET_ASIG!$B46),"No existe información")))} -> AUDITORÍA TRIBUTARIA | P61: AUDITORÍA DE CALIDAD | Q61: EVALUACIÓN DE PROYECTOS SOCIALES Y PRODUACTIVOS | R61: AUDITORÍA GUBERNAMENTAL
A62: {=TRANSPOSE(_xlfn.UNIQUE(_xlfn._xlws.FILTER(MAE_ASIGNATURA[ID_NIVEL],MAE_ASIGNATURA[ID_CARRERA]=DET_ASIG!$B47,"No existe información")))} -> 1 | B62: 2 | C62: 3 | D62: 4 | E62: 5 | F62: 6 | G62: 7 | H62: 8 | O62: {=TRANSPOSE(_xlfn.UNIQUE(_xlfn._xlws.FILTER(MAE_ASIGNATURA[NOM_ASIG],(MAE_ASIGNATURA[ID_NIVEL]=DET_ASIG!$D47)*(MAE_ASIGNATURA[ID_CARRERA]=DET_ASIG!$B47),"No existe información")))} -> AUDITORÍA TRIBUTARIA | P62: AUDITORÍA DE CALIDAD | Q62: EVALUACIÓN DE PROYECTOS SOCIALES Y PRODUACTIVOS | R62: AUDITORÍA GUBERNAMENTAL
A63: {=TRANSPOSE(_xlfn.UNIQUE(_xlfn._xlws.FILTER(MAE_ASIGNATURA[ID_NIVEL],MAE_ASIGNATURA[ID_CARRERA]=DET_ASIG!$B48,"No existe información")))} -> 1 | B63: 2 | C63: 3 | D63: 4 | E63: 5 | F63: 6 | G63: 7 | H63: 8 | O63: {=TRANSPOSE(_xlfn.UNIQUE(_xlfn._xlws.FILTER(MAE_ASIGNATURA[NOM_ASIG],(MAE_ASIGNATURA[ID_NIVEL]=DET_ASIG!$D48)*(MAE_ASIGNATURA[ID_CARRERA]=DET_ASIG!$B48),"No existe información")))} -> AUDITORÍA TRIBUTARIA | P63: AUDITORÍA DE CALIDAD | Q63: EVALUACIÓN DE PROYECTOS SOCIALES Y PRODUACTIVOS | R63: AUDITORÍA GUBERNAMENTAL
A64: {=TRANSPOSE(_xlfn.UNIQUE(_xlfn._xlws.FILTER(MAE_ASIGNATURA[ID_NIVEL],MAE_ASIGNATURA[ID_CARRERA]=DET_ASIG!$B49,"No existe información")))} -> 1 | B64: 2 | C64: 3 | D64: 4 | E64: 5 | F64: 6 | G64: 7 | H64: 8 | O64: {=TRANSPOSE(_xlfn.UNIQUE(_xlfn._xlws.FILTER(MAE_ASIGNATURA[NOM_ASIG],(MAE_ASIGNATURA[ID_NIVEL]=DET_ASIG!$D49)*(MAE_ASIGNATURA[ID_CARRERA]=DET_ASIG!$B49),"No existe información")))} -> AUDITORÍA FORENSE | P64: AUDITORÍA DE GESTIÓN | Q64: AUDITORÍA INFORMÁTICA | R64: PROCESO DE CONTRATACIÓN PÚBLICA | S64: AUDITORÍA AMBIENTAL
A65: {=TRANSPOSE(_xlfn.UNIQUE(_xlfn._xlws.FILTER(MAE_ASIGNATURA[ID_NIVEL],MAE_ASIGNATURA[ID_CARRERA]=DET_ASIG!$B50,"No existe información")))} -> 1 | B65: 2 | C65: 3 | D65: 4 | E65: 5 | F65: 6 | G65: 7 | H65: 8 | O65: {=TRANSPOSE(_xlfn.UNIQUE(_xlfn._xlws.FILTER(MAE_ASIGNATURA[NOM_ASIG],(MAE_ASIGNATURA[ID_NIVEL]=DET_ASIG!$D50)*(MAE_ASIGNATURA[ID_CARRERA]=DET_ASIG!$B50),"No existe información")))} -> AUDITORÍA TRIBUTARIA | P65: AUDITORÍA DE CALIDAD | Q65: EVALUACIÓN DE PROYECTOS SOCIALES Y PRODUACTIVOS | R65: AUDITORÍA GUBERNAMENTAL
A66: {=TRANSPOSE(_xlfn.UNIQUE(_xlfn._xlws.FILTER(MAE_ASIGNATURA[ID_NIVEL],MAE_ASIGNATURA[ID_CARRERA]=DET_ASIG!$B51,"No existe información")))} -> 7 | B66: 8 | O66: {=TRANSPOSE(_xlfn.UNIQUE(_xlfn._xlws.FILTER(MAE_ASIGNATURA[NOM_ASIG],(MAE_ASIGNATURA[ID_NIVEL]=DET_ASIG!$D51)*(MAE_ASIGNATURA[ID_CARRERA]=DET_ASIG!$B51),"No existe información")))} -> Trabajo de integración curricular: Fase de diseño CA-24 | P66: Trabajo de integración curricular: Fase de diseño ACG-24 | Q66: Trabajo de integración curricular: Fase de diseño F-24 | R66: Trabajo de integración curricular: Fase de diseño CA-22
A67: {=TRANSPOSE(_xlfn.UNIQUE(_xlfn._xlws.FILTER(MAE_ASIGNATURA[ID_NIVEL],MAE_ASIGNATURA[ID_CARRERA]=DET_ASIG!$B52,"No existe información")))} -> 7 | B67: 8 | O67: {=TRANSPOSE(_xlfn.UNIQUE(_xlfn._xlws.FILTER(MAE_ASIGNATURA[NOM_ASIG],(MAE_ASIGNATURA[ID_NIVEL]=DET_ASIG!$D52)*(MAE_ASIGNATURA[ID_CARRERA]=DET_ASIG!$B52),"No existe información")))} -> Trabajo de integración curricular: Fase de diseño CA-24 | P67: Trabajo de integración curricular: Fase de diseño ACG-24 | Q67: Trabajo de integración curricular: Fase de diseño F-24 | R67: Trabajo de integración curricular: Fase de diseño CA-22
A68: {=TRANSPOSE(_xlfn.UNIQUE(_xlfn._xlws.FILTER(MAE_ASIGNATURA[ID_NIVEL],MAE_ASIGNATURA[ID_CARRERA]=DET_ASIG!$B53,"No existe información")))} -> 7 | B68: 8 | O68: {=TRANSPOSE(_xlfn.UNIQUE(_xlfn._xlws.FILTER(MAE_ASIGNATURA[NOM_ASIG],(MAE_ASIGNATURA[ID_NIVEL]=DET_ASIG!$D53)*(MAE_ASIGNATURA[ID_CARRERA]=DET_ASIG!$B53),"No existe información")))} -> Trabajo de integración curricular: Fase de diseño CA-24 | P68: Trabajo de integración curricular: Fase de diseño ACG-24 | Q68: Trabajo de integración curricular: Fase de diseño F-24 | R68: Trabajo de integración curricular: Fase de diseño CA-22
A69: {=TRANSPOSE(_xlfn.UNIQUE(_xlfn._xlws.FILTER(MAE_ASIGNATURA[ID_NIVEL],MAE_ASIGNATURA[ID_CARRERA]=DET_ASIG!$B54,"No existe información")))} -> 7 | B69: 8 | O69: {=TRANSPOSE(_xlfn.UNIQUE(_xlfn._xlws.FILTER(MAE_ASIGNATURA[NOM_ASIG],(MAE_ASIGNATURA[ID_NIVEL]=DET_ASIG!$D54)*(MAE_ASIGNATURA[ID_CARRERA]=DET_ASIG!$B54),"No existe información")))} -> Trabajo de integración curricular: Fase de diseño CA-24 | P69: Trabajo de integración curricular: Fase de diseño ACG-24 | Q69: Trabajo de integración curricular: Fase de diseño F-24 | R69: Trabajo de integración curricular: Fase de diseño CA-22
A70: {=TRANSPOSE(_xlfn.UNIQUE(_xlfn._xlws.FILTER(MAE_ASIGNATURA[ID_NIVEL],MAE_ASIGNATURA[ID_CARRERA]=DET_ASIG!$B55,"No existe información")))} -> 7 | B70: 8 | O70: {=TRANSPOSE(_xlfn.UNIQUE(_xlfn._xlws.FILTER(MAE_ASIGNATURA[NOM_ASIG],(MAE_ASIGNATURA[ID_NIVEL]=DET_ASIG!$D55)*(MAE_ASIGNATURA[ID_CARRERA]=DET_ASIG!$B55),"No existe información")))} -> Trabajo de integración curricular: Fase de diseño CA-24 | P70: Trabajo de integración curricular: Fase de diseño ACG-24 | Q70: Trabajo de integración curricular: Fase de diseño F-24 | R70: Trabajo de integración curricular: Fase de diseño CA-22
A71: {=TRANSPOSE(_xlfn.UNIQUE(_xlfn._xlws.FILTER(MAE_ASIGNATURA[ID_NIVEL],MAE_ASIGNATURA[ID_CARRERA]=DET_ASIG!$B56,"No existe información")))} -> 7 | B71: 8 | O71: {=TRANSPOSE(_xlfn.UNIQUE(_xlfn._xlws.FILTER(MAE_ASIGNATURA[NOM_ASIG],(MAE_ASIGNATURA[ID_NIVEL]=DET_ASIG!$D56)*(MAE_ASIGNATURA[ID_CARRERA]=DET_ASIG!$B56),"No existe información")))} -> Trabajo de integración curricular: Fase de diseño CA-24 | P71: Trabajo de integración curricular: Fase de diseño ACG-24 | Q71: Trabajo de integración curricular: Fase de diseño F-24 | R71: Trabajo de integración curricular: Fase de diseño CA-22
A72: {=TRANSPOSE(_xlfn.UNIQUE(_xlfn._xlws.FILTER(MAE_ASIGNATURA[ID_NIVEL],MAE_ASIGNATURA[ID_CARRERA]=DET_ASIG!$B57,"No existe información")))} -> 1 | B72: 2 | C72: 3 | D72: 4 | E72: 5 | F72: 6 | G72: 7 | H72: 8 | O72: {=TRANSPOSE(_xlfn.UNIQUE(_xlfn._xlws.FILTER(MAE_ASIGNATURA[NOM_ASIG],(MAE_ASIGNATURA[ID_NIVEL]=DET_ASIG!$D57)*(MAE_ASIGNATURA[ID_CARRERA]=DET_ASIG!$B57),"No existe información")))} -> AUDITORÍA FORENSE | P72: AUDITORÍA DE GESTIÓN | Q72: AUDITORÍA INFORMÁTICA | R72: PROCESO DE CONTRATACIÓN PÚBLICA | S72: AUDITORÍA AMBIENTAL
A73: {=TRANSPOSE(_xlfn.UNIQUE(_xlfn._xlws.FILTER(MAE_ASIGNATURA[ID_NIVEL],MAE_ASIGNATURA[ID_CARRERA]=DET_ASIG!$B58,"No existe información")))} -> 1 | B73: 2 | C73: 3 | D73: 4 | E73: 5 | F73: 6 | G73: 7 | H73: 8 | O73: {=TRANSPOSE(_xlfn.UNIQUE(_xlfn._xlws.FILTER(MAE_ASIGNATURA[NOM_ASIG],(MAE_ASIGNATURA[ID_NIVEL]=DET_ASIG!$D58)*(MAE_ASIGNATURA[ID_CARRERA]=DET_ASIG!$B58),"No existe información")))} -> AUDITORÍA FORENSE | P73: AUDITORÍA DE GESTIÓN | Q73: AUDITORÍA INFORMÁTICA | R73: PROCESO DE CONTRATACIÓN PÚBLICA | S73: AUDITORÍA AMBIENTAL
A74: {=TRANSPOSE(_xlfn.UNIQUE(_xlfn._xlws.FILTER(MAE_ASIGNATURA[ID_NIVEL],MAE_ASIGNATURA[ID_CARRERA]=DET_ASIG!$B59,"No existe información")))} -> 1 | B74: 2 | C74: 3 | D74: 4 | E74: 5 | F74: 6 | G74: 7 | H74: 8 | O74: {=TRANSPOSE(_xlfn.UNIQUE(_xlfn._xlws.FILTER(MAE_ASIGNATURA[NOM_ASIG],(MAE_ASIGNATURA[ID_NIVEL]=DET_ASIG!$D59)*(MAE_ASIGNATURA[ID_CARRERA]=DET_ASIG!$B59),"No existe información")))} -> AUDITORÍA FORENSE | P74: AUDITORÍA DE GESTIÓN | Q74: AUDITORÍA INFORMÁTICA | R74: PROCESO DE CONTRATACIÓN PÚBLICA | S74: AUDITORÍA AMBIENTAL
A75: {=TRANSPOSE(_xlfn.UNIQUE(_xlfn._xlws.FILTER(MAE_ASIGNATURA[ID_NIVEL],MAE_ASIGNATURA[ID_CARRERA]=DET_ASIG!$B60,"No existe información")))} -> 1 | B75: 2 | C75: 3 | D75: 4 | E75: 5 | F75: 6 | G75: 7 | H75: 8 | O75: {=TRANSPOSE(_xlfn.UNIQUE(_xlfn._xlws.FILTER(MAE_ASIGNATURA[NOM_ASIG],(MAE_ASIGNATURA[ID_NIVEL]=DET_ASIG!$D60)*(MAE_ASIGNATURA[ID_CARRERA]=DET_ASIG!$B60),"No existe información")))} -> AUDITORÍA FORENSE | P75: AUDITORÍA DE GESTIÓN | Q75: AUDITORÍA INFORMÁTICA | R75: PROCESO DE CONTRATACIÓN PÚBLICA | S75: AUDITORÍA AMBIENTAL
A76: {=TRANSPOSE(_xlfn.UNIQUE(_xlfn._xlws.FILTER(MAE_ASIGNATURA[ID_NIVEL],MAE_ASIGNATURA[ID_CARRERA]=DET_ASIG!$B61,"No existe información")))} -> 1 | B76: 2 | C76: 3 | D76: 4 | E76: 5 | F76: 6 | G76: 7 | H76: 8 | O76: {=TRANSPOSE(_xlfn.UNIQUE(_xlfn._xlws.FILTER(MAE_ASIGNATURA[NOM_ASIG],(MAE_ASIGNATURA[ID_NIVEL]=DET_ASIG!$D61)*(MAE_ASIGNATURA[ID_CARRERA]=DET_ASIG!$B61),"No existe información")))} -> AUDITORÍA FORENSE | P76: AUDITORÍA DE GESTIÓN | Q76: AUDITORÍA INFORMÁTICA | R76: PROCESO DE CONTRATACIÓN PÚBLICA | S76: AUDITORÍA AMBIENTAL
A77: {=TRANSPOSE(_xlfn.UNIQUE(_xlfn._xlws.FILTER(MAE_ASIGNATURA[ID_NIVEL],MAE_ASIGNATURA[ID_CARRERA]=DET_ASIG!$B62,"No existe información")))} -> 1 | B77: 2 | C77: 3 | D77: 4 | E77: 5 | F77: 6 | G77: 7 | H77: 8 | O77: {=TRANSPOSE(_xlfn.UNIQUE(_xlfn._xlws.FILTER(MAE_ASIGNATURA[NOM_ASIG],(MAE_ASIGNATURA[ID_NIVEL]=DET_ASIG!$D62)*(MAE_ASIGNATURA[ID_CARRERA]=DET_ASIG!$B62),"No existe información")))} -> AUDITORÍA FORENSE | P77: AUDITORÍA DE GESTIÓN | Q77: AUDITORÍA INFORMÁTICA | R77: PROCESO DE CONTRATACIÓN PÚBLICA | S77: AUDITORÍA AMBIENTAL
A78: {=TRANSPOSE(_xlfn.UNIQUE(_xlfn._xlws.FILTER(MAE_ASIGNATURA[ID_NIVEL],MAE_ASIGNATURA[ID_CARRERA]=DET_ASIG!$B63,"No existe información")))} -> 1 | B78: 2 | C78: 3 | D78: 4 | E78: 5 | F78: 6 | G78: 7 | H78: 8 | O78: {=TRANSPOSE(_xlfn.UNIQUE(_xlfn._xlws.FILTER(MAE_ASIGNATURA[NOM_ASIG],(MAE_ASIGNATURA[ID_NIVEL]=DET_ASIG!$D63)*(MAE_ASIGNATURA[ID_CARRERA]=DET_ASIG!$B63),"No existe información")))} -> AUDITORÍA FORENSE | P78: AUDITORÍA DE GESTIÓN | Q78: AUDITORÍA INFORMÁTICA | R78: PROCESO DE CONTRATACIÓN PÚBLICA | S78: AUDITORÍA AMBIENTAL
A79: {=TRANSPOSE(_xlfn.UNIQUE(_xlfn._xlws.FILTER(MAE_ASIGNATURA[ID_NIVEL],MAE_ASIGNATURA[ID_CARRERA]=DET_ASIG!$B64,"No existe información")))} -> 7 | B79: 8 | O79: {=TRANSPOSE(_xlfn.UNIQUE(_xlfn._xlws.FILTER(MAE_ASIGNATURA[NOM_ASIG],(MAE_ASIGNATURA[ID_NIVEL]=DET_ASIG!$D64)*(MAE_ASIGNATURA[ID_CARRERA]=DET_ASIG!$B64),"No existe información")))} -> Trabajo de integración curricular: Fase de resultados e informe CA-24 | P79: Trabajo de integración curricular: Fase de resultados e informe ACG-24 | Q79: Trabajo de integración curricular: Fase de resultados e informe F-24 | R79: Trabajo de integración curricular: Fase de resultados e informe CA-22
A80: {=TRANSPOSE(_xlfn.UNIQUE(_xlfn._xlws.FILTER(MAE_ASIGNATURA[ID_NIVEL],MAE_ASIGNATURA[ID_CARRERA]=DET_ASIG!$B65,"No existe información")))} -> 7 | B80: 8 | O80: {=TRANSPOSE(_xlfn.UNIQUE(_xlfn._xlws.FILTER(MAE_ASIGNATURA[NOM_ASIG],(MAE_ASIGNATURA[ID_NIVEL]=DET_ASIG!$D65)*(MAE_ASIGNATURA[ID_CARRERA]=DET_ASIG!$B65),"No existe información")))} -> Trabajo de integración curricular: Fase de resultados e informe CA-24 | P80: Trabajo de integración curricular: Fase de resultados e informe ACG-24 | Q80: Trabajo de integración curricular: Fase de resultados e informe F-24 | R80: Trabajo de integración curricular: Fase de resultados e informe CA-22
A81: {=TRANSPOSE(_xlfn.UNIQUE(_xlfn._xlws.FILTER(MAE_ASIGNATURA[ID_NIVEL],MAE_ASIGNATURA[ID_CARRERA]=DET_ASIG!$B66,"No existe información")))} -> 7 | B81: 8 | O81: {=TRANSPOSE(_xlfn.UNIQUE(_xlfn._xlws.FILTER(MAE_ASIGNATURA[NOM_ASIG],(MAE_ASIGNATURA[ID_NIVEL]=DET_ASIG!$D66)*(MAE_ASIGNATURA[ID_CARRERA]=DET_ASIG!$B66),"No existe información")))} -> Trabajo de integración curricular: Fase de resultados e informe CA-24 | P81: Trabajo de integración curricular: Fase de resultados e informe ACG-24 | Q81: Trabajo de integración curricular: Fase de resultados e informe F-24 | R81: Trabajo de integración curricular: Fase de resultados e informe CA-22
A82: {=TRANSPOSE(_xlfn.UNIQUE(_xlfn._xlws.FILTER(MAE_ASIGNATURA[ID_NIVEL],MAE_ASIGNATURA[ID_CARRERA]=DET_ASIG!$B67,"No existe información")))} -> 7 | B82: 8 | O82: {=TRANSPOSE(_xlfn.UNIQUE(_xlfn._xlws.FILTER(MAE_ASIGNATURA[NOM_ASIG],(MAE_ASIGNATURA[ID_NIVEL]=DET_ASIG!$D67)*(MAE_ASIGNATURA[ID_CARRERA]=DET_ASIG!$B67),"No existe información")))} -> Trabajo de integración curricular: Fase de resultados e informe CA-24 | P82: Trabajo de integración curricular: Fase de resultados e informe ACG-24 | Q82: Trabajo de integración curricular: Fase de resultados e informe F-24 | R82: Trabajo de integración curricular: Fase de resultados e informe CA-22
A83: {=TRANSPOSE(_xlfn.UNIQUE(_xlfn._xlws.FILTER(MAE_ASIGNATURA[ID_NIVEL],MAE_ASIGNATURA[ID_CARRERA]=DET_ASIG!$B68,"No existe información")))} -> 7 | B83: 8 | O83: {=TRANSPOSE(_xlfn.UNIQUE(_xlfn._xlws.FILTER(MAE_ASIGNATURA[NOM_ASIG],(MAE_ASIGNATURA[ID_NIVEL]=DET_ASIG!$D68)*(MAE_ASIGNATURA[ID_CARRERA]=DET_ASIG!$B68),"No existe información")))} -> Trabajo de integración curricular: Fase de resultados e informe CA-24 | P83: Trabajo de integración curricular: Fase de resultados e informe ACG-24 | Q83: Trabajo de integración curricular: Fase de resultados e informe F-24 | R83: Trabajo de integración curricular: Fase de resultados e informe CA-22
A84: {=TRANSPOSE(_xlfn.UNIQUE(_xlfn._xlws.FILTER(MAE_ASIGNATURA[ID_NIVEL],MAE_ASIGNATURA[ID_CARRERA]=DET_ASIG!$B69,"No existe información")))} -> 7 | B84: 8 | O84: {=TRANSPOSE(_xlfn.UNIQUE(_xlfn._xlws.FILTER(MAE_ASIGNATURA[NOM_ASIG],(MAE_ASIGNATURA[ID_NIVEL]=DET_ASIG!$D69)*(MAE_ASIGNATURA[ID_CARRERA]=DET_ASIG!$B69),"No existe información")))} -> Trabajo de integración curricular: Fase de resultados e informe CA-24 | P84: Trabajo de integración curricular: Fase de resultados e informe ACG-24 | Q84: Trabajo de integración curricular: Fase de resultados e informe F-24 | R84: Trabajo de integración curricular: Fase de resultados e informe CA-22
A85: {=TRANSPOSE(_xlfn.UNIQUE(_xlfn._xlws.FILTER(MAE_ASIGNATURA[ID_NIVEL],MAE_ASIGNATURA[ID_CARRERA]=DET_ASIG!$B70,"No existe información")))} -> 1 | B85: 2 | C85: 3 | D85: 4 | E85: 5 | F85: 6 | G85: 7 | H85: 8 | O85: {=TRANSPOSE(_xlfn.UNIQUE(_xlfn._xlws.FILTER(MAE_ASIGNATURA[NOM_ASIG],(MAE_ASIGNATURA[ID_NIVEL]=DET_ASIG!$D70)*(MAE_ASIGNATURA[ID_CARRERA]=DET_ASIG!$B70),"No existe información")))} -> FUNDAMENTOS DE CONTABILIDAD | P85: FUNDAMENTOS DE ADMINISTRACIÓN | Q85: ESTADÍSTICA DESCRIPTIVA | R85: LEGISLACIÓN MERCANTIL Y SOCIERTARIA
A86: {=TRANSPOSE(_xlfn.UNIQUE(_xlfn._xlws.FILTER(MAE_ASIGNATURA[ID_NIVEL],MAE_ASIGNATURA[ID_CARRERA]=DET_ASIG!$B71,"No existe información")))} -> 1 | B86: 2 | C86: 3 | D86: 4 | E86: 5 | F86: 6 | G86: 7 | H86: 8 | O86: {=TRANSPOSE(_xlfn.UNIQUE(_xlfn._xlws.FILTER(MAE_ASIGNATURA[NOM_ASIG],(MAE_ASIGNATURA[ID_NIVEL]=DET_ASIG!$D71)*(MAE_ASIGNATURA[ID_CARRERA]=DET_ASIG!$B71),"No existe información")))} -> FUNDAMENTOS DE CONTABILIDAD | P86: FUNDAMENTOS DE ADMINISTRACIÓN | Q86: ESTADÍSTICA DESCRIPTIVA | R86: LEGISLACIÓN MERCANTIL Y SOCIERTARIA
A87: {=TRANSPOSE(_xlfn.UNIQUE(_xlfn._xlws.FILTER(MAE_ASIGNATURA[ID_NIVEL],MAE_ASIGNATURA[ID_CARRERA]=DET_ASIG!$B72,"No existe información")))} -> 1 | B87: 2 | C87: 3 | D87: 4 | E87: 5 | F87: 6 | G87: 7 | H87: 8 | O87: {=TRANSPOSE(_xlfn.UNIQUE(_xlfn._xlws.FILTER(MAE_ASIGNATURA[NOM_ASIG],(MAE_ASIGNATURA[ID_NIVEL]=DET_ASIG!$D72)*(MAE_ASIGNATURA[ID_CARRERA]=DET_ASIG!$B72),"No existe información")))} -> FUNDAMENTOS DE CONTABILIDAD | P87: FUNDAMENTOS DE ADMINISTRACIÓN | Q87: ESTADÍSTICA DESCRIPTIVA | R87: LEGISLACIÓN MERCANTIL Y SOCIERTARIA
A88: {=TRANSPOSE(_xlfn.UNIQUE(_xlfn._xlws.FILTER(MAE_ASIGNATURA[ID_NIVEL],MAE_ASIGNATURA[ID_CARRERA]=DET_ASIG!$B73,"No existe información")))} -> 1 | B88: 2 | C88: 3 | D88: 4 | E88: 5 | F88: 6 | G88: 7 | H88: 8 | O88: {=TRANSPOSE(_xlfn.UNIQUE(_xlfn._xlws.FILTER(MAE_ASIGNATURA[NOM_ASIG],(MAE_ASIGNATURA[ID_NIVEL]=DET_ASIG!$D73)*(MAE_ASIGNATURA[ID_CARRERA]=DET_ASIG!$B73),"No existe información")))} -> FUNDAMENTOS DE CONTABILIDAD | P88: FUNDAMENTOS DE ADMINISTRACIÓN | Q88: ESTADÍSTICA DESCRIPTIVA | R88: LEGISLACIÓN MERCANTIL Y SOCIERTARIA
A89: {=TRANSPOSE(_xlfn.UNIQUE(_xlfn._xlws.FILTER(MAE_ASIGNATURA[ID_NIVEL],MAE_ASIGNATURA[ID_CARRERA]=DET_ASIG!$B74,"No existe información")))} -> 1 | B89: 2 | C89: 3 | D89: 4 | E89: 5 | F89: 6 | G89: 7 | H89: 8 | O89: {=TRANSPOSE(_xlfn.UNIQUE(_xlfn._xlws.FILTER(MAE_ASIGNATURA[NOM_ASIG],(MAE_ASIGNATURA[ID_NIVEL]=DET_ASIG!$D74)*(MAE_ASIGNATURA[ID_CARRERA]=DET_ASIG!$B74),"No existe información")))} -> CONTABILIDAD FINANCIERA | P89: MATEMÁTICA FINANCIERA | Q89: ESTADÍSTICA INFERENCIAL | R89: LEGISLACIÓN LABORAL
A90: {=TRANSPOSE(_xlfn.UNIQUE(_xlfn._xlws.FILTER(MAE_ASIGNATURA[ID_NIVEL],MAE_ASIGNATURA[ID_CARRERA]=DET_ASIG!$B75,"No existe información")))} -> 1 | B90: 2 | C90: 3 | D90: 4 | E90: 5 | F90: 6 | G90: 7 | H90: 8 | O90: {=TRANSPOSE(_xlfn.UNIQUE(_xlfn._xlws.FILTER(MAE_ASIGNATURA[NOM_ASIG],(MAE_ASIGNATURA[ID_NIVEL]=DET_ASIG!$D75)*(MAE_ASIGNATURA[ID_CARRERA]=DET_ASIG!$B75),"No existe información")))} -> CONTABILIDAD FINANCIERA | P90: MATEMÁTICA FINANCIERA | Q90: ESTADÍSTICA INFERENCIAL | R90: LEGISLACIÓN LABORAL
A91: {=TRANSPOSE(_xlfn.UNIQUE(_xlfn._xlws.FILTER(MAE_ASIGNATURA[ID_NIVEL],MAE_ASIGNATURA[ID_CARRERA]=DET_ASIG!$B76,"No existe información")))} -> 1 | B91: 2 | C91: 3 | D91: 4 | E91: 5 | F91: 6 | G91: 7 | H91: 8 | O91: {=TRANSPOSE(_xlfn.UNIQUE(_xlfn._xlws.FILTER(MAE_ASIGNATURA[NOM_ASIG],(MAE_ASIGNATURA[ID_NIVEL]=DET_ASIG!$D76)*(MAE_ASIGNATURA[ID_CARRERA]=DET_ASIG!$B76),"No existe información")))} -> CONTABILIDAD FINANCIERA | P91: MATEMÁTICA FINANCIERA | Q91: ESTADÍSTICA INFERENCIAL | R91: LEGISLACIÓN LABORAL
A92: {=TRANSPOSE(_xlfn.UNIQUE(_xlfn._xlws.FILTER(MAE_ASIGNATURA[ID_NIVEL],MAE_ASIGNATURA[ID_CARRERA]=DET_ASIG!$B77,"No existe información")))} -> 1 | B92: 2 | C92: 3 | D92: 4 | E92: 5 | F92: 6 | G92: 7 | H92: 8 | O92: {=TRANSPOSE(_xlfn.UNIQUE(_xlfn._xlws.FILTER(MAE_ASIGNATURA[NOM_ASIG],(MAE_ASIGNATURA[ID_NIVEL]=DET_ASIG!$D77)*(MAE_ASIGNATURA[ID_CARRERA]=DET_ASIG!$B77),"No existe información")))} -> CONTABILIDAD FINANCIERA | P92: MATEMÁTICA FINANCIERA | Q92: ESTADÍSTICA INFERENCIAL | R92: LEGISLACIÓN LABORAL
A93: {=TRANSPOSE(_xlfn.UNIQUE(_xlfn._xlws.FILTER(MAE_ASIGNATURA[ID_NIVEL],MAE_ASIGNATURA[ID_CARRERA]=DET_ASIG!$B78,"No existe información")))} -> 1 | B93: 2 | C93: 3 | D93: 4 | E93: 5 | F93: 6 | G93: 7 | H93: 8 | O93: {=TRANSPOSE(_xlfn.UNIQUE(_xlfn._xlws.FILTER(MAE_ASIGNATURA[NOM_ASIG],(MAE_ASIGNATURA[ID_NIVEL]=DET_ASIG!$D78)*(MAE_ASIGNATURA[ID_CARRERA]=DET_ASIG!$B78),"No existe información")))} -> CONTABILIDAD DE COSTOS | P93: CONTABILIDAD SOCIAL Y AMBIENTAL | Q93: ADMINISTRACIÓN FINANCIERA | R93: FUNDAMENTOS DE AUDITORÍAS | S93: GESTIÓN DE TALENTO HUMANO
A94: {=TRANSPOSE(_xlfn.UNIQUE(_xlfn._xlws.FILTER(MAE_ASIGNATURA[ID_NIVEL],MAE_ASIGNATURA[ID_CARRERA]=DET_ASIG!$B79,"No existe información")))} -> 1 | B94: 2 | C94: 3 | D94: 4 | E94: 5 | F94: 6 | G94: 7 | H94: 8 | O94: {=TRANSPOSE(_xlfn.UNIQUE(_xlfn._xlws.FILTER(MAE_ASIGNATURA[NOM_ASIG],(MAE_ASIGNATURA[ID_NIVEL]=DET_ASIG!$D79)*(MAE_ASIGNATURA[ID_CARRERA]=DET_ASIG!$B79),"No existe información")))} -> CONTABILIDAD DE COSTOS | P94: CONTABILIDAD SOCIAL Y AMBIENTAL | Q94: ADMINISTRACIÓN FINANCIERA | R94: FUNDAMENTOS DE AUDITORÍAS | S94: GESTIÓN DE TALENTO HUMANO
A95: {=TRANSPOSE(_xlfn.UNIQUE(_xlfn._xlws.FILTER(MAE_ASIGNATURA[ID_NIVEL],MAE_ASIGNATURA[ID_CARRERA]=DET_ASIG!$B80,"No existe información")))} -> 1 | B95: 2 | C95: 3 | D95: 4 | E95: 5 | F95: 6 | G95: 7 | H95: 8 | O95: {=TRANSPOSE(_xlfn.UNIQUE(_xlfn._xlws.FILTER(MAE_ASIGNATURA[NOM_ASIG],(MAE_ASIGNATURA[ID_NIVEL]=DET_ASIG!$D80)*(MAE_ASIGNATURA[ID_CARRERA]=DET_ASIG!$B80),"No existe información")))} -> CONTABILIDAD DE COSTOS | P95: CONTABILIDAD SOCIAL Y AMBIENTAL | Q95: ADMINISTRACIÓN FINANCIERA | R95: FUNDAMENTOS DE AUDITORÍAS | S95: GESTIÓN DE TALENTO HUMANO
A96: {=TRANSPOSE(_xlfn.UNIQUE(_xlfn._xlws.FILTER(MAE_ASIGNATURA[ID_NIVEL],MAE_ASIGNATURA[ID_CARRERA]=DET_ASIG!$B81,"No existe información")))} -> 1 | B96: 2 | C96: 3 | D96: 4 | E96: 5 | F96: 6 | G96: 7 | H96: 8 | O96: {=TRANSPOSE(_xlfn.UNIQUE(_xlfn._xlws.FILTER(MAE_ASIGNATURA[NOM_ASIG],(MAE_ASIGNATURA[ID_NIVEL]=DET_ASIG!$D81)*(MAE_ASIGNATURA[ID_CARRERA]=DET_ASIG!$B81),"No existe información")))} -> CONTABILIDAD DE COSTOS | P96: CONTABILIDAD SOCIAL Y AMBIENTAL | Q96: ADMINISTRACIÓN FINANCIERA | R96: FUNDAMENTOS DE AUDITORÍAS | S96: GESTIÓN DE TALENTO HUMANO
A97: {=TRANSPOSE(_xlfn.UNIQUE(_xlfn._xlws.FILTER(MAE_ASIGNATURA[ID_NIVEL],MAE_ASIGNATURA[ID_CARRERA]=DET_ASIG!$B82,"No existe información")))} -> 1 | B97: 2 | C97: 3 | D97: 4 | E97: 5 | F97: 6 | G97: 7 | H97: 8 | O97: {=TRANSPOSE(_xlfn.UNIQUE(_xlfn._xlws.FILTER(MAE_ASIGNATURA[NOM_ASIG],(MAE_ASIGNATURA[ID_NIVEL]=DET_ASIG!$D82)*(MAE_ASIGNATURA[ID_CARRERA]=DET_ASIG!$B82),"No existe información")))} -> CONTABILIDAD DE COSTOS | P97: CONTABILIDAD SOCIAL Y AMBIENTAL | Q97: ADMINISTRACIÓN FINANCIERA | R97: FUNDAMENTOS DE AUDITORÍAS | S97: GESTIÓN DE TALENTO HUMANO
A98: {=TRANSPOSE(_xlfn.UNIQUE(_xlfn._xlws.FILTER(MAE_ASIGNATURA[ID_NIVEL],MAE_ASIGNATURA[ID_CARRERA]=DET_ASIG!$B83,"No existe información")))} -> 1 | B98: 2 | C98: 3 | D98: 4 | E98: 5 | F98: 6 | G98: 7 | H98: 8 | O98: {=TRANSPOSE(_xlfn.UNIQUE(_xlfn._xlws.FILTER(MAE_ASIGNATURA[NOM_ASIG],(MAE_ASIGNATURA[ID_NIVEL]=DET_ASIG!$D83)*(MAE_ASIGNATURA[ID_CARRERA]=DET_ASIG!$B83),"No existe información")))} -> CONTABILIDAD DE COSTOS | P98: CONTABILIDAD SOCIAL Y AMBIENTAL | Q98: ADMINISTRACIÓN FINANCIERA | R98: FUNDAMENTOS DE AUDITORÍAS | S98: GESTIÓN DE TALENTO HUMANO
A99: {=TRANSPOSE(_xlfn.UNIQUE(_xlfn._xlws.FILTER(MAE_ASIGNATURA[ID_NIVEL],MAE_ASIGNATURA[ID_CARRERA]=DET_ASIG!$B84,"No existe información")))} -> 1 | B99: 2 | C99: 3 | D99: 4 | E99: 5 | F99: 6 | G99: 7 | H99: 8 | O99: {=TRANSPOSE(_xlfn.UNIQUE(_xlfn._xlws.FILTER(MAE_ASIGNATURA[NOM_ASIG],(MAE_ASIGNATURA[ID_NIVEL]=DET_ASIG!$D84)*(MAE_ASIGNATURA[ID_CARRERA]=DET_ASIG!$B84),"No existe información")))} -> CONTABILIDAD DE COSTOS | P99: CONTABILIDAD SOCIAL Y AMBIENTAL | Q99: ADMINISTRACIÓN FINANCIERA | R99: FUNDAMENTOS DE AUDITORÍAS | S99: GESTIÓN DE TALENTO HUMANO
A100: {=TRANSPOSE(_xlfn.UNIQUE(_xlfn._xlws.FILTER(MAE_ASIGNATURA[ID_NIVEL],MAE_ASIGNATURA[ID_CARRERA]=DET_ASIG!$B85,"No existe información")))} -> 1 | B100: 2 | C100: 3 | D100: 4 | E100: 5 | F100: 6 | G100: 7 | H100: 8 | O100: {=TRANSPOSE(_xlfn.UNIQUE(_xlfn._xlws.FILTER(MAE_ASIGNATURA[NOM_ASIG],(MAE_ASIGNATURA[ID_NIVEL]=DET_ASIG!$D85)*(MAE_ASIGNATURA[ID_CARRERA]=DET_ASIG!$B85),"No existe información")))} -> CONTABILIDAD DE COSTOS | P100: CONTABILIDAD SOCIAL Y AMBIENTAL | Q100: ADMINISTRACIÓN FINANCIERA | R100: FUNDAMENTOS DE AUDITORÍAS | S100: GESTIÓN DE TALENTO HUMANO
A101: {=TRANSPOSE(_xlfn.UNIQUE(_xlfn._xlws.FILTER(MAE_ASIGNATURA[ID_NIVEL],MAE_ASIGNATURA[ID_CARRERA]=DET_ASIG!$B86,"No existe información")))} -> 1 | B101: 2 | C101: 3 | D101: 4 | E101: 5 | F101: 6 | G101: 7 | H101: 8 | O101: {=TRANSPOSE(_xlfn.UNIQUE(_xlfn._xlws.FILTER(MAE_ASIGNATURA[NOM_ASIG],(MAE_ASIGNATURA[ID_NIVEL]=DET_ASIG!$D86)*(MAE_ASIGNATURA[ID_CARRERA]=DET_ASIG!$B86),"No existe información")))} -> CONTABILIDAD DE COSTOS | P101: CONTABILIDAD SOCIAL Y AMBIENTAL | Q101: ADMINISTRACIÓN FINANCIERA | R101: FUNDAMENTOS DE AUDITORÍAS | S101: GESTIÓN DE TALENTO HUMANO
A102: {=TRANSPOSE(_xlfn.UNIQUE(_xlfn._xlws.FILTER(MAE_ASIGNATURA[ID_NIVEL],MAE_ASIGNATURA[ID_CARRERA]=DET_ASIG!$B87,"No existe información")))} -> 1 | B102: 2 | C102: 3 | D102: 4 | E102: 5 | F102: 6 | G102: 7 | H102: 8 | O102: {=TRANSPOSE(_xlfn.UNIQUE(_xlfn._xlws.FILTER(MAE_ASIGNATURA[NOM_ASIG],(MAE_ASIGNATURA[ID_NIVEL]=DET_ASIG!$D87)*(MAE_ASIGNATURA[ID_CARRERA]=DET_ASIG!$B87),"No existe información")))} -> PLANIFICACIÓN DE AUDITORÍAS | P102: CONTABILIDAD EN EL SECTOR PÚBLICO | Q102: GESTIÓN TRIBUTARIA | R102: PLANIFICACIÓN Y DIRECCIÓN ESTRATÉGICA | S102: ÉTICA PROFESIONAL
A103: {=TRANSPOSE(_xlfn.UNIQUE(_xlfn._xlws.FILTER(MAE_ASIGNATURA[ID_NIVEL],MAE_ASIGNATURA[ID_CARRERA]=DET_ASIG!$B88,"No existe información")))} -> 1 | B103: 2 | C103: 3 | D103: 4 | E103: 5 | F103: 6 | G103: 7 | H103: 8 | O103: {=TRANSPOSE(_xlfn.UNIQUE(_xlfn._xlws.FILTER(MAE_ASIGNATURA[NOM_ASIG],(MAE_ASIGNATURA[ID_NIVEL]=DET_ASIG!$D88)*(MAE_ASIGNATURA[ID_CARRERA]=DET_ASIG!$B88),"No existe información")))} -> PLANIFICACIÓN DE AUDITORÍAS | P103: CONTABILIDAD EN EL SECTOR PÚBLICO | Q103: GESTIÓN TRIBUTARIA | R103: PLANIFICACIÓN Y DIRECCIÓN ESTRATÉGICA | S103: ÉTICA PROFESIONAL
A104: {=TRANSPOSE(_xlfn.UNIQUE(_xlfn._xlws.FILTER(MAE_ASIGNATURA[ID_NIVEL],MAE_ASIGNATURA[ID_CARRERA]=DET_ASIG!$B89,"No existe información")))} -> 1 | B104: 2 | C104: 3 | D104: 4 | E104: 5 | F104: 6 | G104: 7 | H104: 8 | O104: {=TRANSPOSE(_xlfn.UNIQUE(_xlfn._xlws.FILTER(MAE_ASIGNATURA[NOM_ASIG],(MAE_ASIGNATURA[ID_NIVEL]=DET_ASIG!$D89)*(MAE_ASIGNATURA[ID_CARRERA]=DET_ASIG!$B89),"No existe información")))} -> PLANIFICACIÓN DE AUDITORÍAS | P104: CONTABILIDAD EN EL SECTOR PÚBLICO | Q104: GESTIÓN TRIBUTARIA | R104: PLANIFICACIÓN Y DIRECCIÓN ESTRATÉGICA | S104: ÉTICA PROFESIONAL
...

Sheet MAE_CARRERA
A1: ID_CARRERA | B1: NOMBRE_CARRERA | C1: SEMANAS | D1: TOTAL HORAS | E1: FECHA_INICIO | F1: FECHA_FIN | G1: ESTADO
A2: FCACC-AD-EM | B2: ADMINISTRACIÓN DE EMPRESAS | C2: 16 | D2: 240 | E2: 43831 | F2: 51501 | G2: Vigente
A3: FCACC-AU-CO-GE | B3: AUDITORÍA Y CONTROL DE GESTIÓN 2024 NS | C3: 16 | D3: 240 | E3: 43831 | F3: 51501 | G3: Vigente
A4: FCACC-BI-RA | B4: BIENES RAICES | C4: 16 | D4: 240 | E4: 43831 | F4: 51501 | G4: Vigente
A5: FCACC-CO-EX | B5: COMERCIO EXTERIOR | C5: 16 | D5: 240 | E5: 43831 | F5: 51501 | G5: Vigente
A6: FCACC-CO-AD | B6: CONTABILIDAD Y AUDITORÍA 2024 NS | C6: 16 | D6: 240 | E6: 43831 | F6: 51501 | G6: Vigente
A7: FCACC-FINA | B7: FINANZAS 2024 NS | C7: 16 | D7: 240 | E7: 43831 | F7: 51501 | G7: Vigente
A8: FCACC-GE-IN-GE | B8: GESTION DE LA INFORMACIÓN GERENCIA - 2024 | C8: 16 | D8: 240 | E8: 43831 | F8: 51501 | G8: Vigente
A9: FCACC-GE-TA-HU | B9: GESTIÓN DEL TALENTO HUMANO | C9: 16 | D9: 240 | E9: 43831 | F9: 51501 | G9: Vigente
A10: FCACC-MA | B10: MARKETING | C10: 16 | D10: 240 | E10: 43831 | F10: 51501 | G10: Vigente
A11: FCACC-1-DO-CL | B11: 1. Docencia - Clases | C11: 1 | D11: 1 | E11: 43831 | F11: 51501 | G11: Vigente
A12: FCACC-5-DO-PE-IN | B12: 5. Docencia - Uso pedagógico de la investigación | C12: 1 | D12: 1 | E12: 43831 | F12: 51501 | G12: Vigente
A13: FCACC-4-DO-TU-TI | B13: 4. Docencia - Tutoría de titulación | C13: 1 | D13: 1 | E13: 43831 | F13: 51501 | G13: Vigente
... A18: FCACC-8-TITU | B18: Titulación | C18: 1 | D18: 1 | E18: 43831 | F18: 51501 | G18: Vigente

Sheet MAE_ASIGNATURA
A1: ID_ASIG | B1: NOM_ASIG | C1: HORAS | D1: semanas | E1: ID_CARRERA | F1: NOMBRE_CARRERA | G1: ID_NIVEL
A2: FCACC-AD-EM-NI-1-CONTA-DE -COS | B2: CONTABILIDAD DE COSTOS | C2: 4 | D2: 16 | E2: FCACC-AD-EM | F2: ADMINISTRACIÓN DE EMPRESAS | G2: 1
A3: FCACC-AD-EM-NI-1-MATEM-APL-A L | B3: MATEMÁTICA APLICADA A LA ADMINISTRACIÓN | C3: 4 | D3: 16 | E3: FCACC-AD-EM | F3: ADMINISTRACIÓN DE EMPRESAS | G3: 1
A4: FCACC-AD-EM-NI-1-ADMIN-PAR-LOS | B4: ADMINISTRACIÓN PARA LOS NEGOCIOS | C4: 4 | D4: 16 | E4: FCACC-AD-EM | F4: ADMINISTRACIÓN DE EMPRESAS | G4: 1
A5: FCACC-AD-EM-NI-1-METOD-DE -LA | B5: METODOLOGÍA DE LA INVESTIGACIÓN | C5: 4 | D5: 16 | E5: FCACC-AD-EM | F5: ADMINISTRACIÓN DE EMPRESAS | G5: 1
A6: FCACC-AD-EM-NI-1-MICRO | B6: MICROECONOMÍA | C6: 4 | D6: 16 | E6: FCACC-AD-EM | F6: ADMINISTRACIÓN DE EMPRESAS | G6: 1
A7: FCACC-AD-EM-NI-2-CONTA-FIN | B7: CONTABILIDAD FINANCIERA | C7: 3 | D7: 16 | E7: FCACC-AD-EM | F7: ADMINISTRACIÓN DE EMPRESAS | G7: 2
A8: FCACC-AD-EM-NI-2-MATEM-FIN | B8: MATEMÁTICA FINANCIERA | C8: 4 | D8: 16 | E8: FCACC-AD-EM | F8: ADMINISTRACIÓN DE EMPRESAS | G8: 2
A9: FCACC-AD-EM-NI-2-ADMIN-EST | B9: ADMINISTRACIÓN ESTRATÉGICA | C9: 4 | D9: 16 | E9: FCACC-AD-EM | F9: ADMINISTRACIÓN DE EMPRESAS | G9: 2
A10: FCACC-AD-EM-NI-2-ESTAD-APL-A | B10: ESTADÍSTICA APLICADA A LA ADMINISTRACIÓN | C10: 3 | D10: 16 | E10: FCACC-AD-EM | F10: ADMINISTRACIÓN DE EMPRESAS | G10: 2
A11: FCACC-AD-EM-NI-2-MACRO | B11: MACROECONOMÍA | C11: 3 | D11: 16 | E11: FCACC-AD-EM | F11: ADMINISTRACIÓN DE EMPRESAS | G11: 2
A12: FCACC-AD-EM-NI-2-DEREC-MER-Y S | B12: DERECHO MERCANTIL Y SOCIETARIO | C12: 3 | D12: 16 | E12: FCACC-AD-EM | F12: ADMINISTRACIÓN DE EMPRESAS | G12: 2
A13: FCACC-AD-EM-NI-3-CREAT-E I-INN | B13: CREATIVIDAD E INNOVACIÓN EMPRESARIAL | C13: 4 | D13: 16 | E13: FCACC-AD-EM | F13: ADMINISTRACIÓN DE EMPRESAS | G13: 3
... A353: FCACC-8-TITU-NI-8-Traba-de -int | B353: Trabajo de integración curricular: Fase de resultados e informe CA-22 | C353: 1 | D353: 16 | E353: FCACC-8-TITU | F353: Titulación | G353: 8

Sheet MAE_CONOCIMIENTO
A1: ID_DDETALLADO | B1: CAMPO_DETALLADO
A2: F-C-D-ADM | B2: ADMINISTRACIÓN
A3: F-C-D-ADM-EN -E-C | B3: ADMINISTRACIÓN EN E-COMMERCE
A4: F-C-D-AUD-DE -TEC | B4: AUDITORÍA DE TECNOLOGÍAS
A5: F-C-D-BIB-DOC | B5: BIBLIOTECOLOGÍA, DOCUMENTACIÓN Y ARCHIVOLOGÍA
A6: F-C-D-CIE-COM | B6: CIENCIAS COMPUTACIONALES
A7: F-C-D-CIE-DEL-MED | B7: CIENCIAS DEL MEDIO AMBIENTE
A8: F-C-D-CIE-POL | B8: CIENCIAS POLÍTICAS
A9: F-C-D-COM | B9: COMERCIO
A10: F-C-D-COM-Y N-NEG | B10: COMERCIO Y NEGOCIOS INTERNACIONAL
A11: F-C-D-COM-LAB | B11: COMPETENCIAS LABORALES
A12: F-C-D-CON-Y A-AUD | B12: CONTABILIDAD Y AUDITORÍA
... A34: F-C-D-GES-DE -LA | B34: GESTIÓN DE LA CIENCIA Y LA TECNOLOGÍA
A35: F-C-D-
A36: F-C-D-
A37: F-C-D-
A38: F-C-D-
A39: F-C-D-
A40: F-C-D-
A41: F-C-D-
A42: F-C-D-
A43: F-C-D-
A44: F-C-D-
