Workbook

Sheet ASIGNACION
A1: N° | B1: CARRERA | C1: ID_CARRERA | D1: NIVEL | E1: PARALELO | F1: ASIGNATURA | G1: ID_ASIG_CAM_DET | H1: CAMPO | I1: AFINIDAD/DOCENCIA | J1: HORAS | K1: CALCULAR HORA | L1: TOTAL | M1: NOMBRE_DOCENT | N1: TIPO DOCENTE | O1: ESTUDIO DOCENTE | P1: TOTAL ASIGNATURA | Q1: HORAS NO AFINIDAD | R1: HORAS UNIDAD BASICA | S1: HORAS ACTIVIDAD | T1: HORAS AFINIDAD | U1: TOTAL HORAS CLASES | V1: TOTAL HORAS | W1: CEDULA_DOCENTE
A2: 1 | B2: CONTABILIDAD Y AUDITORÍA 2024 NS | C2: =_xlfn.XLOOKUP(Tabla1[[#This Row],[CARRERA]],MAE_CARRERA[NOMBRE_CARRERA],MAE_CARRERA[ID_CARRERA],"Seleccione Carrera") -> FCACC-CO-AD | D2: 1 | E2: A | F2: CONTABILIDAD BÁSICA | G2: =_xlfn.XLOOKUP(Tabla1[[#This Row],[ASIGNATURA]],MAE_ASIGNATURA[NOM_ASIG],MAE_ASIGNATURA[ID_ASIG],"Seleccione Asignatura") -> FCACC-CO-AD-NI-1-CONTA-BÁS | H2: {=_xlfn.TEXTJOIN("; ",TRUE,TRANSPOSE(_xlfn.UNIQUE(_xlfn._xlws.FILTER(DET_ASIG[DETALLADO],(DET_ASIG[NIVEL]=ASIGNACION!$D2)*(DET_ASIG[ID_CARRERA]=ASIGNACION!$C2)*(DET_ASIG[ID_ASIG]=ASIGNACION!$G2),"No existe información"))))} -> UNIDAD BASICA | I2: NO | J2: =_xlfn.XLOOKUP(Tabla1[[#This Row],[ID_ASIG_CAM_DET]],MAE_ASIGNATURA[ID_ASIG],MAE_ASIGNATURA[HORAS],0) -> 7 | K2: 1 | L2: =+Tabla1[[#This Row],[CALCULAR HORA]]*Tabla1[[#This Row],[HORAS]] -> 7 | M2: CACERES LARREATEGUI ALBA LUCIA | N2: =_xlfn.XLOOKUP(Tabla1[[#This Row],[NOMBRE_DOCENT]],MDOCENTES[DATOS_DOCENTE],MDOCENTES[DEDICACION],"Seleccione Docente") -> TC | O2: =_xlfn.XLOOKUP(Tabla1[[#This Row],[NOMBRE_DOCENT]],MDOCENTES[DATOS_DOCENTE],MDOCENTES[ESTUDIO],"Seleccione Docente") -> MAESTRÍA | P2: =COUNTIFS($M:$M, M2, $H:$H, "<>ACTIVIDAD") -> 4 | Q2: =SUMIFS($L:$L, $M:$M, M2, $I:$I, "NO",$H:$H,"<>UNIDAD BASICA") -> 0 | R2: =SUMIFS($L:$L, $M:$M, M2, $H:$H, "UNIDAD BASICA",$I:$I,"NO") -> 16 | S2: =SUMIFS($L:$L, $M:$M, M2, $I:$I, "ACTIVIDAD") -> 9 | T2: =SUMIFS($L:$L, $M:$M, M2, $I:$I, "SI") -> 0 | U2: =Tabla1[[#This Row],[HORAS NO AFINIDAD]]+Tabla1[[#This Row],[HORAS UNIDAD BASICA]]+Tabla1[[#This Row],[HORAS AFINIDAD]] -> 16 | V2: =+Tabla1[[#This Row],[HORAS AFINIDAD]]+Tabla1[[#This Row],[HORAS ACTIVIDAD]]+Tabla1[[#This Row],[HORAS UNIDAD BASICA]]+Tabla1[[#This Row],[HORAS NO AFINIDAD]] -> 25 | W2: =_xlfn.XLOOKUP(Tabla1[[#This Row],[NOMBRE_DOCENT]],EDU_DOCENTE[NOMBRE_DOCENTE],EDU_DOCENTE[IDENTIFICACION],"Seleccione Docente") -> Seleccione Docente
A3: 2 | B3: CONTABILIDAD Y AUDITORÍA 2024 NS | C3: =_xlfn.XLOOKUP(Tabla1[[#This Row],[CARRERA]],MAE_CARRERA[NOMBRE_CARRERA],MAE_CARRERA[ID_CARRERA],"Seleccione Carrera") -> FCACC-CO-AD | D3: 1 | E3: A | F3: METODOLOGÍA DE LA INVESTIGACIÓN | G3: =_xlfn.XLOOKUP(Tabla1[[#This Row],[ASIGNATURA]],MAE_ASIGNATURA[NOM_ASIG],MAE_ASIGNATURA[ID_ASIG],"Seleccione Asignatura") -> FCACC-AD-EM-NI-1-METOD-DE -LA | H3: {=_xlfn.TEXTJOIN("; ",TRUE,TRANSPOSE(_xlfn.UNIQUE(_xlfn._xlws.FILTER(DET_ASIG[DETALLADO],(DET_ASIG[NIVEL]=ASIGNACION!$D3)*(DET_ASIG[ID_CARRERA]=ASIGNACION!$C3)*(DET_ASIG[ID_ASIG]=ASIGNACION!$G3),"No existe información"))))} -> UNIDAD BASICA | I3: NO | J3: =_xlfn.XLOOKUP(Tabla1[[#This Row],[ID_ASIG_CAM_DET]],MAE_ASIGNATURA[ID_ASIG],MAE_ASIGNATURA[HORAS],0) -> 4 | K3: 1 | L3: =+Tabla1[[#This Row],[CALCULAR HORA]]*Tabla1[[#This Row],[HORAS]] -> 4 | M3: CARRILLO PICO FEDERICO AVELINO | N3: =_xlfn.XLOOKUP(Tabla1[[#This Row],[NOMBRE_DOCENT]],MDOCENTES[DATOS_DOCENTE],MDOCENTES[DEDICACION],"Seleccione Docente") -> TC | O3: =_xlfn.XLOOKUP(Tabla1[[#This Row],[NOMBRE_DOCENT]],MDOCENTES[DATOS_DOCENTE],MDOCENTES[ESTUDIO],"Seleccione Docente") -> MAESTRÍA | P3: =COUNTIFS($M:$M, M3, $H:$H, "<>ACTIVIDAD") -> 2 | Q3: =SUMIFS($L:$L, $M:$M, M3, $I:$I, "NO",$H:$H,"<>UNIDAD BASICA") -> 0 | R3: =SUMIFS($L:$L, $M:$M, M3, $H:$H, "UNIDAD BASICA",$I:$I,"NO") -> 8 | S3: =SUMIFS($L:$L, $M:$M, M3, $I:$I, "ACTIVIDAD") -> 0 | T3: =SUMIFS($L:$L, $M:$M, M3, $I:$I, "SI") -> 0 | U3: =Tabla1[[#This Row],[HORAS NO AFINIDAD]]+Tabla1[[#This Row],[HORAS UNIDAD BASICA]]+Tabla1[[#This Row],[HORAS AFINIDAD]] -> 8 | V3: =+Tabla1[[#This Row],[HORAS AFINIDAD]]+Tabla1[[#This Row],[HORAS ACTIVIDAD]]+Tabla1[[#This Row],[HORAS UNIDAD BASICA]]+Tabla1[[#This Row],[HORAS NO AFINIDAD]] -> 8 | W3: =_xlfn.XLOOKUP(Tabla1[[#This Row],[NOMBRE_DOCENT]],EDU_DOCENTE[NOMBRE_DOCENTE],EDU_DOCENTE[IDENTIFICACION],"Seleccione Docente") -> Seleccione Docente
A4: 3 | B4: CONTABILIDAD Y AUDITORÍA 2024 NS | C4: =_xlfn.XLOOKUP(Tabla1[[#This Row],[CARRERA]],MAE_CARRERA[NOMBRE_CARRERA],MAE_CARRERA[ID_CARRERA],"Seleccione Carrera") -> FCACC-CO-AD | D4: 1 | E4: A | F4: ADMINISTRACIÓN | G4: =_xlfn.XLOOKUP(Tabla1[[#This Row],[ASIGNATURA]],MAE_ASIGNATURA[NOM_ASIG],MAE_ASIGNATURA[ID_ASIG],"Seleccione Asignatura") -> FCACC-CO-AD-NI-1-ADMIN | H4: {=_xlfn.TEXTJOIN("; ",TRUE,TRANSPOSE(_xlfn.UNIQUE(_xlfn._xlws.FILTER(DET_ASIG[DETALLADO],(DET_ASIG[NIVEL]=ASIGNACION!$D4)*(DET_ASIG[ID_CARRERA]=ASIGNACION!$C4)*(DET_ASIG[ID_ASIG]=ASIGNACION!$G4),"No existe información"))))} -> UNIDAD BASICA | I4: NO | J4: =_xlfn.XLOOKUP(Tabla1[[#This Row],[ID_ASIG_CAM_DET]],MAE_ASIGNATURA[ID_ASIG],MAE_ASIGNATURA[HORAS],0) -> 2 | K4: 1 | L4: =+Tabla1[[#This Row],[CALCULAR HORA]]*Tabla1[[#This Row],[HORAS]] -> 2 | M4: CACERES LARREATEGUI ALBA LUCIA | N4: =_xlfn.XLOOKUP(Tabla1[[#This Row],[NOMBRE_DOCENT]],MDOCENTES[DATOS_DOCENTE],MDOCENTES[DEDICACION],"Seleccione Docente") -> TC | O4: =_xlfn.XLOOKUP(Tabla1[[#This Row],[NOMBRE_DOCENT]],MDOCENTES[DATOS_DOCENTE],MDOCENTES[ESTUDIO],"Seleccione Docente") -> MAESTRÍA | P4: =COUNTIFS($M:$M, M4, $H:$H, "<>ACTIVIDAD") -> 4 | Q4: =SUMIFS($L:$L, $M:$M, M4, $I:$I, "NO",$H:$H,"<>UNIDAD BASICA") -> 0 | R4: =SUMIFS($L:$L, $M:$M, M4, $H:$H, "UNIDAD BASICA",$I:$I,"NO") -> 16 | S4: =SUMIFS($L:$L, $M:$M, M4, $I:$I, "ACTIVIDAD") -> 9 | T4: =SUMIFS($L:$L, $M:$M, M4, $I:$I, "SI") -> 0 | U4: =Tabla1[[#This Row],[HORAS NO AFINIDAD]]+Tabla1[[#This Row],[HORAS UNIDAD BASICA]]+Tabla1[[#This Row],[HORAS AFINIDAD]] -> 16 | V4: =+Tabla1[[#This Row],[HORAS AFINIDAD]]+Tabla1[[#This Row],[HORAS ACTIVIDAD]]+Tabla1[[#This Row],[HORAS UNIDAD BASICA]]+Tabla1[[#This Row],[HORAS NO AFINIDAD]] -> 25 | W4: =_xlfn.XLOOKUP(Tabla1[[#This Row],[NOMBRE_DOCENT]],EDU_DOCENTE[NOMBRE_DOCENTE],EDU_DOCENTE[IDENTIFICACION],"Seleccione Docente") -> Seleccione Docente
A5: 4 | B5: CONTABILIDAD Y AUDITORÍA 2024 NS | C5: =_xlfn.XLOOKUP(Tabla1[[#This Row],[CARRERA]],MAE_CARRERA[NOMBRE_CARRERA],MAE_CARRERA[ID_CARRERA],"Seleccione Carrera") -> FCACC-CO-AD | D5: 1 | E5: B | F5: ADMINISTRACIÓN | G5: =_xlfn.XLOOKUP(Tabla1[[#This Row],[ASIGNATURA]],MAE_ASIGNATURA[NOM_ASIG],MAE_ASIGNATURA[ID_ASIG],"Seleccione Asignatura") -> FCACC-CO-AD-NI-1-ADMIN | H5: {=_xlfn.TEXTJOIN("; ",TRUE,TRANSPOSE(_xlfn.UNIQUE(_xlfn._xlws.FILTER(DET_ASIG[DETALLADO],(DET_ASIG[NIVEL]=ASIGNACION!$D5)*(DET_ASIG[ID_CARRERA]=ASIGNACION!$C5)*(DET_ASIG[ID_ASIG]=ASIGNACION!$G5),"No existe información"))))} -> UNIDAD BASICA | I5: NO | J5: =_xlfn.XLOOKUP(Tabla1[[#This Row],[ID_ASIG_CAM_DET]],MAE_ASIGNATURA[ID_ASIG],MAE_ASIGNATURA[HORAS],0) -> 2 | K5: 1 | L5: =+Tabla1[[#This Row],[CALCULAR HORA]]*Tabla1[[#This Row],[HORAS]] -> 2 | M5: CACERES LARREATEGUI ALBA LUCIA | N5: =_xlfn.XLOOKUP(Tabla1[[#This Row],[NOMBRE_DOCENT]],MDOCENTES[DATOS_DOCENTE],MDOCENTES[DEDICACION],"Seleccione Docente") -> TC | O5: =_xlfn.XLOOKUP(Tabla1[[#This Row],[NOMBRE_DOCENT]],MDOCENTES[DATOS_DOCENTE],MDOCENTES[ESTUDIO],"Seleccione Docente") -> MAESTRÍA | P5: =COUNTIFS($M:$M, M5, $H:$H, "<>ACTIVIDAD") -> 4 | Q5: =SUMIFS($L:$L, $M:$M, M5, $I:$I, "NO",$H:$H,"<>UNIDAD BASICA") -> 0 | R5: =SUMIFS($L:$L, $M:$M, M5, $H:$H, "UNIDAD BASICA",$I:$I,"NO") -> 16 | S5: =SUMIFS($L:$L, $M:$M, M5, $I:$I, "ACTIVIDAD") -> 9 | T5: =SUMIFS($L:$L, $M:$M, M5, $I:$I, "SI") -> 0 | U5: =Tabla1[[#This Row],[HORAS NO AFINIDAD]]+Tabla1[[#This Row],[HORAS UNIDAD BASICA]]+Tabla1[[#This Row],[HORAS AFINIDAD]] -> 16 | V5: =+Tabla1[[#This Row],[HORAS AFINIDAD]]+Tabla1[[#This Row],[HORAS ACTIVIDAD]]+Tabla1[[#This Row],[HORAS UNIDAD BASICA]]+Tabla1[[#This Row],[HORAS NO AFINIDAD]] -> 25 | W5: =_xlfn.XLOOKUP(Tabla1[[#This Row],[NOMBRE_DOCENT]],EDU_DOCENTE[NOMBRE_DOCENTE],EDU_DOCENTE[IDENTIFICACION],"Seleccione Docente") -> Seleccione Docente
A6: 5 | B6: CONTABILIDAD Y AUDITORÍA 2024 NS | C6: =_xlfn.XLOOKUP(Tabla1[[#This Row],[CARRERA]],MAE_CARRERA[NOMBRE_CARRERA],MAE_CARRERA[ID_CARRERA],"Seleccione Carrera") -> FCACC-CO-AD | D6: 1 | E6: B | F6: MATEMÁTICA | G6: =_xlfn.XLOOKUP(Tabla1[[#This Row],[ASIGNATURA]],MAE_ASIGNATURA[NOM_ASIG],MAE_ASIGNATURA[ID_ASIG],"Seleccione Asignatura") -> FCACC-CO-EX-NI-1-MATEM | H6: {=_xlfn.TEXTJOIN("; ",TRUE,TRANSPOSE(_xlfn.UNIQUE(_xlfn._xlws.FILTER(DET_ASIG[DETALLADO],(DET_ASIG[NIVEL]=ASIGNACION!$D6)*(DET_ASIG[ID_CARRERA]=ASIGNACION!$C6)*(DET_ASIG[ID_ASIG]=ASIGNACION!$G6),"No existe información"))))} -> UNIDAD BASICA | I6: NO | J6: =_xlfn.XLOOKUP(Tabla1[[#This Row],[ID_ASIG_CAM_DET]],MAE_ASIGNATURA[ID_ASIG],MAE_ASIGNATURA[HORAS],0) -> 5 | K6: 1 | L6: =+Tabla1[[#This Row],[CALCULAR HORA]]*Tabla1[[#This Row],[HORAS]] -> 5 | M6: CACERES LARREATEGUI ALBA LUCIA | N6: =_xlfn.XLOOKUP(Tabla1[[#This Row],[NOMBRE_DOCENT]],MDOCENTES[DATOS_DOCENTE],MDOCENTES[DEDICACION],"Seleccione Docente") -> TC | O6: =_xlfn.XLOOKUP(Tabla1[[#This Row],[NOMBRE_DOCENT]],MDOCENTES[DATOS_DOCENTE],MDOCENTES[ESTUDIO],"Seleccione Docente") -> MAESTRÍA | P6: =COUNTIFS($M:$M, M6, $H:$H, "<>ACTIVIDAD") -> 4 | Q6: =SUMIFS($L:$L, $M:$M, M6, $I:$I, "NO",$H:$H,"<>UNIDAD BASICA") -> 0 | R6: =SUMIFS($L:$L, $M:$M, M6, $H:$H, "UNIDAD BASICA",$I:$I,"NO") -> 16 | S6: =SUMIFS($L:$L, $M:$M, M6, $I:$I, "ACTIVIDAD") -> 9 | T6: =SUMIFS($L:$L, $M:$M, M6, $I:$I, "SI") -> 0 | U6: =Tabla1[[#This Row],[HORAS NO AFINIDAD]]+Tabla1[[#This Row],[HORAS UNIDAD BASICA]]+Tabla1[[#This Row],[HORAS AFINIDAD]] -> 16 | V6: =+Tabla1[[#This Row],[HORAS AFINIDAD]]+Tabla1[[#This Row],[HORAS ACTIVIDAD]]+Tabla1[[#This Row],[HORAS UNIDAD BASICA]]+Tabla1[[#This Row],[HORAS NO AFINIDAD]] -> 25 | W6: =_xlfn.XLOOKUP(Tabla1[[#This Row],[NOMBRE_DOCENT]],EDU_DOCENTE[NOMBRE_DOCENTE],EDU_DOCENTE[IDENTIFICACION],"Seleccione Docente") -> Seleccione Docente
A7: 6 | B7: CONTABILIDAD Y AUDITORÍA 2024 NS | C7: =_xlfn.XLOOKUP(Tabla1[[#This Row],[CARRERA]],MAE_CARRERA[NOMBRE_CARRERA],MAE_CARRERA[ID_CARRERA],"Seleccione Carrera") -> FCACC-CO-AD | D7: 1 | E7: A | F7: METODOLOGÍA DE LA INVESTIGACIÓN | G7: =_xlfn.XLOOKUP(Tabla1[[#This Row],[ASIGNATURA]],MAE_ASIGNATURA[NOM_ASIG],MAE_ASIGNATURA[ID_ASIG],"Seleccione Asignatura") -> FCACC-AD-EM-NI-1-METOD-DE -LA | H7: {=_xlfn.TEXTJOIN("; ",TRUE,TRANSPOSE(_xlfn.UNIQUE(_xlfn._xlws.FILTER(DET_ASIG[DETALLADO],(DET_ASIG[NIVEL]=ASIGNACION!$D7)*(DET_ASIG[ID_CARRERA]=ASIGNACION!$C7)*(DET_ASIG[ID_ASIG]=ASIGNACION!$G7),"No existe información"))))} -> UNIDAD BASICA | I7: NO | J7: =_xlfn.XLOOKUP(Tabla1[[#This Row],[ID_ASIG_CAM_DET]],MAE_ASIGNATURA[ID_ASIG],MAE_ASIGNATURA[HORAS],0) -> 4 | K7: 1 | L7: =+Tabla1[[#This Row],[CALCULAR HORA]]*Tabla1[[#This Row],[HORAS]] -> 4 | M7: CARRILLO PICO FEDERICO AVELINO | N7: =_xlfn.XLOOKUP(Tabla1[[#This Row],[NOMBRE_DOCENT]],MDOCENTES[DATOS_DOCENTE],MDOCENTES[DEDICACION],"Seleccione Docente") -> TC | O7: =_xlfn.XLOOKUP(Tabla1[[#This Row],[NOMBRE_DOCENT]],MDOCENTES[DATOS_DOCENTE],MDOCENTES[ESTUDIO],"Seleccione Docente") -> MAESTRÍA | P7: =COUNTIFS($M:$M, M7, $H:$H, "<>ACTIVIDAD") -> 2 | Q7: =SUMIFS($L:$L, $M:$M, M7, $I:$I, "NO",$H:$H,"<>UNIDAD BASICA") -> 0 | R7: =SUMIFS($L:$L, $M:$M, M7, $H:$H, "UNIDAD BASICA",$I:$I,"NO") -> 8 | S7: =SUMIFS($L:$L, $M:$M, M7, $I:$I, "ACTIVIDAD") -> 0 | T7: =SUMIFS($L:$L, $M:$M, M7, $I:$I, "SI") -> 0 | U7: =Tabla1[[#This Row],[HORAS NO AFINIDAD]]+Tabla1[[#This Row],[HORAS UNIDAD BASICA]]+Tabla1[[#This Row],[HORAS AFINIDAD]] -> 8 | V7: =+Tabla1[[#This Row],[HORAS AFINIDAD]]+Tabla1[[#This Row],[HORAS ACTIVIDAD]]+Tabla1[[#This Row],[HORAS UNIDAD BASICA]]+Tabla1[[#This Row],[HORAS NO AFINIDAD]] -> 8 | W7: =_xlfn.XLOOKUP(Tabla1[[#This Row],[NOMBRE_DOCENT]],EDU_DOCENTE[NOMBRE_DOCENTE],EDU_DOCENTE[IDENTIFICACION],"Seleccione Docente") -> Seleccione Docente
A8: 7 | B8: 1. Docencia - Clases | C8: =_xlfn.XLOOKUP(Tabla1[[#This Row],[CARRERA]],MAE_CARRERA[NOMBRE_CARRERA],MAE_CARRERA[ID_CARRERA],"Seleccione Carrera") -> FCACC-1-DO-CL | D8: 0 | F8: AD4 Preparación de Clases | G8: =_xlfn.XLOOKUP(Tabla1[[#This Row],[ASIGNATURA]],MAE_ASIGNATURA[NOM_ASIG],MAE_ASIGNATURA[ID_ASIG],"Seleccione Asignatura") -> FCACC-1-DO-CL-NI-0-AD4 P-Pre-de | H8: {=_xlfn.TEXTJOIN("; ",TRUE,TRANSPOSE(_xlfn.UNIQUE(_xlfn._xlws.FILTER(DET_ASIG[DETALLADO],(DET_ASIG[NIVEL]=ASIGNACION!$D8)*(DET_ASIG[ID_CARRERA]=ASIGNACION!$C8)*(DET_ASIG[ID_ASIG]=ASIGNACION!$G8),"No existe información"))))} -> ACTIVIDAD | I8: ACTIVIDAD | J8: =_xlfn.XLOOKUP(Tabla1[[#This Row],[ID_ASIG_CAM_DET]],MAE_ASIGNATURA[ID_ASIG],MAE_ASIGNATURA[HORAS],0) -> 1 | K8: 3 | L8: =+Tabla1[[#This Row],[CALCULAR HORA]]*Tabla1[[#This Row],[HORAS]] -> 3 | M8: CACERES LARREATEGUI ALBA LUCIA | N8: =_xlfn.XLOOKUP(Tabla1[[#This Row],[NOMBRE_DOCENT]],MDOCENTES[DATOS_DOCENTE],MDOCENTES[DEDICACION],"Seleccione Docente") -> TC | O8: =_xlfn.XLOOKUP(Tabla1[[#This Row],[NOMBRE_DOCENT]],MDOCENTES[DATOS_DOCENTE],MDOCENTES[ESTUDIO],"Seleccione Docente") -> MAESTRÍA | P8: =COUNTIFS($M:$M, M8, $H:$H, "<>ACTIVIDAD") -> 4 | Q8: =SUMIFS($L:$L, $M:$M, M8, $I:$I, "NO",$H:$H,"<>UNIDAD BASICA") -> 0 | R8: =SUMIFS($L:$L, $M:$M, M8, $H:$H, "UNIDAD BASICA",$I:$I,"NO") -> 16 | S8: =SUMIFS($L:$L, $M:$M, M8, $I:$I, "ACTIVIDAD") -> 9 | T8: =SUMIFS($L:$L, $M:$M, M8, $I:$I, "SI") -> 0 | U8: =Tabla1[[#This Row],[HORAS NO AFINIDAD]]+Tabla1[[#This Row],[HORAS UNIDAD BASICA]]+Tabla1[[#This Row],[HORAS AFINIDAD]] -> 16 | V8: =+Tabla1[[#This Row],[HORAS AFINIDAD]]+Tabla1[[#This Row],[HORAS ACTIVIDAD]]+Tabla1[[#This Row],[HORAS UNIDAD BASICA]]+Tabla1[[#This Row],[HORAS NO AFINIDAD]] -> 25 | W8: =_xlfn.XLOOKUP(Tabla1[[#This Row],[NOMBRE_DOCENT]],EDU_DOCENTE[NOMBRE_DOCENTE],EDU_DOCENTE[IDENTIFICACION],"Seleccione Docente") -> Seleccione Docente
A9: 8 | B9: 1. Docencia - Clases | C9: =_xlfn.XLOOKUP(Tabla1[[#This Row],[CARRERA]],MAE_CARRERA[NOMBRE_CARRERA],MAE_CARRERA[ID_CARRERA],"Seleccione Carrera") -> FCACC-1-DO-CL | D9: 0 | F9: AD5 Elaboración y calificación de evaluaciones | G9: =_xlfn.XLOOKUP(Tabla1[[#This Row],[ASIGNATURA]],MAE_ASIGNATURA[NOM_ASIG],MAE_ASIGNATURA[ID_ASIG],"Seleccione Asignatura") -> FCACC-1-DO-CL-NI-0-AD5 E-Ela-y c | H9: {=_xlfn.TEXTJOIN("; ",TRUE,TRANSPOSE(_xlfn.UNIQUE(_xlfn._xlws.FILTER(DET_ASIG[DETALLADO],(DET_ASIG[NIVEL]=ASIGNACION!$D9)*(DET_ASIG[ID_CARRERA]=ASIGNACION!$C9)*(DET_ASIG[ID_ASIG]=ASIGNACION!$G9),"No existe información"))))} -> ACTIVIDAD | I9: ACTIVIDAD | J9: =_xlfn.XLOOKUP(Tabla1[[#This Row],[ID_ASIG_CAM_DET]],MAE_ASIGNATURA[ID_ASIG],MAE_ASIGNATURA[HORAS],0) -> 1 | K9: 3 | L9: =+Tabla1[[#This Row],[CALCULAR HORA]]*Tabla1[[#This Row],[HORAS]] -> 3 | M9: CACERES LARREATEGUI ALBA LUCIA | N9: =_xlfn.XLOOKUP(Tabla1[[#This Row],[NOMBRE_DOCENT]],MDOCENTES[DATOS_DOCENTE],MDOCENTES[DEDICACION],"Seleccione Docente") -> TC | O9: =_xlfn.XLOOKUP(Tabla1[[#This Row],[NOMBRE_DOCENT]],MDOCENTES[DATOS_DOCENTE],MDOCENTES[ESTUDIO],"Seleccione Docente") -> MAESTRÍA | P9: =COUNTIFS($M:$M, M9, $H:$H, "<>ACTIVIDAD") -> 4 | Q9: =SUMIFS($L:$L, $M:$M, M9, $I:$I, "NO",$H:$H,"<>UNIDAD BASICA") -> 0 | R9: =SUMIFS($L:$L, $M:$M, M9, $H:$H, "UNIDAD BASICA",$I:$I,"NO") -> 16 | S9: =SUMIFS($L:$L, $M:$M, M9, $I:$I, "ACTIVIDAD") -> 9 | T9: =SUMIFS($L:$L, $M:$M, M9, $I:$I, "SI") -> 0 | U9: =Tabla1[[#This Row],[HORAS NO AFINIDAD]]+Tabla1[[#This Row],[HORAS UNIDAD BASICA]]+Tabla1[[#This Row],[HORAS AFINIDAD]] -> 16 | V9: =+Tabla1[[#This Row],[HORAS AFINIDAD]]+Tabla1[[#This Row],[HORAS ACTIVIDAD]]+Tabla1[[#This Row],[HORAS UNIDAD BASICA]]+Tabla1[[#This Row],[HORAS NO AFINIDAD]] -> 25
A10: 9 | B10: 1. Docencia - Clases | C10: =_xlfn.XLOOKUP(Tabla1[[#This Row],[CARRERA]],MAE_CARRERA[NOMBRE_CARRERA],MAE_CARRERA[ID_CARRERA],"Seleccione Carrera") -> FCACC-1-DO-CL | D10: 0 | F10: AD6 Orientación a través de Tutorías | G10: =_xlfn.XLOOKUP(Tabla1[[#This Row],[ASIGNATURA]],MAE_ASIGNATURA[NOM_ASIG],MAE_ASIGNATURA[ID_ASIG],"Seleccione Asignatura") -> FCACC-1-DO-CL-NI-0-AD6 O-Ori-a t | H10: {=_xlfn.TEXTJOIN("; ",TRUE,TRANSPOSE(_xlfn.UNIQUE(_xlfn._xlws.FILTER(DET_ASIG[DETALLADO],(DET_ASIG[NIVEL]=ASIGNACION!$D10)*(DET_ASIG[ID_CARRERA]=ASIGNACION!$C10)*(DET_ASIG[ID_ASIG]=ASIGNACION!$G10),"No existe información"))))} -> ACTIVIDAD | I10: ACTIVIDAD | J10: =_xlfn.XLOOKUP(Tabla1[[#This Row],[ID_ASIG_CAM_DET]],MAE_ASIGNATURA[ID_ASIG],MAE_ASIGNATURA[HORAS],0) -> 1 | K10: 3 | L10: =+Tabla1[[#This Row],[CALCULAR HORA]]*Tabla1[[#This Row],[HORAS]] -> 3 | M10: CACERES LARREATEGUI ALBA LUCIA | N10: =_xlfn.XLOOKUP(Tabla1[[#This Row],[NOMBRE_DOCENT]],MDOCENTES[DATOS_DOCENTE],MDOCENTES[DEDICACION],"Seleccione Docente") -> TC | O10: =_xlfn.XLOOKUP(Tabla1[[#This Row],[NOMBRE_DOCENT]],MDOCENTES[DATOS_DOCENTE],MDOCENTES[ESTUDIO],"Seleccione Docente") -> MAESTRÍA | P10: =COUNTIFS($M:$M, M10, $H:$H, "<>ACTIVIDAD") -> 4 | Q10: =SUMIFS($L:$L, $M:$M, M10, $I:$I, "NO",$H:$H,"<>UNIDAD BASICA") -> 0 | R10: =SUMIFS($L:$L, $M:$M, M10, $H:$H, "UNIDAD BASICA",$I:$I,"NO") -> 16 | S10: =SUMIFS($L:$L, $M:$M, M10, $I:$I, "ACTIVIDAD") -> 9 | T10: =SUMIFS($L:$L, $M:$M, M10, $I:$I, "SI") -> 0 | U10: =Tabla1[[#This Row],[HORAS NO AFINIDAD]]+Tabla1[[#This Row],[HORAS UNIDAD BASICA]]+Tabla1[[#This Row],[HORAS AFINIDAD]] -> 16 | V10: =+Tabla1[[#This Row],[HORAS AFINIDAD]]+Tabla1[[#This Row],[HORAS ACTIVIDAD]]+Tabla1[[#This Row],[HORAS UNIDAD BASICA]]+Tabla1[[#This Row],[HORAS NO AFINIDAD]] -> 25
A11: 10 | B11: CONTABILIDAD Y AUDITORÍA 2024 NS | C11: =_xlfn.XLOOKUP(Tabla1[[#This Row],[CARRERA]],MAE_CARRERA[NOMBRE_CARRERA],MAE_CARRERA[ID_CARRERA],"Seleccione Carrera") -> FCACC-CO-AD | D11: 2 | F11: ESTADÍSTICA DESCRIPTIVA | G11: =_xlfn.XLOOKUP(Tabla1[[#This Row],[ASIGNATURA]],MAE_ASIGNATURA[NOM_ASIG],MAE_ASIGNATURA[ID_ASIG],"Seleccione Asignatura") -> FCACC-AU-CO-GE-NI-1-ESTAD-DES | H11: {=_xlfn.TEXTJOIN("; ",TRUE,TRANSPOSE(_xlfn.UNIQUE(_xlfn._xlws.FILTER(DET_ASIG[DETALLADO],(DET_ASIG[NIVEL]=ASIGNACION!$D11)*(DET_ASIG[ID_CARRERA]=ASIGNACION!$C11)*(DET_ASIG[ID_ASIG]=ASIGNACION!$G11),"No existe información"))))} -> UNIDAD BASICA | I11: NO | J11: =_xlfn.XLOOKUP(Tabla1[[#This Row],[ID_ASIG_CAM_DET]],MAE_ASIGNATURA[ID_ASIG],MAE_ASIGNATURA[HORAS],0) -> 2 | K11: 8 | L11: =+Tabla1[[#This Row],[CALCULAR HORA]]*Tabla1[[#This Row],[HORAS]] -> 16 | M11: ARAUZ CHAVEZ MARIO ROBERTO | N11: =_xlfn.XLOOKUP(Tabla1[[#This Row],[NOMBRE_DOCENT]],MDOCENTES[DATOS_DOCENTE],MDOCENTES[DEDICACION],"Seleccione Docente") -> TC | O11: =_xlfn.XLOOKUP(Tabla1[[#This Row],[NOMBRE_DOCENT]],MDOCENTES[DATOS_DOCENTE],MDOCENTES[ESTUDIO],"Seleccione Docente") -> MAESTRÍA | P11: =COUNTIFS($M:$M, M11, $H:$H, "<>ACTIVIDAD") -> 1 | Q11: =SUMIFS($L:$L, $M:$M, M11, $I:$I, "NO",$H:$H,"<>UNIDAD BASICA") -> 0 | R11: =SUMIFS($L:$L, $M:$M, M11, $H:$H, "UNIDAD BASICA",$I:$I,"NO") -> 16 | S11: =SUMIFS($L:$L, $M:$M, M11, $I:$I, "ACTIVIDAD") -> 0 | T11: =SUMIFS($L:$L, $M:$M, M11, $I:$I, "SI") -> 0 | U11: =Tabla1[[#This Row],[HORAS NO AFINIDAD]]+Tabla1[[#This Row],[HORAS UNIDAD BASICA]]+Tabla1[[#This Row],[HORAS AFINIDAD]] -> 16 | V11: =+Tabla1[[#This Row],[HORAS AFINIDAD]]+Tabla1[[#This Row],[HORAS ACTIVIDAD]]+Tabla1[[#This Row],[HORAS UNIDAD BASICA]]+Tabla1[[#This Row],[HORAS NO AFINIDAD]] -> 16
A12: 11 | C12: =_xlfn.XLOOKUP(Tabla1[[#This Row],[CARRERA]],MAE_CARRERA[NOMBRE_CARRERA],MAE_CARRERA[ID_CARRERA],"Seleccione Carrera") -> Seleccione Carrera | G12: =_xlfn.XLOOKUP(Tabla1[[#This Row],[ASIGNATURA]],MAE_ASIGNATURA[NOM_ASIG],MAE_ASIGNATURA[ID_ASIG],"Seleccione Asignatura") -> Seleccione Asignatura | H12: {=_xlfn.TEXTJOIN("; ",TRUE,TRANSPOSE(_xlfn.UNIQUE(_xlfn._xlws.FILTER(DET_ASIG[DETALLADO],(DET_ASIG[NIVEL]=ASIGNACION!$D12)*(DET_ASIG[ID_CARRERA]=ASIGNACION!$C12)*(DET_ASIG[ID_ASIG]=ASIGNACION!$G12),"No existe información"))))} -> No existe información | J12: =_xlfn.XLOOKUP(Tabla1[[#This Row],[ID_ASIG_CAM_DET]],MAE_ASIGNATURA[ID_ASIG],MAE_ASIGNATURA[HORAS],0) -> 0 | K12: 4 | L12: =+Tabla1[[#This Row],[CALCULAR HORA]]*Tabla1[[#This Row],[HORAS]] -> 0 | N12: =_xlfn.XLOOKUP(Tabla1[[#This Row],[NOMBRE_DOCENT]],MDOCENTES[DATOS_DOCENTE],MDOCENTES[DEDICACION],"Seleccione Docente") -> Seleccione Docente | O12: =_xlfn.XLOOKUP(Tabla1[[#This Row],[NOMBRE_DOCENT]],MDOCENTES[DATOS_DOCENTE],MDOCENTES[ESTUDIO],"Seleccione Docente") -> Seleccione Docente | P12: =COUNTIFS($M:$M, M12, $H:$H, "<>ACTIVIDAD") -> 0 | Q12: =SUMIFS($L:$L, $M:$M, M12, $I:$I, "NO",$H:$H,"<>UNIDAD BASICA") -> 0 | R12: =SUMIFS($L:$L, $M:$M, M12, $H:$H, "UNIDAD BASICA",$I:$I,"NO") -> 0 | S12: =SUMIFS($L:$L, $M:$M, M12, $I:$I, "ACTIVIDAD") -> 0 | T12: =SUMIFS($L:$L, $M:$M, M12, $I:$I, "SI") -> 0 | U12: =Tabla1[[#This Row],[HORAS NO AFINIDAD]]+Tabla1[[#This Row],[HORAS UNIDAD BASICA]]+Tabla1[[#This Row],[HORAS AFINIDAD]] -> 0 | V12: =+Tabla1[[#This Row],[HORAS AFINIDAD]]+Tabla1[[#This Row],[HORAS ACTIVIDAD]]+Tabla1[[#This Row],[HORAS UNIDAD BASICA]]+Tabla1[[#This Row],[HORAS NO AFINIDAD]] -> 0
A13: 12 | C13: =_xlfn.XLOOKUP(Tabla1[[#This Row],[CARRERA]],MAE_CARRERA[NOMBRE_CARRERA],MAE_CARRERA[ID_CARRERA],"Seleccione Carrera") -> Seleccione Carrera | G13: =_xlfn.XLOOKUP(Tabla1[[#This Row],[ASIGNATURA]],MAE_ASIGNATURA[NOM_ASIG],MAE_ASIGNATURA[ID_ASIG],"Seleccione Asignatura") -> Seleccione Asignatura | H13: {=_xlfn.TEXTJOIN("; ",TRUE,TRANSPOSE(_xlfn.UNIQUE(_xlfn._xlws.FILTER(DET_ASIG[DETALLADO],(DET_ASIG[NIVEL]=ASIGNACION!$D13)*(DET_ASIG[ID_CARRERA]=ASIGNACION!$C13)*(DET_ASIG[ID_ASIG]=ASIGNACION!$G13),"No existe información"))))} -> No existe información | J13: =_xlfn.XLOOKUP(Tabla1[[#This Row],[ID_ASIG_CAM_DET]],MAE_ASIGNATURA[ID_ASIG],MAE_ASIGNATURA[HORAS],0) -> 0 | K13: 4 | L13: =+Tabla1[[#This Row],[CALCULAR HORA]]*Tabla1[[#This Row],[HORAS]] -> 0 | N13: =_xlfn.XLOOKUP(Tabla1[[#This Row],[NOMBRE_DOCENT]],MDOCENTES[DATOS_DOCENTE],MDOCENTES[DEDICACION],"Seleccione Docente") -> Seleccione Docente | O13: =_xlfn.XLOOKUP(Tabla1[[#This Row],[NOMBRE_DOCENT]],MDOCENTES[DATOS_DOCENTE],MDOCENTES[ESTUDIO],"Seleccione Docente") -> Seleccione Docente | P13: =COUNTIFS($M:$M, M13, $H:$H, "<>ACTIVIDAD") -> 0 | Q13: =SUMIFS($L:$L, $M:$M, M13, $I:$I, "NO",$H:$H,"<>UNIDAD BASICA") -> 0 | R13: =SUMIFS($L:$L, $M:$M, M13, $H:$H, "UNIDAD BASICA",$I:$I,"NO") -> 0 | S13: =SUMIFS($L:$L, $M:$M, M13, $I:$I, "ACTIVIDAD") -> 0 | T13: =SUMIFS($L:$L, $M:$M, M13, $I:$I, "SI") -> 0 | U13: =Tabla1[[#This Row],[HORAS NO AFINIDAD]]+Tabla1[[#This Row],[HORAS UNIDAD BASICA]]+Tabla1[[#This Row],[HORAS AFINIDAD]] -> 0 | V13: =+Tabla1[[#This Row],[HORAS AFINIDAD]]+Tabla1[[#This Row],[HORAS ACTIVIDAD]]+Tabla1[[#This Row],[HORAS UNIDAD BASICA]]+Tabla1[[#This Row],[HORAS NO AFINIDAD]] -> 0
A14: 13 | C14: =_xlfn.XLOOKUP(Tabla1[[#This Row],[CARRERA]],MAE_CARRERA[NOMBRE_CARRERA],MAE_CARRERA[ID_CARRERA],"Seleccione Carrera") -> Seleccione Carrera | G14: =_xlfn.XLOOKUP(Tabla1[[#This Row],[ASIGNATURA]],MAE_ASIGNATURA[NOM_ASIG],MAE_ASIGNATURA[ID_ASIG],"Seleccione Asignatura") -> Seleccione Asignatura | H14: {=_xlfn.TEXTJOIN("; ",TRUE,TRANSPOSE(_xlfn.UNIQUE(_xlfn._xlws.FILTER(DET_ASIG[DETALLADO],(DET_ASIG[NIVEL]=ASIGNACION!$D14)*(DET_ASIG[ID_CARRERA]=ASIGNACION!$C14)*(DET_ASIG[ID_ASIG]=ASIGNACION!$G14),"No existe información"))))} -> No existe información | J14: =_xlfn.XLOOKUP(Tabla1[[#This Row],[ID_ASIG_CAM_DET]],MAE_ASIGNATURA[ID_ASIG],MAE_ASIGNATURA[HORAS],0) -> 0 | K14: 4 | L14: =+Tabla1[[#This Row],[CALCULAR HORA]]*Tabla1[[#This Row],[HORAS]] -> 0 | N14: =_xlfn.XLOOKUP(Tabla1[[#This Row],[NOMBRE_DOCENT]],MDOCENTES[DATOS_DOCENTE],MDOCENTES[DEDICACION],"Seleccione Docente") -> Seleccione Docente | O14: =_xlfn.XLOOKUP(Tabla1[[#This Row],[NOMBRE_DOCENT]],MDOCENTES[DATOS_DOCENTE],MDOCENTES[ESTUDIO],"Seleccione Docente") -> Seleccione Docente | P14: =COUNTIFS($M:$M, M14, $H:$H, "<>ACTIVIDAD") -> 0 | Q14: =SUMIFS($L:$L, $M:$M, M14, $I:$I, "NO",$H:$H,"<>UNIDAD BASICA") -> 0 | R14: =SUMIFS($L:$L, $M:$M, M14, $H:$H, "UNIDAD BASICA",$I:$I,"NO") -> 0 | S14: =SUMIFS($L:$L, $M:$M, M14, $I:$I, "ACTIVIDAD") -> 0 | T14: =SUMIFS($L:$L, $M:$M, M14, $I:$I, "SI") -> 0 | U14: =Tabla1[[#This Row],[HORAS NO AFINIDAD]]+Tabla1[[#This Row],[HORAS UNIDAD BASICA]]+Tabla1[[#This Row],[HORAS AFINIDAD]] -> 0 | V14: =+Tabla1[[#This Row],[HORAS AFINIDAD]]+Tabla1[[#This Row],[HORAS ACTIVIDAD]]+Tabla1[[#This Row],[HORAS UNIDAD BASICA]]+Tabla1[[#This Row],[HORAS NO AFINIDAD]] -> 0
A15: 14 | C15: =_xlfn.XLOOKUP(Tabla1[[#This Row],[CARRERA]],MAE_CARRERA[NOMBRE_CARRERA],MAE_CARRERA[ID_CARRERA],"Seleccione Carrera") -> Seleccione Carrera | G15: =_xlfn.XLOOKUP(Tabla1[[#This Row],[ASIGNATURA]],MAE_ASIGNATURA[NOM_ASIG],MAE_ASIGNATURA[ID_ASIG],"Seleccione Asignatura") -> Seleccione Asignatura | H15: {=_xlfn.TEXTJOIN("; ",TRUE,TRANSPOSE(_xlfn.UNIQUE(_xlfn._xlws.FILTER(DET_ASIG[DETALLADO],(DET_ASIG[NIVEL]=ASIGNACION!$D15)*(DET_ASIG[ID_CARRERA]=ASIGNACION!$C15)*(DET_ASIG[ID_ASIG]=ASIGNACION!$G15),"No existe información"))))} -> No existe información | J15: =_xlfn.XLOOKUP(Tabla1[[#This Row],[ID_ASIG_CAM_DET]],MAE_ASIGNATURA[ID_ASIG],MAE_ASIGNATURA[HORAS],0) -> 0 | K15: 4 | L15: =+Tabla1[[#This Row],[CALCULAR HORA]]*Tabla1[[#This Row],[HORAS]] -> 0 | N15: =_xlfn.XLOOKUP(Tabla1[[#This Row],[NOMBRE_DOCENT]],MDOCENTES[DATOS_DOCENTE],MDOCENTES[DEDICACION],"Seleccione Docente") -> Seleccione Docente | O15: =_xlfn.XLOOKUP(Tabla1[[#This Row],[NOMBRE_DOCENT]],MDOCENTES[DATOS_DOCENTE],MDOCENTES[ESTUDIO],"Seleccione Docente") -> Seleccione Docente | P15: =COUNTIFS($M:$M, M15, $H:$H, "<>ACTIVIDAD") -> 0 | Q15: =SUMIFS($L:$L, $M:$M, M15, $I:$I, "NO",$H:$H,"<>UNIDAD BASICA") -> 0 | R15: =SUMIFS($L:$L, $M:$M, M15, $H:$H, "UNIDAD BASICA",$I:$I,"NO") -> 0 | S15: =SUMIFS($L:$L, $M:$M, M15, $I:$I, "ACTIVIDAD") -> 0 | T15: =SUMIFS($L:$L, $M:$M, M15, $I:$I, "SI") -> 0 | U15: =Tabla1[[#This Row],[HORAS NO AFINIDAD]]+Tabla1[[#This Row],[HORAS UNIDAD BASICA]]+Tabla1[[#This Row],[HORAS AFINIDAD]] -> 0 | V15: =+Tabla1[[#This Row],[HORAS AFINIDAD]]+Tabla1[[#This Row],[HORAS ACTIVIDAD]]+Tabla1[[#This Row],[HORAS UNIDAD BASICA]]+Tabla1[[#This Row],[HORAS NO AFINIDAD]] -> 0
A16: 15 | C16: =_xlfn.XLOOKUP(Tabla1[[#This Row],[CARRERA]],MAE_CARRERA[NOMBRE_CARRERA],MAE_CARRERA[ID_CARRERA],"Seleccione Carrera") -> Seleccione Carrera | G16: =_xlfn.XLOOKUP(Tabla1[[#This Row],[ASIGNATURA]],MAE_ASIGNATURA[NOM_ASIG],MAE_ASIGNATURA[ID_ASIG],"Seleccione Asignatura") -> Seleccione Asignatura | H16: {=_xlfn.TEXTJOIN("; ",TRUE,TRANSPOSE(_xlfn.UNIQUE(_xlfn._xlws.FILTER(DET_ASIG[DETALLADO],(DET_ASIG[NIVEL]=ASIGNACION!$D16)*(DET_ASIG[ID_CARRERA]=ASIGNACION!$C16)*(DET_ASIG[ID_ASIG]=ASIGNACION!$G16),"No existe información"))))} -> No existe información | J16: =_xlfn.XLOOKUP(Tabla1[[#This Row],[ID_ASIG_CAM_DET]],MAE_ASIGNATURA[ID_ASIG],MAE_ASIGNATURA[HORAS],0) -> 0 | K16: 4 | L16: =+Tabla1[[#This Row],[CALCULAR HORA]]*Tabla1[[#This Row],[HORAS]] -> 0 | N16: =_xlfn.XLOOKUP(Tabla1[[#This Row],[NOMBRE_DOCENT]],MDOCENTES[DATOS_DOCENTE],MDOCENTES[DEDICACION],"Seleccione Docente") -> Seleccione Docente | O16: =_xlfn.XLOOKUP(Tabla1[[#This Row],[NOMBRE_DOCENT]],MDOCENTES[DATOS_DOCENTE],MDOCENTES[ESTUDIO],"Seleccione Docente") -> Seleccione Docente | P16: =COUNTIFS($M:$M, M16, $H:$H, "<>ACTIVIDAD") -> 0 | Q16: =SUMIFS($L:$L, $M:$M, M16, $I:$I, "NO",$H:$H,"<>UNIDAD BASICA") -> 0 | R16: =SUMIFS($L:$L, $M:$M, M16, $H:$H, "UNIDAD BASICA",$I:$I,"NO") -> 0 | S16: =SUMIFS($L:$L, $M:$M, M16, $I:$I, "ACTIVIDAD") -> 0 | T16: =SUMIFS($L:$L, $M:$M, M16, $I:$I, "SI") -> 0 | U16: =Tabla1[[#This Row],[HORAS NO AFINIDAD]]+Tabla1[[#This Row],[HORAS UNIDAD BASICA]]+Tabla1[[#This Row],[HORAS AFINIDAD]] -> 0 | V16: =+Tabla1[[#This Row],[HORAS AFINIDAD]]+Tabla1[[#This Row],[HORAS ACTIVIDAD]]+Tabla1[[#This Row],[HORAS UNIDAD BASICA]]+Tabla1[[#This Row],[HORAS NO AFINIDAD]] -> 0
A17: 16 | C17: =_xlfn.XLOOKUP(Tabla1[[#This Row],[CARRERA]],MAE_CARRERA[NOMBRE_CARRERA],MAE_CARRERA[ID_CARRERA],"Seleccione Carrera") -> Seleccione Carrera | G17: =_xlfn.XLOOKUP(Tabla1[[#This Row],[ASIGNATURA]],MAE_ASIGNATURA[NOM_ASIG],MAE_ASIGNATURA[ID_ASIG],"Seleccione Asignatura") -> Seleccione Asignatura | H17: {=_xlfn.TEXTJOIN("; ",TRUE,TRANSPOSE(_xlfn.UNIQUE(_xlfn._xlws.FILTER(DET_ASIG[DETALLADO],(DET_ASIG[NIVEL]=ASIGNACION!$D17)*(DET_ASIG[ID_CARRERA]=ASIGNACION!$C17)*(DET_ASIG[ID_ASIG]=ASIGNACION!$G17),"No existe información"))))} -> No existe información | J17: =_xlfn.XLOOKUP(Tabla1[[#This Row],[ID_ASIG_CAM_DET]],MAE_ASIGNATURA[ID_ASIG],MAE_ASIGNATURA[HORAS],0) -> 0 | K17: 4 | L17: =+Tabla1[[#This Row],[CALCULAR HORA]]*Tabla1[[#This Row],[HORAS]] -> 0 | N17: =_xlfn.XLOOKUP(Tabla1[[#This Row],[NOMBRE_DOCENT]],MDOCENTES[DATOS_DOCENTE],MDOCENTES[DEDICACION],"Seleccione Docente") -> Seleccione Docente | O17: =_xlfn.XLOOKUP(Tabla1[[#This Row],[NOMBRE_DOCENT]],MDOCENTES[DATOS_DOCENTE],MDOCENTES[ESTUDIO],"Seleccione Docente") -> Seleccione Docente | P17: =COUNTIFS($M:$M, M17, $H:$H, "<>ACTIVIDAD") -> 0 | Q17: =SUMIFS($L:$L, $M:$M, M17, $I:$I, "NO",$H:$H,"<>UNIDAD BASICA") -> 0 | R17: =SUMIFS($L:$L, $M:$M, M17, $H:$H, "UNIDAD BASICA",$I:$I,"NO") -> 0 | S17: =SUMIFS($L:$L, $M:$M, M17, $I:$I, "ACTIVIDAD") -> 0 | T17: =SUMIFS($L:$L, $M:$M, M17, $I:$I, "SI") -> 0 | U17: =Tabla1[[#This Row],[HORAS NO AFINIDAD]]+Tabla1[[#This Row],[HORAS UNIDAD BASICA]]+Tabla1[[#This Row],[HORAS AFINIDAD]] -> 0 | V17: =+Tabla1[[#This Row],[HORAS AFINIDAD]]+Tabla1[[#This Row],[HORAS ACTIVIDAD]]+Tabla1[[#This Row],[HORAS UNIDAD BASICA]]+Tabla1[[#This Row],[HORAS NO AFINIDAD]] -> 0
A18: 17 | C18: =_xlfn.XLOOKUP(Tabla1[[#This Row],[CARRERA]],MAE_CARRERA[NOMBRE_CARRERA],MAE_CARRERA[ID_CARRERA],"Seleccione Carrera") -> Seleccione Carrera | G18: =_xlfn.XLOOKUP(Tabla1[[#This Row],[ASIGNATURA]],MAE_ASIGNATURA[NOM_ASIG],MAE_ASIGNATURA[ID_ASIG],"Seleccione Asignatura") -> Seleccione Asignatura | H18: {=_xlfn.TEXTJOIN("; ",TRUE,TRANSPOSE(_xlfn.UNIQUE(_xlfn._xlws.FILTER(DET_ASIG[DETALLADO],(DET_ASIG[NIVEL]=ASIGNACION!$D18)*(DET_ASIG[ID_CARRERA]=ASIGNACION!$C18)*(DET_ASIG[ID_ASIG]=ASIGNACION!$G18),"No existe información"))))} -> No existe información | J18: =_xlfn.XLOOKUP(Tabla1[[#This Row],[ID_ASIG_CAM_DET]],MAE_ASIGNATURA[ID_ASIG],MAE_ASIGNATURA[HORAS],0) -> 0 | K18: 4 | L18: =+Tabla1[[#This Row],[CALCULAR HORA]]*Tabla1[[#This Row],[HORAS]] -> 0 | N18: =_xlfn.XLOOKUP(Tabla1[[#This Row],[NOMBRE_DOCENT]],MDOCENTES[DATOS_DOCENTE],MDOCENTES[DEDICACION],"Seleccione Docente") -> Seleccione Docente | O18: =_xlfn.XLOOKUP(Tabla1[[#This Row],[NOMBRE_DOCENT]],MDOCENTES[DATOS_DOCENTE],MDOCENTES[ESTUDIO],"Seleccione Docente") -> Seleccione Docente | P18: =COUNTIFS($M:$M, M18, $H:$H, "<>ACTIVIDAD") -> 0 | Q18: =SUMIFS($L:$L, $M:$M, M18, $I:$I, "NO",$H:$H,"<>UNIDAD BASICA") -> 0 | R18: =SUMIFS($L:$L, $M:$M, M18, $H:$H, "UNIDAD BASICA",$I:$I,"NO") -> 0 | S18: =SUMIFS($L:$L, $M:$M, M18, $I:$I, "ACTIVIDAD") -> 0 | T18: =SUMIFS($L:$L, $M:$M, M18, $I:$I, "SI") -> 0 | U18: =Tabla1[[#This Row],[HORAS NO AFINIDAD]]+Tabla1[[#This Row],[HORAS UNIDAD BASICA]]+Tabla1[[#This Row],[HORAS AFINIDAD]] -> 0 | V18: =+Tabla1[[#This Row],[HORAS AFINIDAD]]+Tabla1[[#This Row],[HORAS ACTIVIDAD]]+Tabla1[[#This Row],[HORAS UNIDAD BASICA]]+Tabla1[[#This Row],[HORAS NO AFINIDAD]] -> 0
A19: 18 | C19: =_xlfn.XLOOKUP(Tabla1[[#This Row],[CARRERA]],MAE_CARRERA[NOMBRE_CARRERA],MAE_CARRERA[ID_CARRERA],"Seleccione Carrera") -> Seleccione Carrera | G19: =_xlfn.XLOOKUP(Tabla1[[#This Row],[ASIGNATURA]],MAE_ASIGNATURA[NOM_ASIG],MAE_ASIGNATURA[ID_ASIG],"Seleccione Asignatura") -> Seleccione Asignatura | H19: {=_xlfn.TEXTJOIN("; ",TRUE,TRANSPOSE(_xlfn.UNIQUE(_xlfn._xlws.FILTER(DET_ASIG[DETALLADO],(DET_ASIG[NIVEL]=ASIGNACION!$D19)*(DET_ASIG[ID_CARRERA]=ASIGNACION!$C19)*(DET_ASIG[ID_ASIG]=ASIGNACION!$G19),"No existe información"))))} -> No existe información | J19: =_xlfn.XLOOKUP(Tabla1[[#This Row],[ID_ASIG_CAM_DET]],MAE_ASIGNATURA[ID_ASIG],MAE_ASIGNATURA[HORAS],0) -> 0 | K19: 4 | L19: =+Tabla1[[#This Row],[CALCULAR HORA]]*Tabla1[[#This Row],[HORAS]] -> 0 | N19: =_xlfn.XLOOKUP(Tabla1[[#This Row],[NOMBRE_DOCENT]],MDOCENTES[DATOS_DOCENTE],MDOCENTES[DEDICACION],"Seleccione Docente") -> Seleccione Docente | O19: =_xlfn.XLOOKUP(Tabla1[[#This Row],[NOMBRE_DOCENT]],MDOCENTES[DATOS_DOCENTE],MDOCENTES[ESTUDIO],"Seleccione Docente") -> Seleccione Docente | P19: =COUNTIFS($M:$M, M19, $H:$H, "<>ACTIVIDAD") -> 0 | Q19: =SUMIFS($L:$L, $M:$M, M19, $I:$I, "NO",$H:$H,"<>UNIDAD BASICA") -> 0 | R19: =SUMIFS($L:$L, $M:$M, M19, $H:$H, "UNIDAD BASICA",$I:$I,"NO") -> 0 | S19: =SUMIFS($L:$L, $M:$M, M19, $I:$I, "ACTIVIDAD") -> 0 | T19: =SUMIFS($L:$L, $M:$M, M19, $I:$I, "SI") -> 0 | U19: =Tabla1[[#This Row],[HORAS NO AFINIDAD]]+Tabla1[[#This Row],[HORAS UNIDAD BASICA]]+Tabla1[[#This Row],[HORAS AFINIDAD]] -> 0 | V19: =+Tabla1[[#This Row],[HORAS AFINIDAD]]+Tabla1[[#This Row],[HORAS ACTIVIDAD]]+Tabla1[[#This Row],[HORAS UNIDAD BASICA]]+Tabla1[[#This Row],[HORAS NO AFINIDAD]] -> 0
A20: 19 | C20: =_xlfn.XLOOKUP(Tabla1[[#This Row],[CARRERA]],MAE_CARRERA[NOMBRE_CARRERA],MAE_CARRERA[ID_CARRERA],"Seleccione Carrera") -> Seleccione Carrera | G20: =_xlfn.XLOOKUP(Tabla1[[#This Row],[ASIGNATURA]],MAE_ASIGNATURA[NOM_ASIG],MAE_ASIGNATURA[ID_ASIG],"Seleccione Asignatura") -> Seleccione Asignatura | H20: {=_xlfn.TEXTJOIN("; ",TRUE,TRANSPOSE(_xlfn.UNIQUE(_xlfn._xlws.FILTER(DET_ASIG[DETALLADO],(DET_ASIG[NIVEL]=ASIGNACION!$D20)*(DET_ASIG[ID_CARRERA]=ASIGNACION!$C20)*(DET_ASIG[ID_ASIG]=ASIGNACION!$G20),"No existe información"))))} -> No existe información | J20: =_xlfn.XLOOKUP(Tabla1[[#This Row],[ID_ASIG_CAM_DET]],MAE_ASIGNATURA[ID_ASIG],MAE_ASIGNATURA[HORAS],0) -> 0 | K20: 4 | L20: =+Tabla1[[#This Row],[CALCULAR HORA]]*Tabla1[[#This Row],[HORAS]] -> 0 | N20: =_xlfn.XLOOKUP(Tabla1[[#This Row],[NOMBRE_DOCENT]],MDOCENTES[DATOS_DOCENTE],MDOCENTES[DEDICACION],"Seleccione Docente") -> Seleccione Docente | O20: =_xlfn.XLOOKUP(Tabla1[[#This Row],[NOMBRE_DOCENT]],MDOCENTES[DATOS_DOCENTE],MDOCENTES[ESTUDIO],"Seleccione Docente") -> Seleccione Docente | P20: =COUNTIFS($M:$M, M20, $H:$H, "<>ACTIVIDAD") -> 0 | Q20: =SUMIFS($L:$L, $M:$M, M20, $I:$I, "NO",$H:$H,"<>UNIDAD BASICA") -> 0 | R20: =SUMIFS($L:$L, $M:$M, M20, $H:$H, "UNIDAD BASICA",$I:$I,"NO") -> 0 | S20: =SUMIFS($L:$L, $M:$M, M20, $I:$I, "ACTIVIDAD") -> 0 | T20: =SUMIFS($L:$L, $M:$M, M20, $I:$I, "SI") -> 0 | U20: =Tabla1[[#This Row],[HORAS NO AFINIDAD]]+Tabla1[[#This Row],[HORAS UNIDAD BASICA]]+Tabla1[[#This Row],[HORAS AFINIDAD]] -> 0 | V20: =+Tabla1[[#This Row],[HORAS AFINIDAD]]+Tabla1[[#This Row],[HORAS ACTIVIDAD]]+Tabla1[[#This Row],[HORAS UNIDAD BASICA]]+Tabla1[[#This Row],[HORAS NO AFINIDAD]] -> 0
A21: 20 | C21: =_xlfn.XLOOKUP(Tabla1[[#This Row],[CARRERA]],MAE_CARRERA[NOMBRE_CARRERA],MAE_CARRERA[ID_CARRERA],"Seleccione Carrera") -> Seleccione Carrera | G21: =_xlfn.XLOOKUP(Tabla1[[#This Row],[ASIGNATURA]],MAE_ASIGNATURA[NOM_ASIG],MAE_ASIGNATURA[ID_ASIG],"Seleccione Asignatura") -> Seleccione Asignatura | H21: {=_xlfn.TEXTJOIN("; ",TRUE,TRANSPOSE(_xlfn.UNIQUE(_xlfn._xlws.FILTER(DET_ASIG[DETALLADO],(DET_ASIG[NIVEL]=ASIGNACION!$D21)*(DET_ASIG[ID_CARRERA]=ASIGNACION!$C21)*(DET_ASIG[ID_ASIG]=ASIGNACION!$G21),"No existe información"))))} -> No existe información | J21: =_xlfn.XLOOKUP(Tabla1[[#This Row],[ID_ASIG_CAM_DET]],MAE_ASIGNATURA[ID_ASIG],MAE_ASIGNATURA[HORAS],0) -> 0 | K21: 4 | L21: =+Tabla1[[#This Row],[CALCULAR HORA]]*Tabla1[[#This Row],[HORAS]] -> 0 | N21: =_xlfn.XLOOKUP(Tabla1[[#This Row],[NOMBRE_DOCENT]],MDOCENTES[DATOS_DOCENTE],MDOCENTES[DEDICACION],"Seleccione Docente") -> Seleccione Docente | O21: =_xlfn.XLOOKUP(Tabla1[[#This Row],[NOMBRE_DOCENT]],MDOCENTES[DATOS_DOCENTE],MDOCENTES[ESTUDIO],"Seleccione Docente") -> Seleccione Docente | P21: =COUNTIFS($M:$M, M21, $H:$H, "<>ACTIVIDAD") -> 0 | Q21: =SUMIFS($L:$L, $M:$M, M21, $I:$I, "NO",$H:$H,"<>UNIDAD BASICA") -> 0 | R21: =SUMIFS($L:$L, $M:$M, M21, $H:$H, "UNIDAD BASICA",$I:$I,"NO") -> 0 | S21: =SUMIFS($L:$L, $M:$M, M21, $I:$I, "ACTIVIDAD") -> 0 | T21: =SUMIFS($L:$L, $M:$M, M21, $I:$I, "SI") -> 0 | U21: =Tabla1[[#This Row],[HORAS NO AFINIDAD]]+Tabla1[[#This Row],[HORAS UNIDAD BASICA]]+Tabla1[[#This Row],[HORAS AFINIDAD]] -> 0 | V21: =+Tabla1[[#This Row],[HORAS AFINIDAD]]+Tabla1[[#This Row],[HORAS ACTIVIDAD]]+Tabla1[[#This Row],[HORAS UNIDAD BASICA]]+Tabla1[[#This Row],[HORAS NO AFINIDAD]] -> 0
A22: 21 | C22: =_xlfn.XLOOKUP(Tabla1[[#This Row],[CARRERA]],MAE_CARRERA[NOMBRE_CARRERA],MAE_CARRERA[ID_CARRERA],"Seleccione Carrera") -> Seleccione Carrera | G22: =_xlfn.XLOOKUP(Tabla1[[#This Row],[ASIGNATURA]],MAE_ASIGNATURA[NOM_ASIG],MAE_ASIGNATURA[ID_ASIG],"Seleccione Asignatura") -> Seleccione Asignatura | H22: {=_xlfn.TEXTJOIN("; ",TRUE,TRANSPOSE(_xlfn.UNIQUE(_xlfn._xlws.FILTER(DET_ASIG[DETALLADO],(DET_ASIG[NIVEL]=ASIGNACION!$D22)*(DET_ASIG[ID_CARRERA]=ASIGNACION!$C22)*(DET_ASIG[ID_ASIG]=ASIGNACION!$G22),"No existe información"))))} -> No existe información | J22: =_xlfn.XLOOKUP(Tabla1[[#This Row],[ID_ASIG_CAM_DET]],MAE_ASIGNATURA[ID_ASIG],MAE_ASIGNATURA[HORAS],0) -> 0 | K22: 4 | L22: =+Tabla1[[#This Row],[CALCULAR HORA]]*Tabla1[[#This Row],[HORAS]] -> 0 | N22: =_xlfn.XLOOKUP(Tabla1[[#This Row],[NOMBRE_DOCENT]],MDOCENTES[DATOS_DOCENTE],MDOCENTES[DEDICACION],"Seleccione Docente") -> Seleccione Docente | O22: =_xlfn.XLOOKUP(Tabla1[[#This Row],[NOMBRE_DOCENT]],MDOCENTES[DATOS_DOCENTE],MDOCENTES[ESTUDIO],"Seleccione Docente") -> Seleccione Docente | P22: =COUNTIFS($M:$M, M22, $H:$H, "<>ACTIVIDAD") -> 0 | Q22: =SUMIFS($L:$L, $M:$M, M22, $I:$I, "NO",$H:$H,"<>UNIDAD BASICA") -> 0 | R22: =SUMIFS($L:$L, $M:$M, M22, $H:$H, "UNIDAD BASICA",$I:$I,"NO") -> 0 | S22: =SUMIFS($L:$L, $M:$M, M22, $I:$I, "ACTIVIDAD") -> 0 | T22: =SUMIFS($L:$L, $M:$M, M22, $I:$I, "SI") -> 0 | U22: =Tabla1[[#This Row],[HORAS NO AFINIDAD]]+Tabla1[[#This Row],[HORAS UNIDAD BASICA]]+Tabla1[[#This Row],[HORAS AFINIDAD]] -> 0 | V22: =+Tabla1[[#This Row],[HORAS AFINIDAD]]+Tabla1[[#This Row],[HORAS ACTIVIDAD]]+Tabla1[[#This Row],[HORAS UNIDAD BASICA]]+Tabla1[[#This Row],[HORAS NO AFINIDAD]] -> 0
A23: 22 | C23: =_xlfn.XLOOKUP(Tabla1[[#This Row],[CARRERA]],MAE_CARRERA[NOMBRE_CARRERA],MAE_CARRERA[ID_CARRERA],"Seleccione Carrera") -> Seleccione Carrera | G23: =_xlfn.XLOOKUP(Tabla1[[#This Row],[ASIGNATURA]],MAE_ASIGNATURA[NOM_ASIG],MAE_ASIGNATURA[ID_ASIG],"Seleccione Asignatura") -> Seleccione Asignatura | H23: {=_xlfn.TEXTJOIN("; ",TRUE,TRANSPOSE(_xlfn.UNIQUE(_xlfn._xlws.FILTER(DET_ASIG[DETALLADO],(DET_ASIG[NIVEL]=ASIGNACION!$D23)*(DET_ASIG[ID_CARRERA]=ASIGNACION!$C23)*(DET_ASIG[ID_ASIG]=ASIGNACION!$G23),"No existe información"))))} -> No existe información | J23: =_xlfn.XLOOKUP(Tabla1[[#This Row],[ID_ASIG_CAM_DET]],MAE_ASIGNATURA[ID_ASIG],MAE_ASIGNATURA[HORAS],0) -> 0 | K23: 4 | L23: =+Tabla1[[#This Row],[CALCULAR HORA]]*Tabla1[[#This Row],[HORAS]] -> 0 | N23: =_xlfn.XLOOKUP(Tabla1[[#This Row],[NOMBRE_DOCENT]],MDOCENTES[DATOS_DOCENTE],MDOCENTES[DEDICACION],"Seleccione Docente") -> Seleccione Docente | O23: =_xlfn.XLOOKUP(Tabla1[[#This Row],[NOMBRE_DOCENT]],MDOCENTES[DATOS_DOCENTE],MDOCENTES[ESTUDIO],"Seleccione Docente") -> Seleccione Docente | P23: =COUNTIFS($M:$M, M23, $H:$H, "<>ACTIVIDAD") -> 0 | Q23: =SUMIFS($L:$L, $M:$M, M23, $I:$I, "NO",$H:$H,"<>UNIDAD BASICA") -> 0 | R23: =SUMIFS($L:$L, $M:$M, M23, $H:$H, "UNIDAD BASICA",$I:$I,"NO") -> 0 | S23: =SUMIFS($L:$L, $M:$M, M23, $I:$I, "ACTIVIDAD") -> 0 | T23: =SUMIFS($L:$L, $M:$M, M23, $I:$I, "SI") -> 0 | U23: =Tabla1[[#This Row],[HORAS NO AFINIDAD]]+Tabla1[[#This Row],[HORAS UNIDAD BASICA]]+Tabla1[[#This Row],[HORAS AFINIDAD]] -> 0 | V23: =+Tabla1[[#This Row],[HORAS AFINIDAD]]+Tabla1[[#This Row],[HORAS ACTIVIDAD]]+Tabla1[[#This Row],[HORAS UNIDAD BASICA]]+Tabla1[[#This Row],[HORAS NO AFINIDAD]] -> 0
... A600: 599 | C600: =_xlfn.XLOOKUP(Tabla1[[#This Row],[CARRERA]],MAE_CARRERA[NOMBRE_CARRERA],MAE_CARRERA[ID_CARRERA],"Seleccione Carrera") -> Seleccione Carrera | G600: =_xlfn.XLOOKUP(Tabla1[[#This Row],[ASIGNATURA]],MAE_ASIGNATURA[NOM_ASIG],MAE_ASIGNATURA[ID_ASIG],"Seleccione Asignatura") -> Seleccione Asignatura | H600: {=_xlfn.TEXTJOIN("; ",TRUE,TRANSPOSE(_xlfn.UNIQUE(_xlfn._xlws.FILTER(DET_ASIG[DETALLADO],(DET_ASIG[NIVEL]=ASIGNACION!$D600)*(DET_ASIG[ID_CARRERA]=ASIGNACION!$C600)*(DET_ASIG[ID_ASIG]=ASIGNACION!$G600),"No existe información"))))} -> No existe información | J600: =_xlfn.XLOOKUP(Tabla1[[#This Row],[ID_ASIG_CAM_DET]],MAE_ASIGNATURA[ID_ASIG],MAE_ASIGNATURA[HORAS],0) -> 0 | K600: 4 | L600: =+Tabla1[[#This Row],[CALCULAR HORA]]*Tabla1[[#This Row],[HORAS]] -> 0 | N600: =_xlfn.XLOOKUP(Tabla1[[#This Row],[NOMBRE_DOCENT]],MDOCENTES[DATOS_DOCENTE],MDOCENTES[DEDICACION],"Seleccione Docente") -> Seleccione Docente | O600: =_xlfn.XLOOKUP(Tabla1[[#This Row],[NOMBRE_DOCENT]],MDOCENTES[DATOS_DOCENTE],MDOCENTES[ESTUDIO],"Seleccione Docente") -> Seleccione Docente | P600: =COUNTIFS($M:$M, M600, $H:$H, "<>ACTIVIDAD") -> 0 | Q600: =SUMIFS($L:$L, $M:$M, M600, $I:$I, "NO",$H:$H,"<>UNIDAD BASICA") -> 0 | R600: =SUMIFS($L:$L, $M:$M, M600, $H:$H, "UNIDAD BASICA",$I:$I,"NO") -> 0 | S600: =SUMIFS($L:$L, $M:$M, M600, $I:$I, "ACTIVIDAD") -> 0 | T600: =SUMIFS($L:$L, $M:$M, M600, $I:$I, "SI") -> 0 | U600: =Tabla1[[#This Row],[HORAS NO AFINIDAD]]+Tabla1[[#This Row],[HORAS UNIDAD BASICA]]+Tabla1[[#This Row],[HORAS AFINIDAD]] -> 0 | V600: =+Tabla1[[#This Row],[HORAS AFINIDAD]]+Tabla1[[#This Row],[HORAS ACTIVIDAD]]+Tabla1[[#This Row],[HORAS UNIDAD BASICA]]+Tabla1[[#This Row],[HORAS NO AFINIDAD]] -> 0

Sheet INTERCAMBIO
BQ1: maestria | EA1: lista docente
A2: {=TRANSPOSE(_xlfn.UNIQUE(_xlfn._xlws.FILTER(MAE_ASIGNATURA[ID_NIVEL],MAE_ASIGNATURA[ID_CARRERA]=ASIGNACION!$C2,"No existe información")))} -> 1 | B2: 2 | C2: 3 | D2: 4 | E2: 5 | F2: 6 | G2: 7 | H2: 8 | S2: {=TRANSPOSE(_xlfn.UNIQUE(_xlfn._xlws.FILTER(MAE_ASIGNATURA[NOM_ASIG],(MAE_ASIGNATURA[ID_NIVEL]=ASIGNACION!$D2)*(MAE_ASIGNATURA[ID_CARRERA]=ASIGNACION!$C2),"No existe información")))} -> CONTABILIDAD BÁSICA | T2: MATEMÁTICA | U2: METODOLOGÍA DE LA INVESTIGACIÓN | V2: ADMINISTRACIÓN | W2: MACROECONOMÍA | BD2: {=TRANSPOSE(_xlfn.UNIQUE(_xlfn._xlws.FILTER(DET_ASIG[DETALLADO],(DET_ASIG[ID_CARRERA]=ASIGNACION!$C2)*(DET_ASIG[NIVEL]=ASIGNACION!$D2)*(DET_ASIG[ID_ASIG]=ASIGNACION!$G2),"No existe información")))} -> UNIDAD BASICA | BQ2: {=IFERROR( TRANSPOSE( _xlfn.UNIQUE( _xlfn._xlws.FILTER(MAESTRIA_DETALLADO[MAESTRIA], ISNUMBER(MATCH(MAESTRIA_DETALLADO[CAMPO_DETALLADO], BD2:BP2,0)) ) ) ),IF(BD2="ACTIVIDAD","DOCENCIA",""))} | EA2: {=IF( ASIGNACION!I2="SI", IFERROR( TRANSPOSE( _xlfn.UNIQUE( _xlfn._xlws.FILTER(EDU_DOCENTE[NOMBRE_DOCENTE], ISNUMBER(MATCH(EDU_DOCENTE[MAESTRIA], BQ2:DY2,0)) ) ) ), "" ), TRANSPOSE( _xlfn.UNIQUE(EDU_DOCENTE[NOMBRE_DOCENTE] ) ) )} -> ALCIVAR CEDEÑO BEATRIZ ISABEL | EB2: ALCIVAR VERA GEMA MICHELLE | EC2: ARAUZ CHAVEZ MARIO ROBERTO | ED2: BAILON LOURIDO WALTER ALBERTO | EE2: CALDERERO VILLAGOMEZ ERICK ANTONIO | EF2: CASTILLO GARCIA PAOLA GERMANIA | EG2: CEDEÑO CHOEZ PEDRO JAVIER | EH2: CEVALLOS HOPPE JUAN CARLOS | EI2: DELGADO CHAVEZ MARIA IRASEMA | EJ2: DUARTE VALENCIA CRISTHIAN DARIO | EK2: FORTTY BARBERAN DENNY ALEXANDER | EL2: GUTIERREZ ZAMBRANO CARMEN EBELINA | EM2: INTRIAGO MOLINA GEMA VALERIA | EN2: LINO VELEZ LEONEL LIVINGTON | EO2: LOOR ALCIVAR MARIA ILIANA | EP2: LOOR MIELES TANIA JACQUELINE | EQ2: LOOR SOLORZANO ROSA MARIA | ER2: LOPEZ DELGADO RONALD MAURICIO | ES2: MACIAS VALENCIA DAVID GABRIEL | ET2: MENDOZA ZAMORA WALTER MANUEL | EU2: MOLINA CEVALLOS MARIA LORENA | EV2: MURILLO DELGADO ISAAC GABRIEL | EW2: ANGULO MURILLO NAVIRA GISSELA | EX2: OCHOA SOLEDISPA NESTOR IVAN | EY2: PARRAGA FRANCO SILVANA MARIELA | EZ2: PINARGOTE VASQUEZ NANCY FABIOLA | FA2: REYES VELEZ PEDRO ENRIQUE | FB2: SAN ANDRES HORMAZA DALLAS CECILIA | FC2: SORNOZA ZAMORA JUAN CARLOS | FD2: TOMALA PINTO JESUS JACINTO | FE2: VALLE JARAMILLO SILVIA ARACELY | FF2: VELÁSQUEZ BRAVO IRMA KATHERINE | FG2: VELEZ MENDOZA LAYSY VALERIA | FH2: VINUEZA TELLO SHIRLEY ELIZABETH | FI2: ZAMBRANO ALCIVAR NILDA ISABEL | FJ2: ZAMBRANO LOOR RITA MAYDA | FK2: ZAMBRANO VERA MONICA JANETH | FL2: VERA DELGADO BRYAN ADRIÁN | FM2: MORAN GONZALES DAVID RENATO | FN2: 0
A3: {=TRANSPOSE(_xlfn.UNIQUE(_xlfn._xlws.FILTER(MAE_ASIGNATURA[ID_NIVEL],MAE_ASIGNATURA[ID_CARRERA]=ASIGNACION!$C3,"No existe información")))} -> 1 | B3: 2 | C3: 3 | D3: 4 | E3: 5 | F3: 6 | G3: 7 | H3: 8 | S3: {=TRANSPOSE(_xlfn.UNIQUE(_xlfn._xlws.FILTER(MAE_ASIGNATURA[NOM_ASIG],(MAE_ASIGNATURA[ID_NIVEL]=ASIGNACION!$D3)*(MAE_ASIGNATURA[ID_CARRERA]=ASIGNACION!$C3),"No existe información")))} -> CONTABILIDAD BÁSICA | T3: MATEMÁTICA | U3: METODOLOGÍA DE LA INVESTIGACIÓN | V3: ADMINISTRACIÓN | W3: MACROECONOMÍA | BD3: {=TRANSPOSE(_xlfn.UNIQUE(_xlfn._xlws.FILTER(DET_ASIG[DETALLADO],(DET_ASIG[ID_CARRERA]=ASIGNACION!$C3)*(DET_ASIG[NIVEL]=ASIGNACION!$D3)*(DET_ASIG[ID_ASIG]=ASIGNACION!$G3),"No existe información")))} -> UNIDAD BASICA | BQ3: {=IFERROR( TRANSPOSE( _xlfn.UNIQUE( _xlfn._xlws.FILTER(MAESTRIA_DETALLADO[MAESTRIA], ISNUMBER(MATCH(MAESTRIA_DETALLADO[CAMPO_DETALLADO], BD3:BP3,0)) ) ) ),IF(BD3="ACTIVIDAD","DOCENCIA",""))} | EA3: {=IF( ASIGNACION!I3="SI", IFERROR( TRANSPOSE( _xlfn.UNIQUE( _xlfn._xlws.FILTER(EDU_DOCENTE[NOMBRE_DOCENTE], ISNUMBER(MATCH(EDU_DOCENTE[MAESTRIA], BQ3:DY3,0)) ) ) ), "" ), TRANSPOSE( _xlfn.UNIQUE(EDU_DOCENTE[NOMBRE_DOCENTE] ) ) )} -> ALCIVAR CEDEÑO BEATRIZ ISABEL | EB3: ALCIVAR VERA GEMA MICHELLE | EC3: ARAUZ CHAVEZ MARIO ROBERTO | ED3: BAILON LOURIDO WALTER ALBERTO | EE3: CALDERERO VILLAGOMEZ ERICK ANTONIO | EF3: CASTILLO GARCIA PAOLA GERMANIA | EG3: CEDEÑO CHOEZ PEDRO JAVIER | EH3: CEVALLOS HOPPE JUAN CARLOS | EI3: DELGADO CHAVEZ MARIA IRASEMA | EJ3: DUARTE VALENCIA CRISTHIAN DARIO | EK3: FORTTY BARBERAN DENNY ALEXANDER | EL3: GUTIERREZ ZAMBRANO CARMEN EBELINA | EM3: INTRIAGO MOLINA GEMA VALERIA | EN3: LINO VELEZ LEONEL LIVINGTON | EO3: LOOR ALCIVAR MARIA ILIANA | EP3: LOOR MIELES TANIA JACQUELINE | EQ3: LOOR SOLORZANO ROSA MARIA | ER3: LOPEZ DELGADO RONALD MAURICIO | ES3: MACIAS VALENCIA DAVID GABRIEL | ET3: MENDOZA ZAMORA WALTER MANUEL | EU3: MOLINA CEVALLOS MARIA LORENA | EV3: MURILLO DELGADO ISAAC GABRIEL | EW3: ANGULO MURILLO NAVIRA GISSELA | EX3: OCHOA SOLEDISPA NESTOR IVAN | EY3: PARRAGA FRANCO SILVANA MARIELA | EZ3: PINARGOTE VASQUEZ NANCY FABIOLA | FA3: REYES VELEZ PEDRO ENRIQUE | FB3: SAN ANDRES HORMAZA DALLAS CECILIA | FC3: SORNOZA ZAMORA JUAN CARLOS | FD3: TOMALA PINTO JESUS JACINTO | FE3: VALLE JARAMILLO SILVIA ARACELY | FF3: VELÁSQUEZ BRAVO IRMA KATHERINE | FG3: VELEZ MENDOZA LAYSY VALERIA | FH3: VINUEZA TELLO SHIRLEY ELIZABETH | FI3: ZAMBRANO ALCIVAR NILDA ISABEL | FJ3: ZAMBRANO LOOR RITA MAYDA | FK3: ZAMBRANO VERA MONICA JANETH | FL3: VERA DELGADO BRYAN ADRIÁN | FM3: MORAN GONZALES DAVID RENATO | FN3: 0
A4: {=TRANSPOSE(_xlfn.UNIQUE(_xlfn._xlws.FILTER(MAE_ASIGNATURA[ID_NIVEL],MAE_ASIGNATURA[ID_CARRERA]=ASIGNACION!$C4,"No existe información")))} -> 1 | B4: 2 | C4: 3 | D4: 4 | E4: 5 | F4: 6 | G4: 7 | H4: 8 | S4: {=TRANSPOSE(_xlfn.UNIQUE(_xlfn._xlws.FILTER(MAE_ASIGNATURA[NOM_ASIG],(MAE_ASIGNATURA[ID_NIVEL]=ASIGNACION!$D4)*(MAE_ASIGNATURA[ID_CARRERA]=ASIGNACION!$C4),"No existe información")))} -> CONTABILIDAD BÁSICA | T4: MATEMÁTICA | U4: METODOLOGÍA DE LA INVESTIGACIÓN | V4: ADMINISTRACIÓN | W4: MACROECONOMÍA | BD4: {=TRANSPOSE(_xlfn.UNIQUE(_xlfn._xlws.FILTER(DET_ASIG[DETALLADO],(DET_ASIG[ID_CARRERA]=ASIGNACION!$C4)*(DET_ASIG[NIVEL]=ASIGNACION!$D4)*(DET_ASIG[ID_ASIG]=ASIGNACION!$G4),"No existe información")))} -> UNIDAD BASICA | BQ4: {=IFERROR( TRANSPOSE( _xlfn.UNIQUE( _xlfn._xlws.FILTER(MAESTRIA_DETALLADO[MAESTRIA], ISNUMBER(MATCH(MAESTRIA_DETALLADO[CAMPO_DETALLADO], BD4:BP4,0)) ) ) ),IF(BD4="ACTIVIDAD","DOCENCIA",""))} | EA4: {=IF( ASIGNACION!I4="SI", IFERROR( TRANSPOSE( _xlfn.UNIQUE( _xlfn._xlws.FILTER(EDU_DOCENTE[NOMBRE_DOCENTE], ISNUMBER(MATCH(EDU_DOCENTE[MAESTRIA], BQ4:DY4,0)) ) ) ), "" ), TRANSPOSE( _xlfn.UNIQUE(EDU_DOCENTE[NOMBRE_DOCENTE] ) ) )} -> ALCIVAR CEDEÑO BEATRIZ ISABEL | EB4: ALCIVAR VERA GEMA MICHELLE | EC4: ARAUZ CHAVEZ MARIO ROBERTO | ED4: BAILON LOURIDO WALTER ALBERTO | EE4: CALDERERO VILLAGOMEZ ERICK ANTONIO | EF4: CASTILLO GARCIA PAOLA GERMANIA | EG4: CEDEÑO CHOEZ PEDRO JAVIER | EH4: CEVALLOS HOPPE JUAN CARLOS | EI4: DELGADO CHAVEZ MARIA IRASEMA | EJ4: DUARTE VALENCIA CRISTHIAN DARIO | EK4: FORTTY BARBERAN DENNY ALEXANDER | EL4: GUTIERREZ ZAMBRANO CARMEN EBELINA | EM4: INTRIAGO MOLINA GEMA VALERIA | EN4: LINO VELEZ LEONEL LIVINGTON | EO4: LOOR ALCIVAR MARIA ILIANA | EP4: LOOR MIELES TANIA JACQUELINE | EQ4: LOOR SOLORZANO ROSA MARIA | ER4: LOPEZ DELGADO RONALD MAURICIO | ES4: MACIAS VALENCIA DAVID GABRIEL | ET4: MENDOZA ZAMORA WALTER MANUEL | EU4: MOLINA CEVALLOS MARIA LORENA | EV4: MURILLO DELGADO ISAAC GABRIEL | EW4: ANGULO MURILLO NAVIRA GISSELA | EX4: OCHOA SOLEDISPA NESTOR IVAN | EY4: PARRAGA FRANCO SILVANA MARIELA | EZ4: PINARGOTE VASQUEZ NANCY FABIOLA | FA4: REYES VELEZ PEDRO ENRIQUE | FB4: SAN ANDRES HORMAZA DALLAS CECILIA | FC4: SORNOZA ZAMORA JUAN CARLOS | FD4: TOMALA PINTO JESUS JACINTO | FE4: VALLE JARAMILLO SILVIA ARACELY | FF4: VELÁSQUEZ BRAVO IRMA KATHERINE | FG4: VELEZ MENDOZA LAYSY VALERIA | FH4: VINUEZA TELLO SHIRLEY ELIZABETH | FI4: ZAMBRANO ALCIVAR NILDA ISABEL | FJ4: ZAMBRANO LOOR RITA MAYDA | FK4: ZAMBRANO VERA MONICA JANETH | FL4: VERA DELGADO BRYAN ADRIÁN | FM4: MORAN GONZALES DAVID RENATO | FN4: 0
A5: {=TRANSPOSE(_xlfn.UNIQUE(_xlfn._xlws.FILTER(MAE_ASIGNATURA[ID_NIVEL],MAE_ASIGNATURA[ID_CARRERA]=ASIGNACION!$C5,"No existe información")))} -> 1 | B5: 2 | C5: 3 | D5: 4 | E5: 5 | F5: 6 | G5: 7 | H5: 8 | S5: {=TRANSPOSE(_xlfn.UNIQUE(_xlfn._xlws.FILTER(MAE_ASIGNATURA[NOM_ASIG],(MAE_ASIGNATURA[ID_NIVEL]=ASIGNACION!$D5)*(MAE_ASIGNATURA[ID_CARRERA]=ASIGNACION!$C5),"No existe información")))} -> CONTABILIDAD BÁSICA | T5: MATEMÁTICA | U5: METODOLOGÍA DE LA INVESTIGACIÓN | V5: ADMINISTRACIÓN | W5: MACROECONOMÍA | BD5: {=TRANSPOSE(_xlfn.UNIQUE(_xlfn._xlws.FILTER(DET_ASIG[DETALLADO],(DET_ASIG[ID_CARRERA]=ASIGNACION!$C5)*(DET_ASIG[NIVEL]=ASIGNACION!$D5)*(DET_ASIG[ID_ASIG]=ASIGNACION!$G5),"No existe información")))} -> UNIDAD BASICA | BQ5: {=IFERROR( TRANSPOSE( _xlfn.UNIQUE( _xlfn._xlws.FILTER(MAESTRIA_DETALLADO[MAESTRIA], ISNUMBER(MATCH(MAESTRIA_DETALLADO[CAMPO_DETALLADO], BD5:BP5,0)) ) ) ),IF(BD5="ACTIVIDAD","DOCENCIA",""))} | EA5: {=IF( ASIGNACION!I5="SI", IFERROR( TRANSPOSE( _xlfn.UNIQUE( _xlfn._xlws.FILTER(EDU_DOCENTE[NOMBRE_DOCENTE], ISNUMBER(MATCH(EDU_DOCENTE[MAESTRIA], BQ5:DY5,0)) ) ) ), "" ), TRANSPOSE( _xlfn.UNIQUE(EDU_DOCENTE[NOMBRE_DOCENTE] ) ) )} -> ALCIVAR CEDEÑO BEATRIZ ISABEL | EB5: ALCIVAR VERA GEMA MICHELLE | EC5: ARAUZ CHAVEZ MARIO ROBERTO | ED5: BAILON LOURIDO WALTER ALBERTO | EE5: CALDERERO VILLAGOMEZ ERICK ANTONIO | EF5: CASTILLO GARCIA PAOLA GERMANIA | EG5: CEDEÑO CHOEZ PEDRO JAVIER | EH5: CEVALLOS HOPPE JUAN CARLOS | EI5: DELGADO CHAVEZ MARIA IRASEMA | EJ5: DUARTE VALENCIA CRISTHIAN DARIO | EK5: FORTTY BARBERAN DENNY ALEXANDER | EL5: GUTIERREZ ZAMBRANO CARMEN EBELINA | EM5: INTRIAGO MOLINA GEMA VALERIA | EN5: LINO VELEZ LEONEL LIVINGTON | EO5: LOOR ALCIVAR MARIA ILIANA | EP5: LOOR MIELES TANIA JACQUELINE | EQ5: LOOR SOLORZANO ROSA MARIA | ER5: LOPEZ DELGADO RONALD MAURICIO | ES5: MACIAS VALENCIA DAVID GABRIEL | ET5: MENDOZA ZAMORA WALTER MANUEL | EU5: MOLINA CEVALLOS MARIA LORENA | EV5: MURILLO DELGADO ISAAC GABRIEL | EW5: ANGULO MURILLO NAVIRA GISSELA | EX5: OCHOA SOLEDISPA NESTOR IVAN | EY5: PARRAGA FRANCO SILVANA MARIELA | EZ5: PINARGOTE VASQUEZ NANCY FABIOLA | FA5: REYES VELEZ PEDRO ENRIQUE | FB5: SAN ANDRES HORMAZA DALLAS CECILIA | FC5: SORNOZA ZAMORA JUAN CARLOS | FD5: TOMALA PINTO JESUS JACINTO | FE5: VALLE JARAMILLO SILVIA ARACELY | FF5: VELÁSQUEZ BRAVO IRMA KATHERINE | FG5: VELEZ MENDOZA LAYSY VALERIA | FH5: VINUEZA TELLO SHIRLEY ELIZABETH | FI5: ZAMBRANO ALCIVAR NILDA ISABEL | FJ5: ZAMBRANO LOOR RITA MAYDA | FK5: ZAMBRANO VERA MONICA JANETH | FL5: VERA DELGADO BRYAN ADRIÁN | FM5: MORAN GONZALES DAVID RENATO | FN5: 0
A6: {=TRANSPOSE(_xlfn.UNIQUE(_xlfn._xlws.FILTER(MAE_ASIGNATURA[ID_NIVEL],MAE_ASIGNATURA[ID_CARRERA]=ASIGNACION!$C6,"No existe información")))} -> 1 | B6: 2 | C6: 3 | D6: 4 | E6: 5 | F6: 6 | G6: 7 | H6: 8 | S6: {=TRANSPOSE(_xlfn.UNIQUE(_xlfn._xlws.FILTER(MAE_ASIGNATURA[NOM_ASIG],(MAE_ASIGNATURA[ID_NIVEL]=ASIGNACION!$D6)*(MAE_ASIGNATURA[ID_CARRERA]=ASIGNACION!$C6),"No existe información")))} -> CONTABILIDAD BÁSICA | T6: MATEMÁTICA | U6: METODOLOGÍA DE LA INVESTIGACIÓN | V6: ADMINISTRACIÓN | W6: MACROECONOMÍA | BD6: {=TRANSPOSE(_xlfn.UNIQUE(_xlfn._xlws.FILTER(DET_ASIG[DETALLADO],(DET_ASIG[ID_CARRERA]=ASIGNACION!$C6)*(DET_ASIG[NIVEL]=ASIGNACION!$D6)*(DET_ASIG[ID_ASIG]=ASIGNACION!$G6),"No existe información")))} -> UNIDAD BASICA | BQ6: {=IFERROR( TRANSPOSE( _xlfn.UNIQUE( _xlfn._xlws.FILTER(MAESTRIA_DETALLADO[MAESTRIA], ISNUMBER(MATCH(MAESTRIA_DETALLADO[CAMPO_DETALLADO], BD6:BP6,0)) ) ) ),IF(BD6="ACTIVIDAD","DOCENCIA",""))} | EA6: {=IF( ASIGNACION!I6="SI", IFERROR( TRANSPOSE( _xlfn.UNIQUE( _xlfn._xlws.FILTER(EDU_DOCENTE[NOMBRE_DOCENTE], ISNUMBER(MATCH(EDU_DOCENTE[MAESTRIA], BQ6:DY6,0)) ) ) ), "" ), TRANSPOSE( _xlfn.UNIQUE(EDU_DOCENTE[NOMBRE_DOCENTE] ) ) )} -> ALCIVAR CEDEÑO BEATRIZ ISABEL | EB6: ALCIVAR VERA GEMA MICHELLE | EC6: ARAUZ CHAVEZ MARIO ROBERTO | ED6: BAILON LOURIDO WALTER ALBERTO | EE6: CALDERERO VILLAGOMEZ ERICK ANTONIO | EF6: CASTILLO GARCIA PAOLA GERMANIA | EG6: CEDEÑO CHOEZ PEDRO JAVIER | EH6: CEVALLOS HOPPE JUAN CARLOS | EI6: DELGADO CHAVEZ MARIA IRASEMA | EJ6: DUARTE VALENCIA CRISTHIAN DARIO | EK6: FORTTY BARBERAN DENNY ALEXANDER | EL6: GUTIERREZ ZAMBRANO CARMEN EBELINA | EM6: INTRIAGO MOLINA GEMA VALERIA | EN6: LINO VELEZ LEONEL LIVINGTON | EO6: LOOR ALCIVAR MARIA ILIANA | EP6: LOOR MIELES TANIA JACQUELINE | EQ6: LOOR SOLORZANO ROSA MARIA | ER6: LOPEZ DELGADO RONALD MAURICIO | ES6: MACIAS VALENCIA DAVID GABRIEL | ET6: MENDOZA ZAMORA WALTER MANUEL | EU6: MOLINA CEVALLOS MARIA LORENA | EV6: MURILLO DELGADO ISAAC GABRIEL | EW6: ANGULO MURILLO NAVIRA GISSELA | EX6: OCHOA SOLEDISPA NESTOR IVAN | EY6: PARRAGA FRANCO SILVANA MARIELA | EZ6: PINARGOTE VASQUEZ NANCY FABIOLA | FA6: REYES VELEZ PEDRO ENRIQUE | FB6: SAN ANDRES HORMAZA DALLAS CECILIA | FC6: SORNOZA ZAMORA JUAN CARLOS | FD6: TOMALA PINTO JESUS JACINTO | FE6: VALLE JARAMILLO SILVIA ARACELY | FF6: VELÁSQUEZ BRAVO IRMA KATHERINE | FG6: VELEZ MENDOZA LAYSY VALERIA | FH6: VINUEZA TELLO SHIRLEY ELIZABETH | FI6: ZAMBRANO ALCIVAR NILDA ISABEL | FJ6: ZAMBRANO LOOR RITA MAYDA | FK6: ZAMBRANO VERA MONICA JANETH | FL6: VERA DELGADO BRYAN ADRIÁN | FM6: MORAN GONZALES DAVID RENATO | FN6: 0
A7: {=TRANSPOSE(_xlfn.UNIQUE(_xlfn._xlws.FILTER(MAE_ASIGNATURA[ID_NIVEL],MAE_ASIGNATURA[ID_CARRERA]=ASIGNACION!$C7,"No existe información")))} -> 1 | B7: 2 | C7: 3 | D7: 4 | E7: 5 | F7: 6 | G7: 7 | H7: 8 | S7: {=TRANSPOSE(_xlfn.UNIQUE(_xlfn._xlws.FILTER(MAE_ASIGNATURA[NOM_ASIG],(MAE_ASIGNATURA[ID_NIVEL]=ASIGNACION!$D7)*(MAE_ASIGNATURA[ID_CARRERA]=ASIGNACION!$C7),"No existe información")))} -> CONTABILIDAD BÁSICA | T7: MATEMÁTICA | U7: METODOLOGÍA DE LA INVESTIGACIÓN | V7: ADMINISTRACIÓN | W7: MACROECONOMÍA | BD7: {=TRANSPOSE(_xlfn.UNIQUE(_xlfn._xlws.FILTER(DET_ASIG[DETALLADO],(DET_ASIG[ID_CARRERA]=ASIGNACION!$C7)*(DET_ASIG[NIVEL]=ASIGNACION!$D7)*(DET_ASIG[ID_ASIG]=ASIGNACION!$G7),"No existe información")))} -> UNIDAD BASICA | BQ7: {=IFERROR( TRANSPOSE( _xlfn.UNIQUE( _xlfn._xlws.FILTER(MAESTRIA_DETALLADO[MAESTRIA], ISNUMBER(MATCH(MAESTRIA_DETALLADO[CAMPO_DETALLADO], BD7:BP7,0)) ) ) ),IF(BD7="ACTIVIDAD","DOCENCIA",""))} | EA7: {=IF( ASIGNACION!I7="SI", IFERROR( TRANSPOSE( _xlfn.UNIQUE( _xlfn._xlws.FILTER(EDU_DOCENTE[NOMBRE_DOCENTE], ISNUMBER(MATCH(EDU_DOCENTE[MAESTRIA], BQ7:DY7,0)) ) ) ), "" ), TRANSPOSE( _xlfn.UNIQUE(EDU_DOCENTE[NOMBRE_DOCENTE] ) ) )} -> ALCIVAR CEDEÑO BEATRIZ ISABEL | EB7: ALCIVAR VERA GEMA MICHELLE | EC7: ARAUZ CHAVEZ MARIO ROBERTO | ED7: BAILON LOURIDO WALTER ALBERTO | EE7: CALDERERO VILLAGOMEZ ERICK ANTONIO | EF7: CASTILLO GARCIA PAOLA GERMANIA | EG7: CEDEÑO CHOEZ PEDRO JAVIER | EH7: CEVALLOS HOPPE JUAN CARLOS | EI7: DELGADO CHAVEZ MARIA IRASEMA | EJ7: DUARTE VALENCIA CRISTHIAN DARIO | EK7: FORTTY BARBERAN DENNY ALEXANDER | EL7: GUTIERREZ ZAMBRANO CARMEN EBELINA | EM7: INTRIAGO MOLINA GEMA VALERIA | EN7: LINO VELEZ LEONEL LIVINGTON | EO7: LOOR ALCIVAR MARIA ILIANA | EP7: LOOR MIELES TANIA JACQUELINE | EQ7: LOOR SOLORZANO ROSA MARIA | ER7: LOPEZ DELGADO RONALD MAURICIO | ES7: MACIAS VALENCIA DAVID GABRIEL | ET7: MENDOZA ZAMORA WALTER MANUEL | EU7: MOLINA CEVALLOS MARIA LORENA | EV7: MURILLO DELGADO ISAAC GABRIEL | EW7: ANGULO MURILLO NAVIRA GISSELA | EX7: OCHOA SOLEDISPA NESTOR IVAN | EY7: PARRAGA FRANCO SILVANA MARIELA | EZ7: PINARGOTE VASQUEZ NANCY FABIOLA | FA7: REYES VELEZ PEDRO ENRIQUE | FB7: SAN ANDRES HORMAZA DALLAS CECILIA | FC7: SORNOZA ZAMORA JUAN CARLOS | FD7: TOMALA PINTO JESUS JACINTO | FE7: VALLE JARAMILLO SILVIA ARACELY | FF7: VELÁSQUEZ BRAVO IRMA KATHERINE | FG7: VELEZ MENDOZA LAYSY VALERIA | FH7: VINUEZA TELLO SHIRLEY ELIZABETH | FI7: ZAMBRANO ALCIVAR NILDA ISABEL | FJ7: ZAMBRANO LOOR RITA MAYDA | FK7: ZAMBRANO VERA MONICA JANETH | FL7: VERA DELGADO BRYAN ADRIÁN | FM7: MORAN GONZALES DAVID RENATO | FN7: 0
A8: {=TRANSPOSE(_xlfn.UNIQUE(_xlfn._xlws.FILTER(MAE_ASIGNATURA[ID_NIVEL],MAE_ASIGNATURA[ID_CARRERA]=ASIGNACION!$C8,"No existe información")))} -> 0 | S8: {=TRANSPOSE(_xlfn.UNIQUE(_xlfn._xlws.FILTER(MAE_ASIGNATURA[NOM_ASIG],(MAE_ASIGNATURA[ID_NIVEL]=ASIGNACION!$D8)*(MAE_ASIGNATURA[ID_CARRERA]=ASIGNACION!$C8),"No existe información")))} -> AD5 Elaboración y calificación de evaluaciones | T8: AD4 Preparación de Clases | U8: AD6 Orientación a través de Tutorías | V8: AD8 Participación en colectivos académicos sobre docencia | BD8: {=TRANSPOSE(_xlfn.UNIQUE(_xlfn._xlws.FILTER(DET_ASIG[DETALLADO],(DET_ASIG[ID_CARRERA]=ASIGNACION!$C8)*(DET_ASIG[NIVEL]=ASIGNACION!$D8)*(DET_ASIG[ID_ASIG]=ASIGNACION!$G8),"No existe información")))} -> ACTIVIDAD | BQ8: {=IFERROR( TRANSPOSE( _xlfn.UNIQUE( _xlfn._xlws.FILTER(MAESTRIA_DETALLADO[MAESTRIA], ISNUMBER(MATCH(MAESTRIA_DETALLADO[CAMPO_DETALLADO], BD8:BP8,0)) ) ) ),IF(BD8="ACTIVIDAD","DOCENCIA",""))} -> DOCENCIA | EA8: {=IF( ASIGNACION!I8="SI", IFERROR( TRANSPOSE( _xlfn.UNIQUE( _xlfn._xlws.FILTER(EDU_DOCENTE[NOMBRE_DOCENTE], ISNUMBER(MATCH(EDU_DOCENTE[MAESTRIA], BQ8:DY8,0)) ) ) ), "" ), TRANSPOSE( _xlfn.UNIQUE(EDU_DOCENTE[NOMBRE_DOCENTE] ) ) )} -> ALCIVAR CEDEÑO BEATRIZ ISABEL | EB8: ALCIVAR VERA GEMA MICHELLE | EC8: ARAUZ CHAVEZ MARIO ROBERTO | ED8: BAILON LOURIDO WALTER ALBERTO | EE8: CALDERERO VILLAGOMEZ ERICK ANTONIO | EF8: CASTILLO GARCIA PAOLA GERMANIA | EG8: CEDEÑO CHOEZ PEDRO JAVIER | EH8: CEVALLOS HOPPE JUAN CARLOS | EI8: DELGADO CHAVEZ MARIA IRASEMA | EJ8: DUARTE VALENCIA CRISTHIAN DARIO | EK8: FORTTY BARBERAN DENNY ALEXANDER | EL8: GUTIERREZ ZAMBRANO CARMEN EBELINA | EM8: INTRIAGO MOLINA GEMA VALERIA | EN8: LINO VELEZ LEONEL LIVINGTON | EO8: LOOR ALCIVAR MARIA ILIANA | EP8: LOOR MIELES TANIA JACQUELINE | EQ8: LOOR SOLORZANO ROSA MARIA | ER8: LOPEZ DELGADO RONALD MAURICIO | ES8: MACIAS VALENCIA DAVID GABRIEL | ET8: MENDOZA ZAMORA WALTER MANUEL | EU8: MOLINA CEVALLOS MARIA LORENA | EV8: MURILLO DELGADO ISAAC GABRIEL | EW8: ANGULO MURILLO NAVIRA GISSELA | EX8: OCHOA SOLEDISPA NESTOR IVAN | EY8: PARRAGA FRANCO SILVANA MARIELA | EZ8: PINARGOTE VASQUEZ NANCY FABIOLA | FA8: REYES VELEZ PEDRO ENRIQUE | FB8: SAN ANDRES HORMAZA DALLAS CECILIA | FC8: SORNOZA ZAMORA JUAN CARLOS | FD8: TOMALA PINTO JESUS JACINTO | FE8: VALLE JARAMILLO SILVIA ARACELY | FF8: VELÁSQUEZ BRAVO IRMA KATHERINE | FG8: VELEZ MENDOZA LAYSY VALERIA | FH8: VINUEZA TELLO SHIRLEY ELIZABETH | FI8: ZAMBRANO ALCIVAR NILDA ISABEL | FJ8: ZAMBRANO LOOR RITA MAYDA | FK8: ZAMBRANO VERA MONICA JANETH | FL8: VERA DELGADO BRYAN ADRIÁN | FM8: MORAN GONZALES DAVID RENATO | FN8: 0
A9: {=TRANSPOSE(_xlfn.UNIQUE(_xlfn._xlws.FILTER(MAE_ASIGNATURA[ID_NIVEL],MAE_ASIGNATURA[ID_CARRERA]=ASIGNACION!$C9,"No existe información")))} -> 0 | S9: {=TRANSPOSE(_xlfn.UNIQUE(_xlfn._xlws.FILTER(MAE_ASIGNATURA[NOM_ASIG],(MAE_ASIGNATURA[ID_NIVEL]=ASIGNACION!$D9)*(MAE_ASIGNATURA[ID_CARRERA]=ASIGNACION!$C9),"No existe información")))} -> AD5 Elaboración y calificación de evaluaciones | T9: AD4 Preparación de Clases | U9: AD6 Orientación a través de Tutorías | V9: AD8 Participación en colectivos académicos sobre docencia | BD9: {=TRANSPOSE(_xlfn.UNIQUE(_xlfn._xlws.FILTER(DET_ASIG[DETALLADO],(DET_ASIG[ID_CARRERA]=ASIGNACION!$C9)*(DET_ASIG[NIVEL]=ASIGNACION!$D9)*(DET_ASIG[ID_ASIG]=ASIGNACION!$G9),"No existe información")))} -> ACTIVIDAD | BQ9: {=IFERROR( TRANSPOSE( _xlfn.UNIQUE( _xlfn._xlws.FILTER(MAESTRIA_DETALLADO[MAESTRIA], ISNUMBER(MATCH(MAESTRIA_DETALLADO[CAMPO_DETALLADO], BD9:BP9,0)) ) ) ),IF(BD9="ACTIVIDAD","DOCENCIA",""))} -> DOCENCIA | EA9: {=IF( ASIGNACION!I9="SI", IFERROR( TRANSPOSE( _xlfn.UNIQUE( _xlfn._xlws.FILTER(EDU_DOCENTE[NOMBRE_DOCENTE], ISNUMBER(MATCH(EDU_DOCENTE[MAESTRIA], BQ9:DY9,0)) ) ) ), "" ), TRANSPOSE( _xlfn.UNIQUE(EDU_DOCENTE[NOMBRE_DOCENTE] ) ) )} -> ALCIVAR CEDEÑO BEATRIZ ISABEL | EB9: ALCIVAR VERA GEMA MICHELLE | EC9: ARAUZ CHAVEZ MARIO ROBERTO | ED9: BAILON LOURIDO WALTER ALBERTO | EE9: CALDERERO VILLAGOMEZ ERICK ANTONIO | EF9: CASTILLO GARCIA PAOLA GERMANIA | EG9: CEDEÑO CHOEZ PEDRO JAVIER | EH9: CEVALLOS HOPPE JUAN CARLOS | EI9: DELGADO CHAVEZ MARIA IRASEMA | EJ9: DUARTE VALENCIA CRISTHIAN DARIO | EK9: FORTTY BARBERAN DENNY ALEXANDER | EL9: GUTIERREZ ZAMBRANO CARMEN EBELINA | EM9: INTRIAGO MOLINA GEMA VALERIA | EN9: LINO VELEZ LEONEL LIVINGTON | EO9: LOOR ALCIVAR MARIA ILIANA | EP9: LOOR MIELES TANIA JACQUELINE | EQ9: LOOR SOLORZANO ROSA MARIA | ER9: LOPEZ DELGADO RONALD MAURICIO | ES9: MACIAS VALENCIA DAVID GABRIEL | ET9: MENDOZA ZAMORA WALTER MANUEL | EU9: MOLINA CEVALLOS MARIA LORENA | EV9: MURILLO DELGADO ISAAC GABRIEL | EW9: ANGULO MURILLO NAVIRA GISSELA | EX9: OCHOA SOLEDISPA NESTOR IVAN | EY9: PARRAGA FRANCO SILVANA MARIELA | EZ9: PINARGOTE VASQUEZ NANCY FABIOLA | FA9: REYES VELEZ PEDRO ENRIQUE | FB9: SAN ANDRES HORMAZA DALLAS CECILIA | FC9: SORNOZA ZAMORA JUAN CARLOS | FD9: TOMALA PINTO JESUS JACINTO | FE9: VALLE JARAMILLO SILVIA ARACELY | FF9: VELÁSQUEZ BRAVO IRMA KATHERINE | FG9: VELEZ MENDOZA LAYSY VALERIA | FH9: VINUEZA TELLO SHIRLEY ELIZABETH | FI9: ZAMBRANO ALCIVAR NILDA ISABEL | FJ9: ZAMBRANO LOOR RITA MAYDA | FK9: ZAMBRANO VERA MONICA JANETH | FL9: VERA DELGADO BRYAN ADRIÁN | FM9: MORAN GONZALES DAVID RENATO | FN9: 0
A10: {=TRANSPOSE(_xlfn.UNIQUE(_xlfn._xlws.FILTER(MAE_ASIGNATURA[ID_NIVEL],MAE_ASIGNATURA[ID_CARRERA]=ASIGNACION!$C10,"No existe información")))} -> 0 | S10: {=TRANSPOSE(_xlfn.UNIQUE(_xlfn._xlws.FILTER(MAE_ASIGNATURA[NOM_ASIG],(MAE_ASIGNATURA[ID_NIVEL]=ASIGNACION!$D10)*(MAE_ASIGNATURA[ID_CARRERA]=ASIGNACION!$C10),"No existe información")))} -> AD5 Elaboración y calificación de evaluaciones | T10: AD4 Preparación de Clases | U10: AD6 Orientación a través de Tutorías | V10: AD8 Participación en colectivos académicos sobre docencia | BD10: {=TRANSPOSE(_xlfn.UNIQUE(_xlfn._xlws.FILTER(DET_ASIG[DETALLADO],(DET_ASIG[ID_CARRERA]=ASIGNACION!$C10)*(DET_ASIG[NIVEL]=ASIGNACION!$D10)*(DET_ASIG[ID_ASIG]=ASIGNACION!$G10),"No existe información")))} -> ACTIVIDAD | BQ10: {=IFERROR( TRANSPOSE( _xlfn.UNIQUE( _xlfn._xlws.FILTER(MAESTRIA_DETALLADO[MAESTRIA], ISNUMBER(MATCH(MAESTRIA_DETALLADO[CAMPO_DETALLADO], BD10:BP10,0)) ) ) ),IF(BD10="ACTIVIDAD","DOCENCIA",""))} -> DOCENCIA | EA10: {=IF( ASIGNACION!I10="SI", IFERROR( TRANSPOSE( _xlfn.UNIQUE( _xlfn._xlws.FILTER(EDU_DOCENTE[NOMBRE_DOCENTE], ISNUMBER(MATCH(EDU_DOCENTE[MAESTRIA], BQ10:DY10,0)) ) ) ), "" ), TRANSPOSE( _xlfn.UNIQUE(EDU_DOCENTE[NOMBRE_DOCENTE] ) ) )} -> ALCIVAR CEDEÑO BEATRIZ ISABEL | EB10: ALCIVAR VERA GEMA MICHELLE | EC10: ARAUZ CHAVEZ MARIO ROBERTO | ED10: BAILON LOURIDO WALTER ALBERTO | EE10: CALDERERO VILLAGOMEZ ERICK ANTONIO | EF10: CASTILLO GARCIA PAOLA GERMANIA | EG10: CEDEÑO CHOEZ PEDRO JAVIER | EH10: CEVALLOS HOPPE JUAN CARLOS | EI10: DELGADO CHAVEZ MARIA IRASEMA | EJ10: DUARTE VALENCIA CRISTHIAN DARIO | EK10: FORTTY BARBERAN DENNY ALEXANDER | EL10: GUTIERREZ ZAMBRANO CARMEN EBELINA | EM10: INTRIAGO MOLINA GEMA VALERIA | EN10: LINO VELEZ LEONEL LIVINGTON | EO10: LOOR ALCIVAR MARIA ILIANA | EP10: LOOR MIELES TANIA JACQUELINE | EQ10: LOOR SOLORZANO ROSA MARIA | ER10: LOPEZ DELGADO RONALD MAURICIO | ES10: MACIAS VALENCIA DAVID GABRIEL | ET10: MENDOZA ZAMORA WALTER MANUEL | EU10: MOLINA CEVALLOS MARIA LORENA | EV10: MURILLO DELGADO ISAAC GABRIEL | EW10: ANGULO MURILLO NAVIRA GISSELA | EX10: OCHOA SOLEDISPA NESTOR IVAN | EY10: PARRAGA FRANCO SILVANA MARIELA | EZ10: PINARGOTE VASQUEZ NANCY FABIOLA | FA10: REYES VELEZ PEDRO ENRIQUE | FB10: SAN ANDRES HORMAZA DALLAS CECILIA | FC10: SORNOZA ZAMORA JUAN CARLOS | FD10: TOMALA PINTO JESUS JACINTO | FE10: VALLE JARAMILLO SILVIA ARACELY | FF10: VELÁSQUEZ BRAVO IRMA KATHERINE | FG10: VELEZ MENDOZA LAYSY VALERIA | FH10: VINUEZA TELLO SHIRLEY ELIZABETH | FI10: ZAMBRANO ALCIVAR NILDA ISABEL | FJ10: ZAMBRANO LOOR RITA MAYDA | FK10: ZAMBRANO VERA MONICA JANETH | FL10: VERA DELGADO BRYAN ADRIÁN | FM10: MORAN GONZALES DAVID RENATO | FN10: 0
A11: {=TRANSPOSE(_xlfn.UNIQUE(_xlfn._xlws.FILTER(MAE_ASIGNATURA[ID_NIVEL],MAE_ASIGNATURA[ID_CARRERA]=ASIGNACION!$C11,"No existe información")))} -> 1 | B11: 2 | C11: 3 | D11: 4 | E11: 5 | F11: 6 | G11: 7 | H11: 8 | S11: {=TRANSPOSE(_xlfn.UNIQUE(_xlfn._xlws.FILTER(MAE_ASIGNATURA[NOM_ASIG],(MAE_ASIGNATURA[ID_NIVEL]=ASIGNACION!$D11)*(MAE_ASIGNATURA[ID_CARRERA]=ASIGNACION!$C11),"No existe información")))} -> LEGISLACIÓN LABORAL | T11: CONTABILIDAD INTERMEDIA | U11: ESTADÍSTICA DESCRIPTIVA | V11: LEGISLACIÓN MERCANTIL Y SOCIETARIA | W11: MATEMÁTICA FINANCIERA | BD11: {=TRANSPOSE(_xlfn.UNIQUE(_xlfn._xlws.FILTER(DET_ASIG[DETALLADO],(DET_ASIG[ID_CARRERA]=ASIGNACION!$C11)*(DET_ASIG[NIVEL]=ASIGNACION!$D11)*(DET_ASIG[ID_ASIG]=ASIGNACION!$G11),"No existe información")))} -> UNIDAD BASICA | BQ11: {=IFERROR( TRANSPOSE( _xlfn.UNIQUE( _xlfn._xlws.FILTER(MAESTRIA_DETALLADO[MAESTRIA], ISNUMBER(MATCH(MAESTRIA_DETALLADO[CAMPO_DETALLADO], BD11:BP11,0)) ) ) ),IF(BD11="ACTIVIDAD","DOCENCIA",""))} | EA11: {=IF( ASIGNACION!I11="SI", IFERROR( TRANSPOSE( _xlfn.UNIQUE( _xlfn._xlws.FILTER(EDU_DOCENTE[NOMBRE_DOCENTE], ISNUMBER(MATCH(EDU_DOCENTE[MAESTRIA], BQ11:DY11,0)) ) ) ), "" ), TRANSPOSE( _xlfn.UNIQUE(EDU_DOCENTE[NOMBRE_DOCENTE] ) ) )} -> ALCIVAR CEDEÑO BEATRIZ ISABEL | EB11: ALCIVAR VERA GEMA MICHELLE | EC11: ARAUZ CHAVEZ MARIO ROBERTO | ED11: BAILON LOURIDO WALTER ALBERTO | EE11: CALDERERO VILLAGOMEZ ERICK ANTONIO | EF11: CASTILLO GARCIA PAOLA GERMANIA | EG11: CEDEÑO CHOEZ PEDRO JAVIER | EH11: CEVALLOS HOPPE JUAN CARLOS | EI11: DELGADO CHAVEZ MARIA IRASEMA | EJ11: DUARTE VALENCIA CRISTHIAN DARIO | EK11: FORTTY BARBERAN DENNY ALEXANDER | EL11: GUTIERREZ ZAMBRANO CARMEN EBELINA | EM11: INTRIAGO MOLINA GEMA VALERIA | EN11: LINO VELEZ LEONEL LIVINGTON | EO11: LOOR ALCIVAR MARIA ILIANA | EP11: LOOR MIELES TANIA JACQUELINE | EQ11: LOOR SOLORZANO ROSA MARIA | ER11: LOPEZ DELGADO RONALD MAURICIO | ES11: MACIAS VALENCIA DAVID GABRIEL | ET11: MENDOZA ZAMORA WALTER MANUEL | EU11: MOLINA CEVALLOS MARIA LORENA | EV11: MURILLO DELGADO ISAAC GABRIEL | EW11: ANGULO MURILLO NAVIRA GISSELA | EX11: OCHOA SOLEDISPA NESTOR IVAN | EY11: PARRAGA FRANCO SILVANA MARIELA | EZ11: PINARGOTE VASQUEZ NANCY FABIOLA | FA11: REYES VELEZ PEDRO ENRIQUE | FB11: SAN ANDRES HORMAZA DALLAS CECILIA | FC11: SORNOZA ZAMORA JUAN CARLOS | FD11: TOMALA PINTO JESUS JACINTO | FE11: VALLE JARAMILLO SILVIA ARACELY | FF11: VELÁSQUEZ BRAVO IRMA KATHERINE | FG11: VELEZ MENDOZA LAYSY VALERIA | FH11: VINUEZA TELLO SHIRLEY ELIZABETH | FI11: ZAMBRANO ALCIVAR NILDA ISABEL | FJ11: ZAMBRANO LOOR RITA MAYDA | FK11: ZAMBRANO VERA MONICA JANETH | FL11: VERA DELGADO BRYAN ADRIÁN | FM11: MORAN GONZALES DAVID RENATO | FN11: 0
A12: {=TRANSPOSE(_xlfn.UNIQUE(_xlfn._xlws.FILTER(MAE_ASIGNATURA[ID_NIVEL],MAE_ASIGNATURA[ID_CARRERA]=ASIGNACION!$C12,"No existe información")))} -> No existe información | S12: {=TRANSPOSE(_xlfn.UNIQUE(_xlfn._xlws.FILTER(MAE_ASIGNATURA[NOM_ASIG],(MAE_ASIGNATURA[ID_NIVEL]=ASIGNACION!$D12)*(MAE_ASIGNATURA[ID_CARRERA]=ASIGNACION!$C12),"No existe información")))} -> No existe información | BD12: {=TRANSPOSE(_xlfn.UNIQUE(_xlfn._xlws.FILTER(DET_ASIG[DETALLADO],(DET_ASIG[ID_CARRERA]=ASIGNACION!$C12)*(DET_ASIG[NIVEL]=ASIGNACION!$D12)*(DET_ASIG[ID_ASIG]=ASIGNACION!$G12),"No existe información")))} -> No existe información | BQ12: {=IFERROR( TRANSPOSE( _xlfn.UNIQUE( _xlfn._xlws.FILTER(MAESTRIA_DETALLADO[MAESTRIA], ISNUMBER(MATCH(MAESTRIA_DETALLADO[CAMPO_DETALLADO], BD12:BP12,0)) ) ) ),IF(BD12="ACTIVIDAD","DOCENCIA",""))} | EA12: {=IF( ASIGNACION!I12="SI", IFERROR( TRANSPOSE( _xlfn.UNIQUE( _xlfn._xlws.FILTER(EDU_DOCENTE[NOMBRE_DOCENTE], ISNUMBER(MATCH(EDU_DOCENTE[MAESTRIA], BQ12:DY12,0)) ) ) ), "" ), TRANSPOSE( _xlfn.UNIQUE(EDU_DOCENTE[NOMBRE_DOCENTE] ) ) )} -> ALCIVAR CEDEÑO BEATRIZ ISABEL | EB12: ALCIVAR VERA GEMA MICHELLE | EC12: ARAUZ CHAVEZ MARIO ROBERTO | ED12: BAILON LOURIDO WALTER ALBERTO | EE12: CALDERERO VILLAGOMEZ ERICK ANTONIO | EF12: CASTILLO GARCIA PAOLA GERMANIA | EG12: CEDEÑO CHOEZ PEDRO JAVIER | EH12: CEVALLOS HOPPE JUAN CARLOS | EI12: DELGADO CHAVEZ MARIA IRASEMA | EJ12: DUARTE VALENCIA CRISTHIAN DARIO | EK12: FORTTY BARBERAN DENNY ALEXANDER | EL12: GUTIERREZ ZAMBRANO CARMEN EBELINA | EM12: INTRIAGO MOLINA GEMA VALERIA | EN12: LINO VELEZ LEONEL LIVINGTON | EO12: LOOR ALCIVAR MARIA ILIANA | EP12: LOOR MIELES TANIA JACQUELINE | EQ12: LOOR SOLORZANO ROSA MARIA | ER12: LOPEZ DELGADO RONALD MAURICIO | ES12: MACIAS VALENCIA DAVID GABRIEL | ET12: MENDOZA ZAMORA WALTER MANUEL | EU12: MOLINA CEVALLOS MARIA LORENA | EV12: MURILLO DELGADO ISAAC GABRIEL | EW12: ANGULO MURILLO NAVIRA GISSELA | EX12: OCHOA SOLEDISPA NESTOR IVAN | EY12: PARRAGA FRANCO SILVANA MARIELA | EZ12: PINARGOTE VASQUEZ NANCY FABIOLA | FA12: REYES VELEZ PEDRO ENRIQUE | FB12: SAN ANDRES HORMAZA DALLAS CECILIA | FC12: SORNOZA ZAMORA JUAN CARLOS | FD12: TOMALA PINTO JESUS JACINTO | FE12: VALLE JARAMILLO SILVIA ARACELY | FF12: VELÁSQUEZ BRAVO IRMA KATHERINE | FG12: VELEZ MENDOZA LAYSY VALERIA | FH12: VINUEZA TELLO SHIRLEY ELIZABETH | FI12: ZAMBRANO ALCIVAR NILDA ISABEL | FJ12: ZAMBRANO LOOR RITA MAYDA | FK12: ZAMBRANO VERA MONICA JANETH | FL12: VERA DELGADO BRYAN ADRIÁN | FM12: MORAN GONZALES DAVID RENATO | FN12: 0
A13: {=TRANSPOSE(_xlfn.UNIQUE(_xlfn._xlws.FILTER(MAE_ASIGNATURA[ID_NIVEL],MAE_ASIGNATURA[ID_CARRERA]=ASIGNACION!$C13,"No existe información")))} -> No existe información | S13: {=TRANSPOSE(_xlfn.UNIQUE(_xlfn._xlws.FILTER(MAE_ASIGNATURA[NOM_ASIG],(MAE_ASIGNATURA[ID_NIVEL]=ASIGNACION!$D13)*(MAE_ASIGNATURA[ID_CARRERA]=ASIGNACION!$C13),"No existe información")))} -> No existe información | BD13: {=TRANSPOSE(_xlfn.UNIQUE(_xlfn._xlws.FILTER(DET_ASIG[DETALLADO],(DET_ASIG[ID_CARRERA]=ASIGNACION!$C13)*(DET_ASIG[NIVEL]=ASIGNACION!$D13)*(DET_ASIG[ID_ASIG]=ASIGNACION!$G13),"No existe información")))} -> No existe información | BQ13: {=IFERROR( TRANSPOSE( _xlfn.UNIQUE( _xlfn._xlws.FILTER(MAESTRIA_DETALLADO[MAESTRIA], ISNUMBER(MATCH(MAESTRIA_DETALLADO[CAMPO_DETALLADO], BD13:BP13,0)) ) ) ),IF(BD13="ACTIVIDAD","DOCENCIA",""))} | EA13: {=IF( ASIGNACION!I13="SI", IFERROR( TRANSPOSE( _xlfn.UNIQUE( _xlfn._xlws.FILTER(EDU_DOCENTE[NOMBRE_DOCENTE], ISNUMBER(MATCH(EDU_DOCENTE[MAESTRIA], BQ13:DY13,0)) ) ) ), "" ), TRANSPOSE( _xlfn.UNIQUE(EDU_DOCENTE[NOMBRE_DOCENTE] ) ) )} -> ALCIVAR CEDEÑO BEATRIZ ISABEL | EB13: ALCIVAR VERA GEMA MICHELLE | EC13: ARAUZ CHAVEZ MARIO ROBERTO | ED13: BAILON LOURIDO WALTER ALBERTO | EE13: CALDERERO VILLAGOMEZ ERICK ANTONIO | EF13: CASTILLO GARCIA PAOLA GERMANIA | EG13: CEDEÑO CHOEZ PEDRO JAVIER | EH13: CEVALLOS HOPPE JUAN CARLOS | EI13: DELGADO CHAVEZ MARIA IRASEMA | EJ13: DUARTE VALENCIA CRISTHIAN DARIO | EK13: FORTTY BARBERAN DENNY ALEXANDER | EL13: GUTIERREZ ZAMBRANO CARMEN EBELINA | EM13: INTRIAGO MOLINA GEMA VALERIA | EN13: LINO VELEZ LEONEL LIVINGTON | EO13: LOOR ALCIVAR MARIA ILIANA | EP13: LOOR MIELES TANIA JACQUELINE | EQ13: LOOR SOLORZANO ROSA MARIA | ER13: LOPEZ DELGADO RONALD MAURICIO | ES13: MACIAS VALENCIA DAVID GABRIEL | ET13: MENDOZA ZAMORA WALTER MANUEL | EU13: MOLINA CEVALLOS MARIA LORENA | EV13: MURILLO DELGADO ISAAC GABRIEL | EW13: ANGULO MURILLO NAVIRA GISSELA | EX13: OCHOA SOLEDISPA NESTOR IVAN | EY13: PARRAGA FRANCO SILVANA MARIELA | EZ13: PINARGOTE VASQUEZ NANCY FABIOLA | FA13: REYES VELEZ PEDRO ENRIQUE | FB13: SAN ANDRES HORMAZA DALLAS CECILIA | FC13: SORNOZA ZAMORA JUAN CARLOS | FD13: TOMALA PINTO JESUS JACINTO | FE13: VALLE JARAMILLO SILVIA ARACELY | FF13: VELÁSQUEZ BRAVO IRMA KATHERINE | FG13: VELEZ MENDOZA LAYSY VALERIA | FH13: VINUEZA TELLO SHIRLEY ELIZABETH | FI13: ZAMBRANO ALCIVAR NILDA ISABEL | FJ13: ZAMBRANO LOOR RITA MAYDA | FK13: ZAMBRANO VERA MONICA JANETH | FL13: VERA DELGADO BRYAN ADRIÁN | FM13: MORAN GONZALES DAVID RENATO | FN13: 0
A14: {=TRANSPOSE(_xlfn.UNIQUE(_xlfn._xlws.FILTER(MAE_ASIGNATURA[ID_NIVEL],MAE_ASIGNATURA[ID_CARRERA]=ASIGNACION!$C14,"No existe información")))} -> No existe información | S14: {=TRANSPOSE(_xlfn.UNIQUE(_xlfn._xlws.FILTER(MAE_ASIGNATURA[NOM_ASIG],(MAE_ASIGNATURA[ID_NIVEL]=ASIGNACION!$D14)*(MAE_ASIGNATURA[ID_CARRERA]=ASIGNACION!$C14),"No existe información")))} -> No existe información | BD14: {=TRANSPOSE(_xlfn.UNIQUE(_xlfn._xlws.FILTER(DET_ASIG[DETALLADO],(DET_ASIG[ID_CARRERA]=ASIGNACION!$C14)*(DET_ASIG[NIVEL]=ASIGNACION!$D14)*(DET_ASIG[ID_ASIG]=ASIGNACION!$G14),"No existe información")))} -> No existe información | BQ14: {=IFERROR( TRANSPOSE( _xlfn.UNIQUE( _xlfn._xlws.FILTER(MAESTRIA_DETALLADO[MAESTRIA], ISNUMBER(MATCH(MAESTRIA_DETALLADO[CAMPO_DETALLADO], BD14:BP14,0)) ) ) ),IF(BD14="ACTIVIDAD","DOCENCIA",""))} | EA14: {=IF( ASIGNACION!I14="SI", IFERROR( TRANSPOSE( _xlfn.UNIQUE( _xlfn._xlws.FILTER(EDU_DOCENTE[NOMBRE_DOCENTE], ISNUMBER(MATCH(EDU_DOCENTE[MAESTRIA], BQ14:DY14,0)) ) ) ), "" ), TRANSPOSE( _xlfn.UNIQUE(EDU_DOCENTE[NOMBRE_DOCENTE] ) ) )} -> ALCIVAR CEDEÑO BEATRIZ ISABEL | EB14: ALCIVAR VERA GEMA MICHELLE | EC14: ARAUZ CHAVEZ MARIO ROBERTO | ED14: BAILON LOURIDO WALTER ALBERTO | EE14: CALDERERO VILLAGOMEZ ERICK ANTONIO | EF14: CASTILLO GARCIA PAOLA GERMANIA | EG14: CEDEÑO CHOEZ PEDRO JAVIER | EH14: CEVALLOS HOPPE JUAN CARLOS | EI14: DELGADO CHAVEZ MARIA IRASEMA | EJ14: DUARTE VALENCIA CRISTHIAN DARIO | EK14: FORTTY BARBERAN DENNY ALEXANDER | EL14: GUTIERREZ ZAMBRANO CARMEN EBELINA | EM14: INTRIAGO MOLINA GEMA VALERIA | EN14: LINO VELEZ LEONEL LIVINGTON | EO14: LOOR ALCIVAR MARIA ILIANA | EP14: LOOR MIELES TANIA JACQUELINE | EQ14: LOOR SOLORZANO ROSA MARIA | ER14: LOPEZ DELGADO RONALD MAURICIO | ES14: MACIAS VALENCIA DAVID GABRIEL | ET14: MENDOZA ZAMORA WALTER MANUEL | EU14: MOLINA CEVALLOS MARIA LORENA | EV14: MURILLO DELGADO ISAAC GABRIEL | EW14: ANGULO MURILLO NAVIRA GISSELA | EX14: OCHOA SOLEDISPA NESTOR IVAN | EY14: PARRAGA FRANCO SILVANA MARIELA | EZ14: PINARGOTE VASQUEZ NANCY FABIOLA | FA14: REYES VELEZ PEDRO ENRIQUE | FB14: SAN ANDRES HORMAZA DALLAS CECILIA | FC14: SORNOZA ZAMORA JUAN CARLOS | FD14: TOMALA PINTO JESUS JACINTO | FE14: VALLE JARAMILLO SILVIA ARACELY | FF14: VELÁSQUEZ BRAVO IRMA KATHERINE | FG14: VELEZ MENDOZA LAYSY VALERIA | FH14: VINUEZA TELLO SHIRLEY ELIZABETH | FI14: ZAMBRANO ALCIVAR NILDA ISABEL | FJ14: ZAMBRANO LOOR RITA MAYDA | FK14: ZAMBRANO VERA MONICA JANETH | FL14: VERA DELGADO BRYAN ADRIÁN | FM14: MORAN GONZALES DAVID RENATO | FN14: 0
A15: {=TRANSPOSE(_xlfn.UNIQUE(_xlfn._xlws.FILTER(MAE_ASIGNATURA[ID_NIVEL],MAE_ASIGNATURA[ID_CARRERA]=ASIGNACION!$C15,"No existe información")))} -> No existe información | S15: {=TRANSPOSE(_xlfn.UNIQUE(_xlfn._xlws.FILTER(MAE_ASIGNATURA[NOM_ASIG],(MAE_ASIGNATURA[ID_NIVEL]=ASIGNACION!$D15)*(MAE_ASIGNATURA[ID_CARRERA]=ASIGNACION!$C15),"No existe información")))} -> No existe información | BD15: {=TRANSPOSE(_xlfn.UNIQUE(_xlfn._xlws.FILTER(DET_ASIG[DETALLADO],(DET_ASIG[ID_CARRERA]=ASIGNACION!$C15)*(DET_ASIG[NIVEL]=ASIGNACION!$D15)*(DET_ASIG[ID_ASIG]=ASIGNACION!$G15),"No existe información")))} -> No existe información | BQ15: {=IFERROR( TRANSPOSE( _xlfn.UNIQUE( _xlfn._xlws.FILTER(MAESTRIA_DETALLADO[MAESTRIA], ISNUMBER(MATCH(MAESTRIA_DETALLADO[CAMPO_DETALLADO], BD15:BP15,0)) ) ) ),IF(BD15="ACTIVIDAD","DOCENCIA",""))} | EA15: {=IF( ASIGNACION!I15="SI", IFERROR( TRANSPOSE( _xlfn.UNIQUE( _xlfn._xlws.FILTER(EDU_DOCENTE[NOMBRE_DOCENTE], ISNUMBER(MATCH(EDU_DOCENTE[MAESTRIA], BQ15:DY15,0)) ) ) ), "" ), TRANSPOSE( _xlfn.UNIQUE(EDU_DOCENTE[NOMBRE_DOCENTE] ) ) )} -> ALCIVAR CEDEÑO BEATRIZ ISABEL | EB15: ALCIVAR VERA GEMA MICHELLE | EC15: ARAUZ CHAVEZ MARIO ROBERTO | ED15: BAILON LOURIDO WALTER ALBERTO | EE15: CALDERERO VILLAGOMEZ ERICK ANTONIO | EF15: CASTILLO GARCIA PAOLA GERMANIA | EG15: CEDEÑO CHOEZ PEDRO JAVIER | EH15: CEVALLOS HOPPE JUAN CARLOS | EI15: DELGADO CHAVEZ MARIA IRASEMA | EJ15: DUARTE VALENCIA CRISTHIAN DARIO | EK15: FORTTY BARBERAN DENNY ALEXANDER | EL15: GUTIERREZ ZAMBRANO CARMEN EBELINA | EM15: INTRIAGO MOLINA GEMA VALERIA | EN15: LINO VELEZ LEONEL LIVINGTON | EO15: LOOR ALCIVAR MARIA ILIANA | EP15: LOOR MIELES TANIA JACQUELINE | EQ15: LOOR SOLORZANO ROSA MARIA | ER15: LOPEZ DELGADO RONALD MAURICIO | ES15: MACIAS VALENCIA DAVID GABRIEL | ET15: MENDOZA ZAMORA WALTER MANUEL | EU15: MOLINA CEVALLOS MARIA LORENA | EV15: MURILLO DELGADO ISAAC GABRIEL | EW15: ANGULO MURILLO NAVIRA GISSELA | EX15: OCHOA SOLEDISPA NESTOR IVAN | EY15: PARRAGA FRANCO SILVANA MARIELA | EZ15: PINARGOTE VASQUEZ NANCY FABIOLA | FA15: REYES VELEZ PEDRO ENRIQUE | FB15: SAN ANDRES HORMAZA DALLAS CECILIA | FC15: SORNOZA ZAMORA JUAN CARLOS | FD15: TOMALA PINTO JESUS JACINTO | FE15: VALLE JARAMILLO SILVIA ARACELY | FF15: VELÁSQUEZ BRAVO IRMA KATHERINE | FG15: VELEZ MENDOZA LAYSY VALERIA | FH15: VINUEZA TELLO SHIRLEY ELIZABETH | FI15: ZAMBRANO ALCIVAR NILDA ISABEL | FJ15: ZAMBRANO LOOR RITA MAYDA | FK15: ZAMBRANO VERA MONICA JANETH | FL15: VERA DELGADO BRYAN ADRIÁN | FM15: MORAN GONZALES DAVID RENATO | FN15: 0
A16: {=TRANSPOSE(_xlfn.UNIQUE(_xlfn._xlws.FILTER(MAE_ASIGNATURA[ID_NIVEL],MAE_ASIGNATURA[ID_CARRERA]=ASIGNACION!$C16,"No existe información")))} -> No existe información | S16: {=TRANSPOSE(_xlfn.UNIQUE(_xlfn._xlws.FILTER(MAE_ASIGNATURA[NOM_ASIG],(MAE_ASIGNATURA[ID_NIVEL]=ASIGNACION!$D16)*(MAE_ASIGNATURA[ID_CARRERA]=ASIGNACION!$C16),"No existe información")))} -> No existe información | BD16: {=TRANSPOSE(_xlfn.UNIQUE(_xlfn._xlws.FILTER(DET_ASIG[DETALLADO],(DET_ASIG[ID_CARRERA]=ASIGNACION!$C16)*(DET_ASIG[NIVEL]=ASIGNACION!$D16)*(DET_ASIG[ID_ASIG]=ASIGNACION!$G16),"No existe información")))} -> No existe información | BQ16: {=IFERROR( TRANSPOSE( _xlfn.UNIQUE( _xlfn._xlws.FILTER(MAESTRIA_DETALLADO[MAESTRIA], ISNUMBER(MATCH(MAESTRIA_DETALLADO[CAMPO_DETALLADO], BD16:BP16,0)) ) ) ),IF(BD16="ACTIVIDAD","DOCENCIA",""))} | EA16: {=IF( ASIGNACION!I16="SI", IFERROR( TRANSPOSE( _xlfn.UNIQUE( _xlfn._xlws.FILTER(EDU_DOCENTE[NOMBRE_DOCENTE], ISNUMBER(MATCH(EDU_DOCENTE[MAESTRIA], BQ16:DY16,0)) ) ) ), "" ), TRANSPOSE( _xlfn.UNIQUE(EDU_DOCENTE[NOMBRE_DOCENTE] ) ) )} -> ALCIVAR CEDEÑO BEATRIZ ISABEL | EB16: ALCIVAR VERA GEMA MICHELLE | EC16: ARAUZ CHAVEZ MARIO ROBERTO | ED16: BAILON LOURIDO WALTER ALBERTO | EE16: CALDERERO VILLAGOMEZ ERICK ANTONIO | EF16: CASTILLO GARCIA PAOLA GERMANIA | EG16: CEDEÑO CHOEZ PEDRO JAVIER | EH16: CEVALLOS HOPPE JUAN CARLOS | EI16: DELGADO CHAVEZ MARIA IRASEMA | EJ16: DUARTE VALENCIA CRISTHIAN DARIO | EK16: FORTTY BARBERAN DENNY ALEXANDER | EL16: GUTIERREZ ZAMBRANO CARMEN EBELINA | EM16: INTRIAGO MOLINA GEMA VALERIA | EN16: LINO VELEZ LEONEL LIVINGTON | EO16: LOOR ALCIVAR MARIA ILIANA | EP16: LOOR MIELES TANIA JACQUELINE | EQ16: LOOR SOLORZANO ROSA MARIA | ER16: LOPEZ DELGADO RONALD MAURICIO | ES16: MACIAS VALENCIA DAVID GABRIEL | ET16: MENDOZA ZAMORA WALTER MANUEL | EU16: MOLINA CEVALLOS MARIA LORENA | EV16: MURILLO DELGADO ISAAC GABRIEL | EW16: ANGULO MURILLO NAVIRA GISSELA | EX16: OCHOA SOLEDISPA NESTOR IVAN | EY16: PARRAGA FRANCO SILVANA MARIELA | EZ16: PINARGOTE VASQUEZ NANCY FABIOLA | FA16: REYES VELEZ PEDRO ENRIQUE | FB16: SAN ANDRES HORMAZA DALLAS CECILIA | FC16: SORNOZA ZAMORA JUAN CARLOS | FD16: TOMALA PINTO JESUS JACINTO | FE16: VALLE JARAMILLO SILVIA ARACELY | FF16: VELÁSQUEZ BRAVO IRMA KATHERINE | FG16: VELEZ MENDOZA LAYSY VALERIA | FH16: VINUEZA TELLO SHIRLEY ELIZABETH | FI16: ZAMBRANO ALCIVAR NILDA ISABEL | FJ16: ZAMBRANO LOOR RITA MAYDA | FK16: ZAMBRANO VERA MONICA JANETH | FL16: VERA DELGADO BRYAN ADRIÁN | FM16: MORAN GONZALES DAVID RENATO | FN16: 0
A17: {=TRANSPOSE(_xlfn.UNIQUE(_xlfn._xlws.FILTER(MAE_ASIGNATURA[ID_NIVEL],MAE_ASIGNATURA[ID_CARRERA]=ASIGNACION!$C17,"No existe información")))} -> No existe información | S17: {=TRANSPOSE(_xlfn.UNIQUE(_xlfn._xlws.FILTER(MAE_ASIGNATURA[NOM_ASIG],(MAE_ASIGNATURA[ID_NIVEL]=ASIGNACION!$D17)*(MAE_ASIGNATURA[ID_CARRERA]=ASIGNACION!$C17),"No existe información")))} -> No existe información | BD17: {=TRANSPOSE(_xlfn.UNIQUE(_xlfn._xlws.FILTER(DET_ASIG[DETALLADO],(DET_ASIG[ID_CARRERA]=ASIGNACION!$C17)*(DET_ASIG[NIVEL]=ASIGNACION!$D17)*(DET_ASIG[ID_ASIG]=ASIGNACION!$G17),"No existe información")))} -> No existe información | BQ17: {=IFERROR( TRANSPOSE( _xlfn.UNIQUE( _xlfn._xlws.FILTER(MAESTRIA_DETALLADO[MAESTRIA], ISNUMBER(MATCH(MAESTRIA_DETALLADO[CAMPO_DETALLADO], BD17:BP17,0)) ) ) ),IF(BD17="ACTIVIDAD","DOCENCIA",""))} | EA17: {=IF( ASIGNACION!I17="SI", IFERROR( TRANSPOSE( _xlfn.UNIQUE( _xlfn._xlws.FILTER(EDU_DOCENTE[NOMBRE_DOCENTE], ISNUMBER(MATCH(EDU_DOCENTE[MAESTRIA], BQ17:DY17,0)) ) ) ), "" ), TRANSPOSE( _xlfn.UNIQUE(EDU_DOCENTE[NOMBRE_DOCENTE] ) ) )} -> ALCIVAR CEDEÑO BEATRIZ ISABEL | EB17: ALCIVAR VERA GEMA MICHELLE | EC17: ARAUZ CHAVEZ MARIO ROBERTO | ED17: BAILON LOURIDO WALTER ALBERTO | EE17: CALDERERO VILLAGOMEZ ERICK ANTONIO | EF17: CASTILLO GARCIA PAOLA GERMANIA | EG17: CEDEÑO CHOEZ PEDRO JAVIER | EH17: CEVALLOS HOPPE JUAN CARLOS | EI17: DELGADO CHAVEZ MARIA IRASEMA | EJ17: DUARTE VALENCIA CRISTHIAN DARIO | EK17: FORTTY BARBERAN DENNY ALEXANDER | EL17: GUTIERREZ ZAMBRANO CARMEN EBELINA | EM17: INTRIAGO MOLINA GEMA VALERIA | EN17: LINO VELEZ LEONEL LIVINGTON | EO17: LOOR ALCIVAR MARIA ILIANA | EP17: LOOR MIELES TANIA JACQUELINE | EQ17: LOOR SOLORZANO ROSA MARIA | ER17: LOPEZ DELGADO RONALD MAURICIO | ES17: MACIAS VALENCIA DAVID GABRIEL | ET17: MENDOZA ZAMORA WALTER MANUEL | EU17: MOLINA CEVALLOS MARIA LORENA | EV17: MURILLO DELGADO ISAAC GABRIEL | EW17: ANGULO MURILLO NAVIRA GISSELA | EX17: OCHOA SOLEDISPA NESTOR IVAN | EY17: PARRAGA FRANCO SILVANA MARIELA | EZ17: PINARGOTE VASQUEZ NANCY FABIOLA | FA17: REYES VELEZ PEDRO ENRIQUE | FB17: SAN ANDRES HORMAZA DALLAS CECILIA | FC17: SORNOZA ZAMORA JUAN CARLOS | FD17: TOMALA PINTO JESUS JACINTO | FE17: VALLE JARAMILLO SILVIA ARACELY | FF17: VELÁSQUEZ BRAVO IRMA KATHERINE | FG17: VELEZ MENDOZA LAYSY VALERIA | FH17: VINUEZA TELLO SHIRLEY ELIZABETH | FI17: ZAMBRANO ALCIVAR NILDA ISABEL | FJ17: ZAMBRANO LOOR RITA MAYDA | FK17: ZAMBRANO VERA MONICA JANETH | FL17: VERA DELGADO BRYAN ADRIÁN | FM17: MORAN GONZALES DAVID RENATO | FN17: 0
A18: {=TRANSPOSE(_xlfn.UNIQUE(_xlfn._xlws.FILTER(MAE_ASIGNATURA[ID_NIVEL],MAE_ASIGNATURA[ID_CARRERA]=ASIGNACION!$C18,"No existe información")))} -> No existe información | S18: {=TRANSPOSE(_xlfn.UNIQUE(_xlfn._xlws.FILTER(MAE_ASIGNATURA[NOM_ASIG],(MAE_ASIGNATURA[ID_NIVEL]=ASIGNACION!$D18)*(MAE_ASIGNATURA[ID_CARRERA]=ASIGNACION!$C18),"No existe información")))} -> No existe información | BD18: {=TRANSPOSE(_xlfn.UNIQUE(_xlfn._xlws.FILTER(DET_ASIG[DETALLADO],(DET_ASIG[ID_CARRERA]=ASIGNACION!$C18)*(DET_ASIG[NIVEL]=ASIGNACION!$D18)*(DET_ASIG[ID_ASIG]=ASIGNACION!$G18),"No existe información")))} -> No existe información | BQ18: {=IFERROR( TRANSPOSE( _xlfn.UNIQUE( _xlfn._xlws.FILTER(MAESTRIA_DETALLADO[MAESTRIA], ISNUMBER(MATCH(MAESTRIA_DETALLADO[CAMPO_DETALLADO], BD18:BP18,0)) ) ) ),IF(BD18="ACTIVIDAD","DOCENCIA",""))} | EA18: {=IF( ASIGNACION!I18="SI", IFERROR( TRANSPOSE( _xlfn.UNIQUE( _xlfn._xlws.FILTER(EDU_DOCENTE[NOMBRE_DOCENTE], ISNUMBER(MATCH(EDU_DOCENTE[MAESTRIA], BQ18:DY18,0)) ) ) ), "" ), TRANSPOSE( _xlfn.UNIQUE(EDU_DOCENTE[NOMBRE_DOCENTE] ) ) )} -> ALCIVAR CEDEÑO BEATRIZ ISABEL | EB18: ALCIVAR VERA GEMA MICHELLE | EC18: ARAUZ CHAVEZ MARIO ROBERTO | ED18: BAILON LOURIDO WALTER ALBERTO | EE18: CALDERERO VILLAGOMEZ ERICK ANTONIO | EF18: CASTILLO GARCIA PAOLA GERMANIA | EG18: CEDEÑO CHOEZ PEDRO JAVIER | EH18: CEVALLOS HOPPE JUAN CARLOS | EI18: DELGADO CHAVEZ MARIA IRASEMA | EJ18: DUARTE VALENCIA CRISTHIAN DARIO | EK18: FORTTY BARBERAN DENNY ALEXANDER | EL18: GUTIERREZ ZAMBRANO CARMEN EBELINA | EM18: INTRIAGO MOLINA GEMA VALERIA | EN18: LINO VELEZ LEONEL LIVINGTON | EO18: LOOR ALCIVAR MARIA ILIANA | EP18: LOOR MIELES TANIA JACQUELINE | EQ18: LOOR SOLORZANO ROSA MARIA | ER18: LOPEZ DELGADO RONALD MAURICIO | ES18: MACIAS VALENCIA DAVID GABRIEL | ET18: MENDOZA ZAMORA WALTER MANUEL | EU18: MOLINA CEVALLOS MARIA LORENA | EV18: MURILLO DELGADO ISAAC GABRIEL | EW18: ANGULO MURILLO NAVIRA GISSELA | EX18: OCHOA SOLEDISPA NESTOR IVAN | EY18: PARRAGA FRANCO SILVANA MARIELA | EZ18: PINARGOTE VASQUEZ NANCY FABIOLA | FA18: REYES VELEZ PEDRO ENRIQUE | FB18: SAN ANDRES HORMAZA DALLAS CECILIA | FC18: SORNOZA ZAMORA JUAN CARLOS | FD18: TOMALA PINTO JESUS JACINTO | FE18: VALLE JARAMILLO SILVIA ARACELY | FF18: VELÁSQUEZ BRAVO IRMA KATHERINE | FG18: VELEZ MENDOZA LAYSY VALERIA | FH18: VINUEZA TELLO SHIRLEY ELIZABETH | FI18: ZAMBRANO ALCIVAR NILDA ISABEL | FJ18: ZAMBRANO LOOR RITA MAYDA | FK18: ZAMBRANO VERA MONICA JANETH | FL18: VERA DELGADO BRYAN ADRIÁN | FM18: MORAN GONZALES DAVID RENATO | FN18: 0
A19: {=TRANSPOSE(_xlfn.UNIQUE(_xlfn._xlws.FILTER(MAE_ASIGNATURA[ID_NIVEL],MAE_ASIGNATURA[ID_CARRERA]=ASIGNACION!$C19,"No existe información")))} -> No existe información | S19: {=TRANSPOSE(_xlfn.UNIQUE(_xlfn._xlws.FILTER(MAE_ASIGNATURA[NOM_ASIG],(MAE_ASIGNATURA[ID_NIVEL]=ASIGNACION!$D19)*(MAE_ASIGNATURA[ID_CARRERA]=ASIGNACION!$C19),"No existe información")))} -> No existe información | BD19: {=TRANSPOSE(_xlfn.UNIQUE(_xlfn._xlws.FILTER(DET_ASIG[DETALLADO],(DET_ASIG[ID_CARRERA]=ASIGNACION!$C19)*(DET_ASIG[NIVEL]=ASIGNACION!$D19)*(DET_ASIG[ID_ASIG]=ASIGNACION!$G19),"No existe información")))} -> No existe información | BQ19: {=IFERROR( TRANSPOSE( _xlfn.UNIQUE( _xlfn._xlws.FILTER(MAESTRIA_DETALLADO[MAESTRIA], ISNUMBER(MATCH(MAESTRIA_DETALLADO[CAMPO_DETALLADO], BD19:BP19,0)) ) ) ),IF(BD19="ACTIVIDAD","DOCENCIA",""))} | EA19: {=IF( ASIGNACION!I19="SI", IFERROR( TRANSPOSE( _xlfn.UNIQUE( _xlfn._xlws.FILTER(EDU_DOCENTE[NOMBRE_DOCENTE], ISNUMBER(MATCH(EDU_DOCENTE[MAESTRIA], BQ19:DY19,0)) ) ) ), "" ), TRANSPOSE( _xlfn.UNIQUE(EDU_DOCENTE[NOMBRE_DOCENTE] ) ) )} -> ALCIVAR CEDEÑO BEATRIZ ISABEL | EB19: ALCIVAR VERA GEMA MICHELLE | EC19: ARAUZ CHAVEZ MARIO ROBERTO | ED19: BAILON LOURIDO WALTER ALBERTO | EE19: CALDERERO VILLAGOMEZ ERICK ANTONIO | EF19: CASTILLO GARCIA PAOLA GERMANIA | EG19: CEDEÑO CHOEZ PEDRO JAVIER | EH19: CEVALLOS HOPPE JUAN CARLOS | EI19: DELGADO CHAVEZ MARIA IRASEMA | EJ19: DUARTE VALENCIA CRISTHIAN DARIO | EK19: FORTTY BARBERAN DENNY ALEXANDER | EL19: GUTIERREZ ZAMBRANO CARMEN EBELINA | EM19: INTRIAGO MOLINA GEMA VALERIA | EN19: LINO VELEZ LEONEL LIVINGTON | EO19: LOOR ALCIVAR MARIA ILIANA | EP19: LOOR MIELES TANIA JACQUELINE | EQ19: LOOR SOLORZANO ROSA MARIA | ER19: LOPEZ DELGADO RONALD MAURICIO | ES19: MACIAS VALENCIA DAVID GABRIEL | ET19: MENDOZA ZAMORA WALTER MANUEL | EU19: MOLINA CEVALLOS MARIA LORENA | EV19: MURILLO DELGADO ISAAC GABRIEL | EW19: ANGULO MURILLO NAVIRA GISSELA | EX19: OCHOA SOLEDISPA NESTOR IVAN | EY19: PARRAGA FRANCO SILVANA MARIELA | EZ19: PINARGOTE VASQUEZ NANCY FABIOLA | FA19: REYES VELEZ PEDRO ENRIQUE | FB19: SAN ANDRES HORMAZA DALLAS CECILIA | FC19: SORNOZA ZAMORA JUAN CARLOS | FD19: TOMALA PINTO JESUS JACINTO | FE19: VALLE JARAMILLO SILVIA ARACELY | FF19: VELÁSQUEZ BRAVO IRMA KATHERINE | FG19: VELEZ MENDOZA LAYSY VALERIA | FH19: VINUEZA TELLO SHIRLEY ELIZABETH | FI19: ZAMBRANO ALCIVAR NILDA ISABEL | FJ19: ZAMBRANO LOOR RITA MAYDA | FK19: ZAMBRANO VERA MONICA JANETH | FL19: VERA DELGADO BRYAN ADRIÁN | FM19: MORAN GONZALES DAVID RENATO | FN19: 0
A20: {=TRANSPOSE(_xlfn.UNIQUE(_xlfn._xlws.FILTER(MAE_ASIGNATURA[ID_NIVEL],MAE_ASIGNATURA[ID_CARRERA]=ASIGNACION!$C20,"No existe información")))} -> No existe información | S20: {=TRANSPOSE(_xlfn.UNIQUE(_xlfn._xlws.FILTER(MAE_ASIGNATURA[NOM_ASIG],(MAE_ASIGNATURA[ID_NIVEL]=ASIGNACION!$D20)*(MAE_ASIGNATURA[ID_CARRERA]=ASIGNACION!$C20),"No existe información")))} -> No existe información | BD20: {=TRANSPOSE(_xlfn.UNIQUE(_xlfn._xlws.FILTER(DET_ASIG[DETALLADO],(DET_ASIG[ID_CARRERA]=ASIGNACION!$C20)*(DET_ASIG[NIVEL]=ASIGNACION!$D20)*(DET_ASIG[ID_ASIG]=ASIGNACION!$G20),"No existe información")))} -> No existe información | BQ20: {=IFERROR( TRANSPOSE( _xlfn.UNIQUE( _xlfn._xlws.FILTER(MAESTRIA_DETALLADO[MAESTRIA], ISNUMBER(MATCH(MAESTRIA_DETALLADO[CAMPO_DETALLADO], BD20:BP20,0)) ) ) ),IF(BD20="ACTIVIDAD","DOCENCIA",""))} | EA20: {=IF( ASIGNACION!I20="SI", IFERROR( TRANSPOSE( _xlfn.UNIQUE( _xlfn._xlws.FILTER(EDU_DOCENTE[NOMBRE_DOCENTE], ISNUMBER(MATCH(EDU_DOCENTE[MAESTRIA], BQ20:DY20,0)) ) ) ), "" ), TRANSPOSE( _xlfn.UNIQUE(EDU_DOCENTE[NOMBRE_DOCENTE] ) ) )} -> ALCIVAR CEDEÑO BEATRIZ ISABEL | EB20: ALCIVAR VERA GEMA MICHELLE | EC20: ARAUZ CHAVEZ MARIO ROBERTO | ED20: BAILON LOURIDO WALTER ALBERTO | EE20: CALDERERO VILLAGOMEZ ERICK ANTONIO | EF20: CASTILLO GARCIA PAOLA GERMANIA | EG20: CEDEÑO CHOEZ PEDRO JAVIER | EH20: CEVALLOS HOPPE JUAN CARLOS | EI20: DELGADO CHAVEZ MARIA IRASEMA | EJ20: DUARTE VALENCIA CRISTHIAN DARIO | EK20: FORTTY BARBERAN DENNY ALEXANDER | EL20: GUTIERREZ ZAMBRANO CARMEN EBELINA | EM20: INTRIAGO MOLINA GEMA VALERIA | EN20: LINO VELEZ LEONEL LIVINGTON | EO20: LOOR ALCIVAR MARIA ILIANA | EP20: LOOR MIELES TANIA JACQUELINE | EQ20: LOOR SOLORZANO ROSA MARIA | ER20: LOPEZ DELGADO RONALD MAURICIO | ES20: MACIAS VALENCIA DAVID GABRIEL | ET20: MENDOZA ZAMORA WALTER MANUEL | EU20: MOLINA CEVALLOS MARIA LORENA | EV20: MURILLO DELGADO ISAAC GABRIEL | EW20: ANGULO MURILLO NAVIRA GISSELA | EX20: OCHOA SOLEDISPA NESTOR IVAN | EY20: PARRAGA FRANCO SILVANA MARIELA | EZ20: PINARGOTE VASQUEZ NANCY FABIOLA | FA20: REYES VELEZ PEDRO ENRIQUE | FB20: SAN ANDRES HORMAZA DALLAS CECILIA | FC20: SORNOZA ZAMORA JUAN CARLOS | FD20: TOMALA PINTO JESUS JACINTO | FE20: VALLE JARAMILLO SILVIA ARACELY | FF20: VELÁSQUEZ BRAVO IRMA KATHERINE | FG20: VELEZ MENDOZA LAYSY VALERIA | FH20: VINUEZA TELLO SHIRLEY ELIZABETH | FI20: ZAMBRANO ALCIVAR NILDA ISABEL | FJ20: ZAMBRANO LOOR RITA MAYDA | FK20: ZAMBRANO VERA MONICA JANETH | FL20: VERA DELGADO BRYAN ADRIÁN | FM20: MORAN GONZALES DAVID RENATO | FN20: 0
A21: {=TRANSPOSE(_xlfn.UNIQUE(_xlfn._xlws.FILTER(MAE_ASIGNATURA[ID_NIVEL],MAE_ASIGNATURA[ID_CARRERA]=ASIGNACION!$C21,"No existe información")))} -> No existe información | S21: {=TRANSPOSE(_xlfn.UNIQUE(_xlfn._xlws.FILTER(MAE_ASIGNATURA[NOM_ASIG],(MAE_ASIGNATURA[ID_NIVEL]=ASIGNACION!$D21)*(MAE_ASIGNATURA[ID_CARRERA]=ASIGNACION!$C21),"No existe información")))} -> No existe información | BD21: {=TRANSPOSE(_xlfn.UNIQUE(_xlfn._xlws.FILTER(DET_ASIG[DETALLADO],(DET_ASIG[ID_CARRERA]=ASIGNACION!$C21)*(DET_ASIG[NIVEL]=ASIGNACION!$D21)*(DET_ASIG[ID_ASIG]=ASIGNACION!$G21),"No existe información")))} -> No existe información | BQ21: {=IFERROR( TRANSPOSE( _xlfn.UNIQUE( _xlfn._xlws.FILTER(MAESTRIA_DETALLADO[MAESTRIA], ISNUMBER(MATCH(MAESTRIA_DETALLADO[CAMPO_DETALLADO], BD21:BP21,0)) ) ) ),IF(BD21="ACTIVIDAD","DOCENCIA",""))} | EA21: {=IF( ASIGNACION!I21="SI", IFERROR( TRANSPOSE( _xlfn.UNIQUE( _xlfn._xlws.FILTER(EDU_DOCENTE[NOMBRE_DOCENTE], ISNUMBER(MATCH(EDU_DOCENTE[MAESTRIA], BQ21:DY21,0)) ) ) ), "" ), TRANSPOSE( _xlfn.UNIQUE(EDU_DOCENTE[NOMBRE_DOCENTE] ) ) )} -> ALCIVAR CEDEÑO BEATRIZ ISABEL | EB21: ALCIVAR VERA GEMA MICHELLE | EC21: ARAUZ CHAVEZ MARIO ROBERTO | ED21: BAILON LOURIDO WALTER ALBERTO | EE21: CALDERERO VILLAGOMEZ ERICK ANTONIO | EF21: CASTILLO GARCIA PAOLA GERMANIA | EG21: CEDEÑO CHOEZ PEDRO JAVIER | EH21: CEVALLOS HOPPE JUAN CARLOS | EI21: DELGADO CHAVEZ MARIA IRASEMA | EJ21: DUARTE VALENCIA CRISTHIAN DARIO | EK21: FORTTY BARBERAN DENNY ALEXANDER | EL21: GUTIERREZ ZAMBRANO CARMEN EBELINA | EM21: INTRIAGO MOLINA GEMA VALERIA | EN21: LINO VELEZ LEONEL LIVINGTON | EO21: LOOR ALCIVAR MARIA ILIANA | EP21: LOOR MIELES TANIA JACQUELINE | EQ21: LOOR SOLORZANO ROSA MARIA | ER21: LOPEZ DELGADO RONALD MAURICIO | ES21: MACIAS VALENCIA DAVID GABRIEL | ET21: MENDOZA ZAMORA WALTER MANUEL | EU21: MOLINA CEVALLOS MARIA LORENA | EV21: MURILLO DELGADO ISAAC GABRIEL | EW21: ANGULO MURILLO NAVIRA GISSELA | EX21: OCHOA SOLEDISPA NESTOR IVAN | EY21: PARRAGA FRANCO SILVANA MARIELA | EZ21: PINARGOTE VASQUEZ NANCY FABIOLA | FA21: REYES VELEZ PEDRO ENRIQUE | FB21: SAN ANDRES HORMAZA DALLAS CECILIA | FC21: SORNOZA ZAMORA JUAN CARLOS | FD21: TOMALA PINTO JESUS JACINTO | FE21: VALLE JARAMILLO SILVIA ARACELY | FF21: VELÁSQUEZ BRAVO IRMA KATHERINE | FG21: VELEZ MENDOZA LAYSY VALERIA | FH21: VINUEZA TELLO SHIRLEY ELIZABETH | FI21: ZAMBRANO ALCIVAR NILDA ISABEL | FJ21: ZAMBRANO LOOR RITA MAYDA | FK21: ZAMBRANO VERA MONICA JANETH | FL21: VERA DELGADO BRYAN ADRIÁN | FM21: MORAN GONZALES DAVID RENATO | FN21: 0
A22: {=TRANSPOSE(_xlfn.UNIQUE(_xlfn._xlws.FILTER(MAE_ASIGNATURA[ID_NIVEL],MAE_ASIGNATURA[ID_CARRERA]=ASIGNACION!$C22,"No existe información")))} -> No existe información | S22: {=TRANSPOSE(_xlfn.UNIQUE(_xlfn._xlws.FILTER(MAE_ASIGNATURA[NOM_ASIG],(MAE_ASIGNATURA[ID_NIVEL]=ASIGNACION!$D22)*(MAE_ASIGNATURA[ID_CARRERA]=ASIGNACION!$C22),"No existe información")))} -> No existe información | BD22: {=TRANSPOSE(_xlfn.UNIQUE(_xlfn._xlws.FILTER(DET_ASIG[DETALLADO],(DET_ASIG[ID_CARRERA]=ASIGNACION!$C22)*(DET_ASIG[NIVEL]=ASIGNACION!$D22)*(DET_ASIG[ID_ASIG]=ASIGNACION!$G22),"No existe información")))} -> No existe información | BQ22: {=IFERROR( TRANSPOSE( _xlfn.UNIQUE( _xlfn._xlws.FILTER(MAESTRIA_DETALLADO[MAESTRIA], ISNUMBER(MATCH(MAESTRIA_DETALLADO[CAMPO_DETALLADO], BD22:BP22,0)) ) ) ),IF(BD22="ACTIVIDAD","DOCENCIA",""))} | EA22: {=IF( ASIGNACION!I22="SI", IFERROR( TRANSPOSE( _xlfn.UNIQUE( _xlfn._xlws.FILTER(EDU_DOCENTE[NOMBRE_DOCENTE], ISNUMBER(MATCH(EDU_DOCENTE[MAESTRIA], BQ22:DY22,0)) ) ) ), "" ), TRANSPOSE( _xlfn.UNIQUE(EDU_DOCENTE[NOMBRE_DOCENTE] ) ) )} -> ALCIVAR CEDEÑO BEATRIZ ISABEL | EB22: ALCIVAR VERA GEMA MICHELLE | EC22: ARAUZ CHAVEZ MARIO ROBERTO | ED22: BAILON LOURIDO WALTER ALBERTO | EE22: CALDERERO VILLAGOMEZ ERICK ANTONIO | EF22: CASTILLO GARCIA PAOLA GERMANIA | EG22: CEDEÑO CHOEZ PEDRO JAVIER | EH22: CEVALLOS HOPPE JUAN CARLOS | EI22: DELGADO CHAVEZ MARIA IRASEMA | EJ22: DUARTE VALENCIA CRISTHIAN DARIO | EK22: FORTTY BARBERAN DENNY ALEXANDER | EL22: GUTIERREZ ZAMBRANO CARMEN EBELINA | EM22: INTRIAGO MOLINA GEMA VALERIA | EN22: LINO VELEZ LEONEL LIVINGTON | EO22: LOOR ALCIVAR MARIA ILIANA | EP22: LOOR MIELES TANIA JACQUELINE | EQ22: LOOR SOLORZANO ROSA MARIA | ER22: LOPEZ DELGADO RONALD MAURICIO | ES22: MACIAS VALENCIA DAVID GABRIEL | ET22: MENDOZA ZAMORA WALTER MANUEL | EU22: MOLINA CEVALLOS MARIA LORENA | EV22: MURILLO DELGADO ISAAC GABRIEL | EW22: ANGULO MURILLO NAVIRA GISSELA | EX22: OCHOA SOLEDISPA NESTOR IVAN | EY22: PARRAGA FRANCO SILVANA MARIELA | EZ22: PINARGOTE VASQUEZ NANCY FABIOLA | FA22: REYES VELEZ PEDRO ENRIQUE | FB22: SAN ANDRES HORMAZA DALLAS CECILIA | FC22: SORNOZA ZAMORA JUAN CARLOS | FD22: TOMALA PINTO JESUS JACINTO | FE22: VALLE JARAMILLO SILVIA ARACELY | FF22: VELÁSQUEZ BRAVO IRMA KATHERINE | FG22: VELEZ MENDOZA LAYSY VALERIA | FH22: VINUEZA TELLO SHIRLEY ELIZABETH | FI22: ZAMBRANO ALCIVAR NILDA ISABEL | FJ22: ZAMBRANO LOOR RITA MAYDA | FK22: ZAMBRANO VERA MONICA JANETH | FL22: VERA DELGADO BRYAN ADRIÁN | FM22: MORAN GONZALES DAVID RENATO | FN22: 0
A23: {=TRANSPOSE(_xlfn.UNIQUE(_xlfn._xlws.FILTER(MAE_ASIGNATURA[ID_NIVEL],MAE_ASIGNATURA[ID_CARRERA]=ASIGNACION!$C23,"No existe información")))} -> No existe información | S23: {=TRANSPOSE(_xlfn.UNIQUE(_xlfn._xlws.FILTER(MAE_ASIGNATURA[NOM_ASIG],(MAE_ASIGNATURA[ID_NIVEL]=ASIGNACION!$D23)*(MAE_ASIGNATURA[ID_CARRERA]=ASIGNACION!$C23),"No existe información")))} -> No existe información | BD23: {=TRANSPOSE(_xlfn.UNIQUE(_xlfn._xlws.FILTER(DET_ASIG[DETALLADO],(DET_ASIG[ID_CARRERA]=ASIGNACION!$C23)*(DET_ASIG[NIVEL]=ASIGNACION!$D23)*(DET_ASIG[ID_ASIG]=ASIGNACION!$G23),"No existe información")))} -> No existe información | BQ23: {=IFERROR( TRANSPOSE( _xlfn.UNIQUE( _xlfn._xlws.FILTER(MAESTRIA_DETALLADO[MAESTRIA], ISNUMBER(MATCH(MAESTRIA_DETALLADO[CAMPO_DETALLADO], BD23:BP23,0)) ) ) ),IF(BD23="ACTIVIDAD","DOCENCIA",""))} | EA23: {=IF( ASIGNACION!I23="SI", IFERROR( TRANSPOSE( _xlfn.UNIQUE( _xlfn._xlws.FILTER(EDU_DOCENTE[NOMBRE_DOCENTE], ISNUMBER(MATCH(EDU_DOCENTE[MAESTRIA], BQ23:DY23,0)) ) ) ), "" ), TRANSPOSE( _xlfn.UNIQUE(EDU_DOCENTE[NOMBRE_DOCENTE] ) ) )} -> ALCIVAR CEDEÑO BEATRIZ ISABEL | EB23: ALCIVAR VERA GEMA MICHELLE | EC23: ARAUZ CHAVEZ MARIO ROBERTO | ED23: BAILON LOURIDO WALTER ALBERTO | EE23: CALDERERO VILLAGOMEZ ERICK ANTONIO | EF23: CASTILLO GARCIA PAOLA GERMANIA | EG23: CEDEÑO CHOEZ PEDRO JAVIER | EH23: CEVALLOS HOPPE JUAN CARLOS | EI23: DELGADO CHAVEZ MARIA IRASEMA | EJ23: DUARTE VALENCIA CRISTHIAN DARIO | EK23: FORTTY BARBERAN DENNY ALEXANDER | EL23: GUTIERREZ ZAMBRANO CARMEN EBELINA | EM23: INTRIAGO MOLINA GEMA VALERIA | EN23: LINO VELEZ LEONEL LIVINGTON | EO23: LOOR ALCIVAR MARIA ILIANA | EP23: LOOR MIELES TANIA JACQUELINE | EQ23: LOOR SOLORZANO ROSA MARIA | ER23: LOPEZ DELGADO RONALD MAURICIO | ES23: MACIAS VALENCIA DAVID GABRIEL | ET23: MENDOZA ZAMORA WALTER MANUEL | EU23: MOLINA CEVALLOS MARIA LORENA | EV23: MURILLO DELGADO ISAAC GABRIEL | EW23: ANGULO MURILLO NAVIRA GISSELA | EX23: OCHOA SOLEDISPA NESTOR IVAN | EY23: PARRAGA FRANCO SILVANA MARIELA | EZ23: PINARGOTE VASQUEZ NANCY FABIOLA | FA23: REYES VELEZ PEDRO ENRIQUE | FB23: SAN ANDRES HORMAZA DALLAS CECILIA | FC23: SORNOZA ZAMORA JUAN CARLOS | FD23: TOMALA PINTO JESUS JACINTO | FE23: VALLE JARAMILLO SILVIA ARACELY | FF23: VELÁSQUEZ BRAVO IRMA KATHERINE | FG23: VELEZ MENDOZA LAYSY VALERIA | FH23: VINUEZA TELLO SHIRLEY ELIZABETH | FI23: ZAMBRANO ALCIVAR NILDA ISABEL | FJ23: ZAMBRANO LOOR RITA MAYDA | FK23: ZAMBRANO VERA MONICA JANETH | FL23: VERA DELGADO BRYAN ADRIÁN | FM23: MORAN GONZALES DAVID RENATO | FN23: 0
... A602: {=TRANSPOSE(_xlfn.UNIQUE(_xlfn._xlws.FILTER(MAE_ASIGNATURA[ID_NIVEL],MAE_ASIGNATURA[ID_CARRERA]=ASIGNACION!$C602,"No existe información")))} -> No existe información | S602: {=TRANSPOSE(_xlfn.UNIQUE(_xlfn._xlws.FILTER(MAE_ASIGNATURA[NOM_ASIG],(MAE_ASIGNATURA[ID_NIVEL]=ASIGNACION!$D602)*(MAE_ASIGNATURA[ID_CARRERA]=ASIGNACION!$C602),"No existe información")))} -> No existe información | BD602: {=TRANSPOSE(_xlfn.UNIQUE(_xlfn._xlws.FILTER(DET_ASIG[DETALLADO],(DET_ASIG[ID_CARRERA]=ASIGNACION!$C602)*(DET_ASIG[NIVEL]=ASIGNACION!$D602)*(DET_ASIG[ID_ASIG]=ASIGNACION!$G602),"No existe información")))} -> No existe información | BQ602: {=IFERROR( TRANSPOSE( _xlfn.UNIQUE( _xlfn._xlws.FILTER(MAESTRIA_DETALLADO[MAESTRIA], ISNUMBER(MATCH(MAESTRIA_DETALLADO[CAMPO_DETALLADO], BD602:BP602,0)) ) ) ),IF(BD602="ACTIVIDAD","DOCENCIA",""))} | EA602: {=IF( ASIGNACION!I602="SI", IFERROR( TRANSPOSE( _xlfn.UNIQUE( _xlfn._xlws.FILTER(EDU_DOCENTE[NOMBRE_DOCENTE], ISNUMBER(MATCH(EDU_DOCENTE[MAESTRIA], BQ602:DY602,0)) ) ) ), "" ), TRANSPOSE( _xlfn.UNIQUE(EDU_DOCENTE[NOMBRE_DOCENTE] ) ) )} -> ALCIVAR CEDEÑO BEATRIZ ISABEL | EB602: ALCIVAR VERA GEMA MICHELLE | EC602: ARAUZ CHAVEZ MARIO ROBERTO | ED602: BAILON LOURIDO WALTER ALBERTO | EE602: CALDERERO VILLAGOMEZ ERICK ANTONIO | EF602: CASTILLO GARCIA PAOLA GERMANIA | EG602: CEDEÑO CHOEZ PEDRO JAVIER | EH602: CEVALLOS HOPPE JUAN CARLOS | EI602: DELGADO CHAVEZ MARIA IRASEMA | EJ602: DUARTE VALENCIA CRISTHIAN DARIO | EK602: FORTTY BARBERAN DENNY ALEXANDER | EL602: GUTIERREZ ZAMBRANO CARMEN EBELINA | EM602: INTRIAGO MOLINA GEMA VALERIA | EN602: LINO VELEZ LEONEL LIVINGTON | EO602: LOOR ALCIVAR MARIA ILIANA | EP602: LOOR MIELES TANIA JACQUELINE | EQ602: LOOR SOLORZANO ROSA MARIA | ER602: LOPEZ DELGADO RONALD MAURICIO | ES602: MACIAS VALENCIA DAVID GABRIEL | ET602: MENDOZA ZAMORA WALTER MANUEL | EU602: MOLINA CEVALLOS MARIA LORENA | EV602: MURILLO DELGADO ISAAC GABRIEL | EW602: ANGULO MURILLO NAVIRA GISSELA | EX602: OCHOA SOLEDISPA NESTOR IVAN | EY602: PARRAGA FRANCO SILVANA MARIELA | EZ602: PINARGOTE VASQUEZ NANCY FABIOLA | FA602: REYES VELEZ PEDRO ENRIQUE | FB602: SAN ANDRES HORMAZA DALLAS CECILIA | FC602: SORNOZA ZAMORA JUAN CARLOS | FD602: TOMALA PINTO JESUS JACINTO | FE602: VALLE JARAMILLO SILVIA ARACELY | FF602: VELÁSQUEZ BRAVO IRMA KATHERINE | FG602: VELEZ MENDOZA LAYSY VALERIA | FH602: VINUEZA TELLO SHIRLEY ELIZABETH | FI602: ZAMBRANO ALCIVAR NILDA ISABEL | FJ602: ZAMBRANO LOOR RITA MAYDA | FK602: ZAMBRANO VERA MONICA JANETH | FL602: VERA DELGADO BRYAN ADRIÁN | FM602: MORAN GONZALES DAVID RENATO | FN602: 0
BQ603: {=IFERROR( TRANSPOSE( _xlfn.UNIQUE( _xlfn._xlws.FILTER(MAESTRIA_DETALLADO[MAESTRIA], ISNUMBER(MATCH(MAESTRIA_DETALLADO[CAMPO_DETALLADO], BD603:BP603,0)) ) ) ),IF(BD603="ACTIVIDAD","DOCENCIA",""))}
BQ604: {=IFERROR( TRANSPOSE( _xlfn.UNIQUE( _xlfn._xlws.FILTER(MAESTRIA_DETALLADO[MAESTRIA], ISNUMBER(MATCH(MAESTRIA_DETALLADO[CAMPO_DETALLADO], BD604:BP604,0)) ) ) ),IF(BD604="ACTIVIDAD","DOCENCIA",""))}
BQ605: {=IFERROR( TRANSPOSE( _xlfn.UNIQUE( _xlfn._xlws.FILTER(MAESTRIA_DETALLADO[MAESTRIA], ISNUMBER(MATCH(MAESTRIA_DETALLADO[CAMPO_DETALLADO], BD605:BP605,0)) ) ) ),IF(BD605="ACTIVIDAD","DOCENCIA",""))}
BQ606: {=IFERROR( TRANSPOSE( _xlfn.UNIQUE( _xlfn._xlws.FILTER(MAESTRIA_DETALLADO[MAESTRIA], ISNUMBER(MATCH(MAESTRIA_DETALLADO[CAMPO_DETALLADO], BD606:BP606,0)) ) ) ),IF(BD606="ACTIVIDAD","DOCENCIA",""))}
BQ607: {=IFERROR( TRANSPOSE( _xlfn.UNIQUE( _xlfn._xlws.FILTER(MAESTRIA_DETALLADO[MAESTRIA], ISNUMBER(MATCH(MAESTRIA_DETALLADO[CAMPO_DETALLADO], BD607:BP607,0)) ) ) ),IF(BD607="ACTIVIDAD","DOCENCIA",""))}
BQ608: {=IFERROR( TRANSPOSE( _xlfn.UNIQUE( _xlfn._xlws.FILTER(MAESTRIA_DETALLADO[MAESTRIA], ISNUMBER(MATCH(MAESTRIA_DETALLADO[CAMPO_DETALLADO], BD608:BP608,0)) ) ) ),IF(BD608="ACTIVIDAD","DOCENCIA",""))}
BQ609: {=IFERROR( TRANSPOSE( _xlfn.UNIQUE( _xlfn._xlws.FILTER(MAESTRIA_DETALLADO[MAESTRIA], ISNUMBER(MATCH(MAESTRIA_DETALLADO[CAMPO_DETALLADO], BD609:BP609,0)) ) ) ),IF(BD609="ACTIVIDAD","DOCENCIA",""))}
BQ610: {=IFERROR( TRANSPOSE( _xlfn.UNIQUE( _xlfn._xlws.FILTER(MAESTRIA_DETALLADO[MAESTRIA], ISNUMBER(MATCH(MAESTRIA_DETALLADO[CAMPO_DETALLADO], BD610:BP610,0)) ) ) ),IF(BD610="ACTIVIDAD","DOCENCIA",""))}
BQ611: {=IFERROR( TRANSPOSE( _xlfn.UNIQUE( _xlfn._xlws.FILTER(MAESTRIA_DETALLADO[MAESTRIA], ISNUMBER(MATCH(MAESTRIA_DETALLADO[CAMPO_DETALLADO], BD611:BP611,0)) ) ) ),IF(BD611="ACTIVIDAD","DOCENCIA",""))}
BQ612: {=IFERROR( TRANSPOSE( _xlfn.UNIQUE( _xlfn._xlws.FILTER(MAESTRIA_DETALLADO[MAESTRIA], ISNUMBER(MATCH(MAESTRIA_DETALLADO[CAMPO_DETALLADO], BD612:BP612,0)) ) ) ),IF(BD612="ACTIVIDAD","DOCENCIA",""))}
BQ613: {=IFERROR( TRANSPOSE( _xlfn.UNIQUE( _xlfn._xlws.FILTER(MAESTRIA_DETALLADO[MAESTRIA], ISNUMBER(MATCH(MAESTRIA_DETALLADO[CAMPO_DETALLADO], BD613:BP613,0)) ) ) ),IF(BD613="ACTIVIDAD","DOCENCIA",""))}
BQ614: {=IFERROR( TRANSPOSE( _xlfn.UNIQUE( _xlfn._xlws.FILTER(MAESTRIA_DETALLADO[MAESTRIA], ISNUMBER(MATCH(MAESTRIA_DETALLADO[CAMPO_DETALLADO], BD614:BP614,0)) ) ) ),IF(BD614="ACTIVIDAD","DOCENCIA",""))}
... BQ637: {=IFERROR( TRANSPOSE( _xlfn.UNIQUE( _xlfn._xlws.FILTER(MAESTRIA_DETALLADO[MAESTRIA], ISNUMBER(MATCH(MAESTRIA_DETALLADO[CAMPO_DETALLADO], BD637:BP637,0)) ) ) ),IF(BD637="ACTIVIDAD","DOCENCIA",""))}

Sheet MAE_CONOCIMIENTO
A1: ID_DDETALLADO | B1: CAMPO_DETALLADO
A2: F-C-D-ADM | B2: ADMINISTRACIÓN
A3: F-C-D-ADM-EN -E-C | B3: ADMINISTRACIÓN EN E-COMMERCE
A4: F-C-D-AUD-DE -TEC | B4: AUDITORÍA DE TECNOLOGÍAS
A5: F-C-D-BIB-DOC | B5: BIBLIOTECOLOGÍA, DOCUMENTACIÓN Y ARCHIVOLOGÍA
A6: F-C-D-CIE-COM | B6: CIENCIAS COMPUTACIONALES
A7: F-C-D-CIE-DEL-MED | B7: CIENCIAS DEL MEDIO AMBIENTE
A8: F-C-D-CIE-POL | B8: CIENCIAS POLÍTICAS
A9: F-C-D-COM | B9: COMERCIO
A10: F-C-D-COM-Y N-NEG | B10: COMERCIO Y NEGOCIOS INTERNACIONAL
A11: F-C-D-COM-LAB | B11: COMPETENCIAS LABORALES
A12: F-C-D-CON-Y A-AUD | B12: CONTABILIDAD Y AUDITORÍA
... A33: F-C-D-GES-AMB | B33: GESTIÓN AMBIENTAL
A34: F-C-D-
A35: F-C-D-
A36: F-C-D-
A37: F-C-D-

Sheet MAE_CARRERA
A1: ID_CARRERA | B1: NOMBRE_CARRERA | C1: SEMANAS | D1: TOTAL HORAS | E1: FECHA_INICIO | F1: FECHA_FIN | G1: ESTADO
A2: FCACC-AD-EM | B2: ADMINISTRACIÓN DE EMPRESAS | C2: 16 | D2: 240 | E2: 43831 | F2: 51501 | G2: Vigente
A3: FCACC-AU-CO-GE | B3: AUDITORÍA Y CONTROL DE GESTIÓN 2024 NS | C3: 16 | D3: 240 | E3: 43831 | F3: 51501 | G3: Vigente
A4: FCACC-BI-RA | B4: BIENES RAICES | C4: 16 | D4: 240 | E4: 43831 | F4: 51501 | G4: Vigente
A5: FCACC-CO-EX | B5: COMERCIO EXTERIOR | C5: 16 | D5: 240 | E5: 43831 | F5: 51501 | G5: Vigente
A6: FCACC-CO-AD | B6: CONTABILIDAD Y AUDITORÍA 2024 NS | C6: 16 | D6: 240 | E6: 43831 | F6: 51501 | G6: Vigente
A7: FCACC-FINA | B7: FINANZAS 2024 NS | C7: 16 | D7: 240 | E7: 43831 | F7: 51501 | G7: Vigente
A8: FCACC-GE-IN-GE | B8: GESTION DE LA INFORMACIÓN GERENCIA - 2024 | C8: 16 | D8: 240 | E8: 43831 | F8: 51501 | G8: Vigente
A9: FCACC-GE-TA-HU | B9: GESTIÓN DEL TALENTO HUMANO | C9: 16 | D9: 240 | E9: 43831 | F9: 51501 | G9: Vigente
A10: FCACC-MA | B10: MARKETING | C10: 16 | D10: 240 | E10: 43831 | F10: 51501 | G10: Vigente
A11: FCACC-1-DO-CL | B11: 1. Docencia - Clases | C11: 1 | D11: 1 | E11: 43831 | F11: 51501 | G11: Vigente
A12: FCACC-5-DO-PE-IN | B12: 5. Docencia - Uso pedagógico de la investigación | C12: 1 | D12: 1 | E12: 43831 | F12: 51501 | G12: Vigente
A13: FCACC-4-DO-TU-TI | B13: 4. Docencia - Tutoría de titulación | C13: 1 | D13: 1 | E13: 43831 | F13: 51501 | G13: Vigente
... A18: FCACC-8-TITU | B18: Titulación | C18: 1 | D18: 1 | E18: 43831 | F18: 51501 | G18: Vigente

Sheet MDOCENTES
A1: ID_DOCENTE | B1: DATOS_DOCENTE | C1: UNIDAD | D1: CORREO | E1: CELULAR | F1: ESTUDIO | G1: DEDICACION | H1: Modalidad_TH | I1: TIPO SANGRE
A2: 1306927581 | B2: ALARCON CHAVEZ CESAR RAUL | C2: ADMINISTRACION DE EMPRESA | D2: cesar.alarcon@uleam.edu.ec | E2: 993841367 | F2: MAESTRÍA | G2: TC | H2: NOMBRAMIENTO
A3: 1309867008 | B3: ALCIVAR MERO MARIA JESSENIA | C3: ADMINISTRACION DE EMPRESA | D3: mariaj.alcivar@uleam.edu.ec | E3: 958996963 | F3: MAESTRÍA | G3: TC | H3: NOMBRAMIENTO
A4: 1312179292 | B4: ALVIA TOALA DAHIANA VALERIA | C4: ADMINISTRACION DE EMPRESA | D4: dahiana.alvia@uleam.edu.ec | E4: 995613221 | F4: MAESTRÍA | G4: TC | H4: NOMBRAMIENTO
A5: 1308397239 | B5: BALSECA MACIAS PAOLA ESTEFANIA | C5: ADMINISTRACION DE EMPRESA | D5: paola.balseca@uleam.edu.ec | E5: 980882709 | F5: MAESTRÍA | G5: TC | H5: NOMBRAMIENTO
A6: 1306327394 | B6: BAYAS ZAMBRANO CARMEN MARIETA | C6: ADMINISTRACION DE EMPRESA | D6: carmen.bayas@uleam.edu.ec | E6: 999471287 | F6: MAESTRÍA | G6: TC | H6: NOMBRAMIENTO
A7: 917967226 | B7: CACERES LARREATEGUI ALBA LUCIA | C7: ADMINISTRACION DE EMPRESA | D7: alba.caceres@uleam.edu.ec | E7: 999853757 | F7: MAESTRÍA | G7: TC | H7: NOMBRAMIENTO
A8: 1310729676 | B8: CALDERON ZAMORA OSCAR XAVIER | C8: ADMINISTRACION DE EMPRESA | D8: oscar.calderon@uleam.edu.ec | E8: 998862735 | F8: MAESTRÍA | G8: TC | H8: NOMBRAMIENTO
A9: 1311435968 | B9: CANO LARA EVELYN DYANN | C9: ADMINISTRACION DE EMPRESA | D9: evelyn.cano@uleam.edu.ec | E9: 992720628 | F9: DOCTORADO | G9: TC | H9: NOMBRAMIENTO
A10: 1712981735 | B10: CEVALLOS ENRIQUEZ RODRIGO PAUL | C10: ADMINISTRACION DE EMPRESA | D10: rodrigo.cevallos@uleam.edu.ec | E10: 987923175 | F10: DOCTORADO | G10: MT | H10: NOMBRAMIENTO
A11: 922028709 | B11: CRUZ MERA RAFER HENRY | C11: ADMINISTRACION DE EMPRESA | D11: rafer.cruz@uleam.edu.ec | E11: 999523745 | F11: DOCTORADO | G11: TC | H11: NOMBRAMIENTO
A12: 1307818615 | B12: FRANCO CHAVEZ MONICA ALEXANDRA | C12: ADMINISTRACION DE EMPRESA | D12: monica.franco@uleam.edu.ec | E12: 958604495 | F12: MAESTRÍA | G12: TC | H12: CONTRATOS OCASIONALES
A13: 1310022536 | B13: FRANCO RODRIGUEZ LUIS ENRIQUE | C13: ADMINISTRACION DE EMPRESA | D13: luise.franco@uleam.edu.ec | E13: 939933873 | F13: MAESTRÍA | G13: MT | H13: CONTRATOS OCASIONALES
... A133: 1311778458 | B133: CARRILLO PICO FEDERICO AVELINO | C133: MERCADOTECNIA | D133: avelino.carrillo@uleam.eud.ec | E133: 991942979 | F133: MAESTRÍA | G133: TC | H133: NOMBRAMIENTO
A134: 912379716 | B134: MORAN GONZALES DAVID RENATO | C134: ADMINISTRACIÓN DE EMPRESA | F134: MAESTRÍA | G134: MT | H134: CONTRATOS OCASIONALES
A135: 1312319641 | B135: VERA DELGADO BRYAN ADRIÁN | C135: CONTABILIDAD Y AUDITORIA | F135: MAESTRÍA | G135: TC | H135: CONTRATOS OCASIONALES

Sheet MAE_ASIGNATURA
A1: ID_ASIG | B1: NOM_ASIG | C1: HORAS | D1: semanas | E1: ID_CARRERA | F1: NOMBRE_CARRERA | G1: ID_NIVEL
A2: FCACC-AD-EM-NI-1-CONTA-DE -COS | B2: CONTABILIDAD DE COSTOS | C2: 4 | D2: 16 | E2: FCACC-AD-EM | F2: ADMINISTRACIÓN DE EMPRESAS | G2: 1
A3: FCACC-AD-EM-NI-1-MATEM-APL-A L | B3: MATEMÁTICA APLICADA A LA ADMINISTRACIÓN | C3: 4 | D3: 16 | E3: FCACC-AD-EM | F3: ADMINISTRACIÓN DE EMPRESAS | G3: 1
A4: FCACC-AD-EM-NI-1-ADMIN-PAR-LOS | B4: ADMINISTRACIÓN PARA LOS NEGOCIOS | C4: 4 | D4: 16 | E4: FCACC-AD-EM | F4: ADMINISTRACIÓN DE EMPRESAS | G4: 1
A5: FCACC-AD-EM-NI-1-METOD-DE -LA | B5: METODOLOGÍA DE LA INVESTIGACIÓN | C5: 4 | D5: 16 | E5: FCACC-AD-EM | F5: ADMINISTRACIÓN DE EMPRESAS | G5: 1
A6: FCACC-AD-EM-NI-1-MICRO | B6: MICROECONOMÍA | C6: 4 | D6: 16 | E6: FCACC-AD-EM | F6: ADMINISTRACIÓN DE EMPRESAS | G6: 1
A7: FCACC-AD-EM-NI-2-CONTA-FIN | B7: CONTABILIDAD FINANCIERA | C7: 3 | D7: 16 | E7: FCACC-AD-EM | F7: ADMINISTRACIÓN DE EMPRESAS | G7: 2
A8: FCACC-AD-EM-NI-2-MATEM-FIN | B8: MATEMÁTICA FINANCIERA | C8: 4 | D8: 16 | E8: FCACC-AD-EM | F8: ADMINISTRACIÓN DE EMPRESAS | G8: 2
A9: FCACC-AD-EM-NI-2-ADMIN-EST | B9: ADMINISTRACIÓN ESTRATÉGICA | C9: 4 | D9: 16 | E9: FCACC-AD-EM | F9: ADMINISTRACIÓN DE EMPRESAS | G9: 2
A10: FCACC-AD-EM-NI-2-ESTAD-APL-A | B10: ESTADÍSTICA APLICADA A LA ADMINISTRACIÓN | C10: 3 | D10: 16 | E10: FCACC-AD-EM | F10: ADMINISTRACIÓN DE EMPRESAS | G10: 2
A11: FCACC-AD-EM-NI-2-MACRO | B11: MACROECONOMÍA | C11: 3 | D11: 16 | E11: FCACC-AD-EM | F11: ADMINISTRACIÓN DE EMPRESAS | G11: 2
A12: FCACC-AD-EM-NI-2-DEREC-MER-Y S | B12: DERECHO MERCANTIL Y SOCIETARIO | C12: 3 | D12: 16 | E12: FCACC-AD-EM | F12: ADMINISTRACIÓN DE EMPRESAS | G12: 2
A13: FCACC-AD-EM-NI-3-CREAT-E I-INN | B13: CREATIVIDAD E INNOVACIÓN EMPRESARIAL | C13: 4 | D13: 16 | E13: FCACC-AD-EM | F13: ADMINISTRACIÓN DE EMPRESAS | G13: 3
... A339: FCACC-8-PRAC-NI-70-Pre-p | B339: Pre-profesionales | C339: 1 | D339: 16 | E339: FCACC-8-PRAC | F339: Prácticas | G339: 70

Sheet MAESTRIA_DETALLADO
A1: ID_DET_MAEST | B1: MAESTRIA | C1: ID_MAESTRIA | D1: CAMPO_DETALLADO | E1: ID_DETALLADO
A2: FCAC-DET-MAES-01 | B2: DOCTOR DENTRO DEL PROGRAMA DE DOCTORADO EN CIENCIAS SOCIALES Y JURÍDICAS | C2: MAES-DOC-DOC-DEN-DEL | D2: DERECHO | E2: F-C-D-DER
A3: FCAC-DET-MAES-02 | B3: DOCTOR EN CIENCIAS SOCIALES MENCIÓN GERENCIA | C3: MAES-DOC-DOC-EN -CIE | D3: ADMINISTRACIÓN | E3: F-C-D-ADM
A4: FCAC-DET-MAES-03 | B4: MAESTRIA EN ALTA DIRECCIÓN (MBA) | C4: MAES-DOC-MAE-EN -ALT | D4: ADMINISTRACIÓN | E4: F-C-D-ADM
A5: FCAC-DET-MAES-04 | B5: MAGISTER EJECUTIVO EN INFORMATICA DE GESTIÓN Y NUEVAS TECNOLOGÍAS | C5: MAES-DOC-MAG-EJE-EN | D5: DESARROLLO Y ANÁLISIS DE SOFTWARE Y APLICACIONES | E5: F-C-D-DES-Y A-ANÁ
A6: FCAC-DET-MAES-05 | B6: MAGISTER EN ADMINISTRACIÓN DE EMPRESAS | C6: MAES-DOC-MAG-EN -ADM | D6: ADMINISTRACIÓN | E6: F-C-D-ADM
A7: FCAC-DET-MAES-06 | B7: MAGISTER EN ADMINISTRACIÓN DE EMPRESAS CON MENCIÓN EN MARKETING | C7: MAES-DOC-MAG-EN -ADM | D7: ADMINISTRACIÓN | E7: F-C-D-ADM
A8: FCAC-DET-MAES-07 | B8: MAGISTER EN ADMINISTRACIÓN DE EMPRESAS CON MENCIÓN EN MARKETING | C8: MAES-DOC-MAG-EN -ADM | D8: MARKETING Y PUBLICIDAD | E8: F-C-D-MAR-Y P-PUB
A9: FCAC-DET-MAES-08 | B9: MAGISTER EN ADMINISTRACIÓN DE EMPRESAS MENCIÓN DIRECCIÓN FINANCIERA | C9: MAES-DOC-MAG-EN -ADM | D9: ADMINISTRACIÓN | E9: F-C-D-ADM
A10: FCAC-DET-MAES-09 | B10: MAGISTER EN ADMINISTRACIÓN DE EMPRESAS MENCIÓN DIRECCIÓN FINANCIERA | C10: MAES-DOC-MAG-EN -ADM | D10: GESTIÓN FINANCIERA | E10: F-C-D-GES-FIN
A11: FCAC-DET-MAES-10 | B11: MAGISTER EN ADMINISTRACIÓN DE EMPRESAS MENCIÓN EN GESTIÓN DE RECURSOS HUMANOS | C11: MAES-DOC-MAG-EN -ADM | D11: ADMINISTRACIÓN | E11: F-C-D-ADM
A12: FCAC-DET-MAES-11 | B12: MAGISTER EN ADMINISTRACIÓN DE EMPRESAS MENCIÓN NEGOCIOS INTERNACIONALES | C12: MAES-DOC-MAG-EN -ADM | D12: ADMINISTRACIÓN | E12: F-C-D-ADM
... A44: FCAC-DET-MAES-43 | B44: MASTER UNIVERSITARIO EN DIRECCIÓN Y GESTIÓN DE RECURSOS HUMANOS | C44: MAES-DOC-MAS-UNI-EN | D44: ADMINISTRACIÓN | E44: F-C-D-ADM
A45: FCAC-DET-MAES-46 | C45: Seleccione Maestria | E45: F-C-D-
A46: FCAC-DET-MAES-47 | C46: Seleccione Maestria | E46: F-C-D-
A47: FCAC-DET-MAES-48 | C47: Seleccione Maestria | E47: F-C-D-
A48: FCAC-DET-MAES-49 | C48: Seleccione Maestria | E48: F-C-D-
A49: FCAC-DET-MAES-50 | C49: Seleccione Maestria | E49: F-C-D-
A50: FCAC-DET-MAES-51 | C50: Seleccione Maestria | E50: F-C-D-
A51: FCAC-DET-MAES-52 | C51: Seleccione Maestria | E51: F-C-D-
A52: FCAC-DET-MAES-53 | C52: Seleccione Maestria | E52: F-C-D-
A53: FCAC-DET-MAES-54 | C53: Seleccione Maestria | E53: F-C-D-
A54: FCAC-DET-MAES-55 | C54: Seleccione Maestria | E54: F-C-D-
A55: FCAC-DET-MAES-56 | C55: Seleccione Maestria | E55: F-C-D-
A56: FCAC-DET-MAES-57 | C56: Seleccione Maestria | E56: F-C-D-
... A598: FCAC-DET-MAES-599 | C598: Seleccione Maestria | E598: F-C-D-

Sheet EDU_DOCENTE
A1: ID_NIVE_DOC | B1: NOMBRE_DOCENTE | C1: IDENTIFICACION | D1: MAESTRIA | E1: VALIDACION | F1: ID_MAESRIA
A2: FCACC-RED-01 | B2: ALCIVAR CEDEÑO BEATRIZ ISABEL | C2: 1307077220 | D2: MAGISTER EN CONTABILIDAD Y AUDITORÍA | F2: MAES-DOC-MAG-EN -CON
A3: FCACC-RED-02 | B3: ALCIVAR VERA GEMA MICHELLE | C3: 1313436188 | D3: MAGISTER EN PEDAGOGÍA DE LOS IDIOMAS NACIONALES Y EXTRANJEROS MENCIÓN EN ENSEÑANZA DEL INGLÉS | F3: MAES-DOC-MAG-EN -PED
A4: FCACC-RED-03 | B4: ARAUZ CHAVEZ MARIO ROBERTO | C4: 1308294501 | D4: MAGISTER EJECUTIVO EN INFORMATICA DE GESTIÓN Y NUEVAS TECNOLOGÍAS | F4: MAES-DOC-MAG-EJE-EN
A5: FCACC-RED-04 | B5: BAILON LOURIDO WALTER ALBERTO | C5: 1304764002 | D5: MAGISTER EN FINANZAS Y COMERCIO INTERNACIONAL | F5: MAES-DOC-MAG-EN -FIN
A6: FCACC-RED-05 | B6: BAILON LOURIDO WALTER ALBERTO | C6: 1304764002 | D6: MAGISTER EN AUDITORÍA DE TECNOLOGÍAS DE LA INFORMACIÓN | F6: MAES-DOC-MAG-EN -AUD
A7: FCACC-RED-06 | B7: CALDERERO VILLAGOMEZ ERICK ANTONIO | C7: 911662674 | D7: MAESTRIA EN ALTA DIRECCIÓN (MBA) | F7: MAES-DOC-MAE-EN -ALT
A8: FCACC-RED-07 | B8: CALDERERO VILLAGOMEZ ERICK ANTONIO | C8: 911662674 | D8: MAGISTER EN ADMINISTRACIÓN DE EMPRESAS MENCIÓN NEGOCIOS INTERNACIONALES | F8: MAES-DOC-MAG-EN -ADM
A9: FCACC-RED-08 | B9: CASTILLO GARCIA PAOLA GERMANIA | C9: 1309751582 | D9: MAGISTER EN TRIBUTACIÓN Y FINANZAS | F9: MAES-DOC-MAG-EN -TRI
A10: FCACC-RED-09 | B10: CASTILLO GARCIA PAOLA GERMANIA | C10: 1309751582 | D10: DOCTOR EN CIENCIAS SOCIALES MENCIÓN GERENCIA | F10: MAES-DOC-DOC-EN -CIE
A11: FCACC-RED-10 | B11: CEDEÑO CHOEZ PEDRO JAVIER | C11: 1309499521 | D11: MAGISTER EN AUDITORÍA INTEGRAL | F11: MAES-DOC-MAG-EN -AUD
A12: FCACC-RED-11 | B12: CEVALLOS HOPPE JUAN CARLOS | C12: 1306306000 | D12: MAGISTER EN EDUCACIÓN SUPERIOR | F12: MAES-DOC-MAG-EN -EDU
A13: FCACC-RED-12 | B13: DELGADO CHAVEZ MARIA IRASEMA | C13: 1305904797 | D13: MAGISTER EN TRIBUTACIÓN Y FINANZAS | F13: MAES-DOC-MAG-EN -TRI
... A54: FCACC-RED-57 | B54: MORAN GONZALES DAVID RENATO | C54: 912379716 | D54: MAGISTER EN GESTIÓN DE PROYECTOS | F54: MAES-DOC-MAG-EN -GES
A55: FCACC-RED-58 | C55: Seleccione Docente | F55: Seleccione Maestria
A56: FCACC-RED-59 | C56: Seleccione Docente | F56: Seleccione Maestria
A57: FCACC-RED-60 | C57: Seleccione Docente | F57: Seleccione Maestria
A58: FCACC-RED-61 | C58: Seleccione Docente | F58: Seleccione Maestria
A59: FCACC-RED-62 | C59: Seleccione Docente | F59: Seleccione Maestria
A60: FCACC-RED-63 | C60: Seleccione Docente | F60: Seleccione Maestria
A61: FCACC-RED-64 | C61: Seleccione Docente | F61: Seleccione Maestria
A62: FCACC-RED-65 | C62: Seleccione Docente | F62: Seleccione Maestria
A63: FCACC-RED-66 | C63: Seleccione Docente | F63: Seleccione Maestria
A64: FCACC-RED-67 | C64: Seleccione Docente | F64: Seleccione Maestria
A65: FCACC-RED-68 | C65: Seleccione Docente | F65: Seleccione Maestria
A66: FCACC-RED-69 | C66: Seleccione Docente | F66: Seleccione Maestria
... A489: FCACC-RED-492 | C489: Seleccione Docente | F489: Seleccione Maestria

Sheet DET_ASIG
A1: ID_ASIG_CAM_DET | B1: ID_CARRERA | C1: NOMBRE_CARRERA | D1: NIVEL | E1: ASIGNATURA | F1: ID_ASIG | G1: DETALLADO | H1: ID_DETALLADO
A2: 1 | B2: FCACC-CO-AD | C2: CONTABILIDAD Y AUDITORÍA 2024 NS | D2: 1 | E2: CONTABILIDAD BÁSICA | F2: FCACC-CO-AD-NI-1-CONTA-BÁS | G2: UNIDAD BASICA | H2: F-C-D-UNI-BAS
A3: 2 | B3: FCACC-CO-AD | C3: CONTABILIDAD Y AUDITORÍA 2024 NS | D3: 1 | E3: MATEMÁTICA | F3: FCACC-CO-EX-NI-1-MATEM | G3: UNIDAD BASICA | H3: F-C-D-UNI-BAS
A4: 3 | B4: FCACC-CO-AD | C4: CONTABILIDAD Y AUDITORÍA 2024 NS | D4: 1 | E4: METODOLOGÍA DE LA INVESTIGACIÓN | F4: FCACC-AD-EM-NI-1-METOD-DE -LA | G4: UNIDAD BASICA | H4: F-C-D-UNI-BAS
A5: 4 | B5: FCACC-CO-AD | C5: CONTABILIDAD Y AUDITORÍA 2024 NS | D5: 1 | E5: ADMINISTRACIÓN | F5: FCACC-CO-AD-NI-1-ADMIN | G5: UNIDAD BASICA | H5: F-C-D-UNI-BAS
A6: 5 | B6: FCACC-CO-AD | C6: CONTABILIDAD Y AUDITORÍA 2024 NS | D6: 2 | E6: LEGISLACIÓN LABORAL | F6: FCACC-AU-CO-GE-NI-2-LEGIS-LAB | G6: UNIDAD BASICA | H6: F-C-D-UNI-BAS
A7: 6 | B7: FCACC-CO-AD | C7: CONTABILIDAD Y AUDITORÍA 2024 NS | D7: 2 | E7: CONTABILIDAD INTERMEDIA | F7: FCACC-CO-AD-NI-2-CONTA-INT | G7: UNIDAD BASICA | H7: F-C-D-UNI-BAS
A8: 7 | B8: FCACC-CO-AD | C8: CONTABILIDAD Y AUDITORÍA 2024 NS | D8: 2 | E8: ESTADÍSTICA DESCRIPTIVA | F8: FCACC-AU-CO-GE-NI-1-ESTAD-DES | G8: UNIDAD BASICA | H8: F-C-D-UNI-BAS
A9: 8 | B9: FCACC-CO-AD | C9: CONTABILIDAD Y AUDITORÍA 2024 NS | D9: 2 | E9: LEGISLACIÓN MERCANTIL Y SOCIETARIA | F9: FCACC-CO-AD-NI-2-LEGIS-MER-Y | G9: UNIDAD BASICA | H9: F-C-D-UNI-BAS
A10: 9 | B10: FCACC-CO-AD | C10: CONTABILIDAD Y AUDITORÍA 2024 NS | D10: 2 | E10: MATEMÁTICA FINANCIERA | F10: FCACC-AD-EM-NI-2-MATEM-FIN | G10: UNIDAD BASICA | H10: F-C-D-UNI-BAS
A11: 10 | B11: FCACC-CO-AD | C11: CONTABILIDAD Y AUDITORÍA 2024 NS | D11: 3 | E11: CONTABILIDAD AVANZADA | F11: FCACC-CO-AD-NI-3-CONTA-AVA | G11: UNIDAD BASICA | H11: F-C-D-UNI-BAS
A12: 11 | B12: FCACC-CO-AD | C12: CONTABILIDAD Y AUDITORÍA 2024 NS | D12: 3 | E12: FUNDAMENTOS DE AUDITORÍA | F12: FCACC-CO-AD-NI-3-FUNDA-DE -AUD | G12: UNIDAD BASICA | H12: F-C-D-UNI-BAS
A13: 12 | B13: FCACC-CO-AD | C13: CONTABILIDAD Y AUDITORÍA 2024 NS | D13: 3 | E13: ESTADÍSTICA APLICADA | F13: FCACC-CO-AD-NI-3-ESTAD-APL | G13: UNIDAD BASICA | H13: F-C-D-UNI-BAS
... A28: 27 | B28: FCACC-8-PRAC | C28: Prácticas | D28: 70 | E28: Laborales | F28: FCACC-8-PRAC-NI-70-Labor | G28: ACTIVIDAD | H28: F-C-D-ACT
A29: 28 | C29: Seleccione ID Carrera | F29: Seleccione Asignatura | H29: F-C-D-
A30: 29 | C30: Seleccione ID Carrera | F30: Seleccione Asignatura | H30: F-C-D-
A31: 30 | C31: Seleccione ID Carrera | F31: Seleccione Asignatura | H31: F-C-D-
A32: 31 | C32: Seleccione ID Carrera | F32: Seleccione Asignatura | H32: F-C-D-
A33: 32 | C33: Seleccione ID Carrera | F33: Seleccione Asignatura | H33: F-C-D-
A34: 33 | C34: Seleccione ID Carrera | F34: Seleccione Asignatura | H34: F-C-D-
A35: 34 | C35: Seleccione ID Carrera | F35: Seleccione Asignatura | H35: F-C-D-
A36: 35 | C36: Seleccione ID Carrera | F36: Seleccione Asignatura | H36: F-C-D-
A37: 36 | C37: Seleccione ID Carrera | F37: Seleccione Asignatura | H37: F-C-D-
A38: 37 | C38: Seleccione ID Carrera | F38: Seleccione Asignatura | H38: F-C-D-
A39: 38 | C39: Seleccione ID Carrera | F39: Seleccione Asignatura | H39: F-C-D-
A40: 39 | C40: Seleccione ID Carrera | F40: Seleccione Asignatura | H40: F-C-D-
... A599: 598 | C599: Seleccione ID Carrera | F599: Seleccione Asignatura | H599: F-C-D-
A600: 599 | C600: Seleccione ID Carrera | E600: No existe información | F600: Seleccione Asignatura | H600: F-C-D-
